package me.rerere.matrix.internal;

import java.io.PrintWriter;
import java.io.UnsupportedEncodingException;
import java.math.BigInteger;
import java.security.MessageDigest;
import java.util.ArrayList;
import java.util.concurrent.ConcurrentHashMap;

public class av {
  private static int k;
  
  private static String a;
  
  private static String j;
  
  private static MessageDigest b;
  
  private static ConcurrentHashMap c;
  
  private static ConcurrentHashMap d;
  
  private static final boolean e = false;
  
  private static String f;
  
  private static ConcurrentHashMap g;
  
  private static ConcurrentHashMap h;
  
  private static final String x = "";
  
  private static PrintWriter writer;
  
  private static final String[] i;
  
  private static final String[] l;
  
  private static void a(ConcurrentHashMap paramConcurrentHashMap) {
    a(paramConcurrentHashMap, a(-17599, -31358));
    a(paramConcurrentHashMap, a(-17600, -17995));
  }
  
  private static void b(ConcurrentHashMap paramConcurrentHashMap) {}
  
  private static void c(ConcurrentHashMap paramConcurrentHashMap) {}
  
  private static void d(ConcurrentHashMap paramConcurrentHashMap) {}
  
  private static void e(ConcurrentHashMap paramConcurrentHashMap) {}
  
  private static void f(ConcurrentHashMap paramConcurrentHashMap) {}
  
  private static void g(ConcurrentHashMap paramConcurrentHashMap) {}
  
  private static void h(ConcurrentHashMap paramConcurrentHashMap) {}
  
  private static void i(ConcurrentHashMap paramConcurrentHashMap) {}
  
  private static void j(ConcurrentHashMap paramConcurrentHashMap) {}
  
  private static void k(ConcurrentHashMap paramConcurrentHashMap) {}
  
  private static void a(ConcurrentHashMap<BigInteger, String> paramConcurrentHashMap, String paramString) {
    int i = paramString.length();
    int j = 0;
    do {
      char c = paramString.charAt(j++);
      String str1 = paramString.substring(j, j + c);
      j += str1.length();
      c = paramString.charAt(j++);
      String str2 = paramString.substring(j, j + c);
      j += str2.length();
      paramConcurrentHashMap.put(new BigInteger(str2, 36), str1);
    } while (j < i);
  }
  
  public static String a(String paramString) {
    if (b == null)
      return paramString; 
    try {
      int i = paramString.lastIndexOf("[") + 1;
      String str1 = paramString.substring(i);
      if (i > 0 && str1.length() == 1)
        return paramString; 
      boolean bool1 = false;
      if (str1.charAt(0) == 'L' && str1.charAt(str1.length() - 1) == ';') {
        bool1 = true;
        str1 = str1.substring(1, str1.length() - 1);
      } 
      boolean bool2 = (str1.indexOf('.') > -1) ? true : false;
      if (bool2)
        str1 = str1.replace('.', '/'); 
      str1 = str1 + f;
      String str2 = b(str1);
      if (str2 != null) {
        if (bool2)
          str2 = str2.replace('/', '.'); 
        StringBuilder stringBuilder = new StringBuilder();
        for (byte b = 0; b < i; b++)
          stringBuilder.append('['); 
        if (bool1)
          stringBuilder.append('L'); 
        stringBuilder.append(str2);
        if (bool1)
          stringBuilder.append(';'); 
        return stringBuilder.toString();
      } 
      return paramString;
    } catch (Throwable throwable) {
      return paramString;
    } 
  }
  
  public static String b(String paramString, Class paramClass, Class[] paramArrayOfClass) {
    if (b == null || paramClass == null)
      return paramString; 
    try {
      String str1 = paramClass.getName();
      String str2 = str1.replace('.', '/');
      StringBuilder stringBuilder = new StringBuilder();
      stringBuilder.append(f);
      stringBuilder.append(paramString);
      stringBuilder.append(f);
      if (paramArrayOfClass != null && paramArrayOfClass.length > 0)
        for (byte b = 0; b < paramArrayOfClass.length; b++) {
          Class clazz = paramArrayOfClass[b];
          stringBuilder.append(a(clazz));
          stringBuilder.append(f);
        }  
      String str3 = stringBuilder.toString();
      String str4 = str2 + str3;
      String str5 = b(str4);
      if (str5 != null)
        return str5; 
      str5 = a(paramClass, str3);
      return (str5 != null) ? str5 : paramString;
    } catch (Throwable throwable) {
      return paramString;
    } 
  }
  
  public static String c(Class paramClass, String paramString) {
    if (b == null || paramClass == null)
      return paramString; 
    try {
      String str1 = paramClass.getName();
      String str2 = str1.replace('.', '/');
      StringBuilder stringBuilder = new StringBuilder();
      stringBuilder.append(f);
      stringBuilder.append(paramString);
      String str3 = stringBuilder.toString();
      String str4 = str2 + str3;
      String str5 = b(str4);
      if (str5 != null)
        return str5; 
      str5 = a(paramClass, str3);
      return (str5 != null) ? str5 : paramString;
    } catch (Throwable throwable) {
      return paramString;
    } 
  }
  
  private static String b(String paramString) {
    String str = (String)g.get(paramString);
    if (str == null && str != "") {
      b.reset();
      try {
        b.update(paramString.getBytes(j));
      } catch (UnsupportedEncodingException unsupportedEncodingException) {}
      byte[] arrayOfByte = b.digest();
      BigInteger bigInteger = new BigInteger(arrayOfByte);
      str = (String)c.get(bigInteger);
      if (str != null) {
        str = a(paramString, str);
        g.put(paramString, str);
      } else {
        g.put(paramString, "");
      } 
    } 
    return (str == "") ? null : str;
  }
  
  private static String a(String paramString1, String paramString2) {
    b.reset();
    byte[] arrayOfByte1 = null;
    try {
      arrayOfByte1 = (paramString1 + a).getBytes(j);
    } catch (UnsupportedEncodingException unsupportedEncodingException) {}
    b.update(arrayOfByte1);
    byte[] arrayOfByte2 = b.digest();
    char[] arrayOfChar = paramString2.toCharArray();
    StringBuilder stringBuilder = new StringBuilder(arrayOfChar.length);
    for (byte b = 0; b < arrayOfChar.length; b++) {
      byte b1;
      char c = arrayOfChar[b];
      if (b < arrayOfByte2.length - 1) {
        b1 = arrayOfByte2[b];
      } else {
        b1 = arrayOfByte2[b % arrayOfByte2.length];
      } 
      stringBuilder.append((char)(c ^ (char)b1));
    } 
    return stringBuilder.toString();
  }
  
  private static String a(Class paramClass, String paramString) {
    ArrayList<String> arrayList = b(paramClass);
    int i = arrayList.size();
    for (byte b = 0; b < i; b++) {
      String str1 = arrayList.get(b);
      String str2 = str1 + paramString;
      String str3 = b(str2);
      if (str3 != null)
        return str3; 
    } 
    return null;
  }
  
  private static String a(Class paramClass) {
    return d.containsKey(paramClass) ? (String)d.get(paramClass) : paramClass.getName().replace('.', '/');
  }
  
  private static ArrayList b(Class paramClass) {
    String str = paramClass.getName();
    ArrayList arrayList1 = (ArrayList)h.get(str);
    if (arrayList1 != null)
      return arrayList1; 
    ArrayList arrayList2 = new ArrayList();
    ConcurrentHashMap<Object, Object> concurrentHashMap = new ConcurrentHashMap<Object, Object>();
    b(paramClass, arrayList2, concurrentHashMap);
    h.put(str, arrayList2);
    return arrayList2;
  }
  
  private static void b(Class paramClass, ArrayList<String> paramArrayList, ConcurrentHashMap<Class<?>, Class<?>> paramConcurrentHashMap) {
    Class<?> clazz = paramClass.getSuperclass();
    if (clazz != null && !paramConcurrentHashMap.containsKey(clazz)) {
      paramArrayList.add(c(clazz));
      paramConcurrentHashMap.put(clazz, clazz);
      b(clazz, paramArrayList, paramConcurrentHashMap);
    } 
    Class[] arrayOfClass = paramClass.getInterfaces();
    for (byte b = 0; b < arrayOfClass.length; b++) {
      Class<?> clazz1 = arrayOfClass[b];
      if (!paramConcurrentHashMap.containsKey(clazz1)) {
        paramArrayList.add(c(clazz1));
        paramConcurrentHashMap.put(clazz1, clazz1);
        b(clazz1, paramArrayList, paramConcurrentHashMap);
      } 
    } 
  }
  
  private static String c(Class paramClass) {
    return paramClass.getName().replace('.', '/');
  }
  
  static {
    // Byte code:
    //   0: iconst_2
    //   1: anewarray java/lang/String
    //   4: astore #5
    //   6: iconst_0
    //   7: istore_3
    //   8: ldc 'Â§Â–Ã\\r!ÃŸ/Â¡AÂ¥ÂÃ…BPÂ˜Ãµ<Â¨Â‡1KÂ®Â®ÃÃ›d$ÃƒwÃ‡ÃªÃ™+Ã tÂÂ¬Â‡ÂÂ—Â¡Ã¤O>ÃÂ¿Ã´F7_Ã¬Ã¤Ã˜Â´Ã»Â°.Ã‚~ÃŠÂÃŒÃœFÃ3Ã©eÂ…ÂŸaÂ¹3vÃº.#Ã¿t*Ã­{Â­ÃœÃªÂ‡Â»Ã˜Â–Â»>ÃŠÃ‡>Ã—ÃšÂ¿Ã”Ã©ÃˆfÂ€jÂ”/Â™zÂ¬\\tÃ¼DIÂ­Â‡Ã‰ÃºÃ•Ã‘Ã€Â£Jy?Â¡Ã“LÂ¬Ãša;Â¦u&]Â®Ã¹7_5\\f:Ã·Âr.ÃÂÂ¿GÃ‚Â5Â²hÃ’Â>Â®?IÃ»Ã¸ÂÃ Âœ'beÂ®8Ã²Â·Ã”edÃ›4ï¾‘gPÂµÂ»ÃŠ=Ã¶Ã8cÂ­Â¾Â“\\fzÃ«Âi%\\nÂŒS?ÂˆÂÂ†FÂ¥ÃŒÂ¹ÃÂ°[Â±Ã¼Â—%Â‘RsÂ¥8Â´ÂªQÂ€=ÂÂ‰Ã‡ÃSS_qÂ¾>ÂÃ´Ã‹Ã¡Fe6FtÃa)ÃŸÂœÂœÂ‹Ã |OÃ£Â¤KÃÃ±\\nÂ—~Â¿Â˜Â¿Ã¥Âµ1ÂÂ´ï¿¢Ã‰Ãœ Ã‘KÃƒuK4Â…Ã¡}fÃ°Ãˆ]ÂªQ\\rÂˆ,Ã‡Ã˜12lLÂ°;Â¡)Â»(Ã­bÂˆFINpÂ’ÃªÃ¶Ã‡Â‹DÂ»UÂ†;Â‘doÃ²Â„ÃÃ•'LÃœrÃ•Ãªo=ÃeÃ½Ã«Ã‘ÂƒÃ°stÃ–VÃ¼1"x!"8Ã§ÃÃ›/j|ÃP7Â¸ï¼ÃšÂ…]Â³Â´Ã¯nÃÂÂÃ‚ 6wÃ¦Ã¿Ã¡$GÂ¦ÃµÃ¯Ã‘Â€]Ã»Ã¿yzÂ±Ã‡Hq`ÂÂ¨ÃºÃ¼>VqÂ‘Â‡Ã‰:Ã¯LÃ­$4M?Â¸ÂŠRÂŸ1Â”BÃ¶Ã‰Â»HA`Ã¨Â¬Ã¾Â£Ã“ÂˆÃAÃ¨Ã©eÃ¥Â¢Â–Â¤ÃÃƒ5ÂªÂÂ´Â½ï¼»EÂ‹HÃ`qgÃI!Â½=4Ã|NÂ¿L2Â“Â¸ÃŠÃ½Ã£tÂˆÃ¦]?Ã Ã¦{Ã²2Ã¤yÃ‡mÃ§Ã©Ã‡Ã†Ã­?HÂ‰ÃÃ¼"<ÃŸ#ÂˆÂƒÃY~fÃ¸Â¹ÃŸ+Â©BÃ¤Ã§WDÂ«HÃ—EÂ˜Âh[Â¡ÂªÃ¡Ã˜Ã)aÃ· Ã˜CDÂ£Â’f+5Ã¼Ã¹MÃ©Ã˜Â‰uFÃ‹F_Ã¾Â•Ã¨Â˜ÂŒrÃšqÃ¶ÂŒ_*;ipÃªÃ“Ã¢XÃ¯Â›Â¯Ã·Ã†\\tÂ¥Ã¿Â˜;Â‹; Ã‹Â¼Â…Â¡ÃÂšÂ´aÂ¡Ã"R$Â»+\\nÃ£Ãœ(dÃ«~Â•Â»UÂ¦3#`Ã¾_(Ã Ã¹}Ã@Â­"Ã‚PIxÂ±+Â¯"Ã¬GEÃ•ÃŸ\\nÂ¤Â©?Â¹kÂº[Â†Â¬k<ÂÂ¬Â³A@2+Â’\\bÃ½'Ã˜+sÂ·Â®[tÂ¾[5Ã”Â“Ã„ÃœÂ›Â“Â‹Ã—]ÃŒ>Ã›Ã‹Ã¦:#mKTiÃ0_ÂÃ­Â¨Â­Ã¢_ÂŠÃ¤ÃˆÂ¿ÂÂ¯3Â‰DWtqÃ¦Ã›\\th]Ã·{Â·lÃ§/Â”UHÃ›gÃ¼t&Â’Ã†ÂŒÃ™@ ÂÂ®aÃ²Â‚Â§Â‹Ã£\\rÂ¾AÂ“Ã^0Â€Ã­PÃŸ <ÂºZqlIÂ”.]UÃ¥Â…Ã¶Ã§Ã’ÃŒÃœÂ¬tÂ¹Ã©ÂŸÂ¹Â¨\\bÃŠNÃ°%Ã”\\fÃ±Â˜Â«odj(Ã½Ã½(FÂµ"Â·OkÃ¦[Ã“Â‹SEÃºhÂŒCrï½¹Ã§Ã¹8ÂŒÂ„ÃÃ¶DDÂÃ›d_Â.(Ã¬Ã\\rÃ¯0Mvc{ygÃ*Ã„IÃ‹Ã…j`S4YhEHÂŒÃƒÃ¿aÂ²|ÃŠ1~Â­ÂšÂ‘ÃÃ’uÃ‰*3Ã±#xÂCÂ€KcEÂŸXÂ—Ã½c\\tÃ´TÃÃ›ecÂ¾Ã¯ÂŸÃŒsuÂŠÃ½Â¡Âª8c*Ã¢ÂÂ¦ï¾¤Ã“0Â¾ÂÂ‘Ã Ã•Ã„$Ã·Ãµ\\nb'Ã­ÂœÂ«Â³ÃƒÃ˜Ã‹Â›rGÂ€Ã ÃºÃ…(qÃ\\nvxÂ°+Â›tnbÃ²Ã‡ÂzÃ‚Â½}Ã˜Ã¤Ã–Âœ;Ã³jÂ‚ÂÃ~Â­#Â‚MÃrÂ¿^}0ÃƒÂ¬6Ã´Â‘HÃ«#\:'Ã…Ã˜Ã•Â©Ãˆ?@ÃÂ^Ãï½…3ÃÃ¾:Ã†Â¬Ã»Â†EjdÃ¬Â…JÃ¯Ã©RÃ³$sÂ©Ã›Â‰Â‚UhÃ˜Ã¾|RÃƒsÃšÃ˜Â(#P VEWÃŠÃ°Ã¤Â¯Ã«I\\bBÃ®ÃªÂµÂºÃ‡=Â¯Ã¯JaeÂÃœÂ£Ã½Ã„Ã¦@i8[@Â„ÃŸ Ã¸Ã¢qÃ­;Ã…/Ã¸Â†ÃµÂ´Â—ÂœÃ°Ã¸jÂ“zÃ™BÂ±Ã¹>Â¶Â‰Â»Ã§<Ã»Â¹&Ã¤Âƒ&Ã¿ÂšÂ±Ã¦Â£_ÃˆÂƒÂ¹)Ã´Â„5ÃšÂºÂ”Ã¾Ã«ÃŒwW>Â›ÂÃµooÂŸ&Pp$Âª@`ÂŠÃ¨`ÂŠÃ¹()Â¼Ã•Â¸ÂŒDÃ°"W+F|ÂÂªÂ¹Ã½Ã¥Ã‡ÂœÃ™Â©ÃªFbvÂ£Ã˜"Ã•Â™)XÃ¼ÂÃÃÃ‹Ã¯ÃƒfÂ£ Ã§ÃÂ·Ã<f.Ã¨Ã¼qÂ–WÂ®Â“Â±ÃsÃ”Â“Ã”LÃÃ¶Ã¡ÂÂ„2Ã¬eJÃ±Ã¤Ã oÂœÃ¦.ÃÂ­ÂŒÂ—Â¡Â_Â†Â”ÃÂ“Â‰@)Â“'OÂ•M%qÂ™`||2Â€Â…Â›Â–BÃŸ0\\rÂ³Ã¥Â±ÂšÂ„ÂŸLï¾½Â¡ÂšueÂª!:+sÃ²Ã‹8ÃŒÂŸÃ°{DÃ™}$Ã¼Ã¥ÂÂª/ÂšyÂ¸Ã½Ã´3ÃºTdFXÂ¨Ã™^ÃÂ§-#Â™Ã¿FÃšÂ¬Ãš";JÃ®QÃÂ—Â§s!ÃªÂ‘ÃªÃ¯ixÂ¨yz\\fÂ­-Ã9Ã™Â˜Ã©,DÃ”ÃÃ—ÂˆÂšAGÂÂ™ÂºÂ”3Ã¤Ã³Â‰ÂMÂºq3{Ã’RÃ KÃ™Ãœ|\\tÃ¥pÂ‰a*ÂÃŒÃ Ã¦!5]cÃ½<a\\bÂ«zyÂ‚DgÂÃÂ®Â¦6Â¿{mÃ¬Ã†BÃ½Ã»7JÂ´xÂ›{&ÂŒÂ€Ã’38"Ã“Â‚Ã®Â–\Â²Â¨Ã­Â€&Â€Â“Ã¯Â”Â‘%zÃTUÃ™Ã¾ÃˆÃ¢ÂÃ‚<ï¿’Â€hÂ†Ã‚Â‘Ã‘iYÂ¼ÃXÂ„Ã¤Ã¦ Â­Â¢Ã„(lÂ˜<ÂÃ“Ã—ÂŒÃ¦Â®Ã“Â™0Ã¢8"ÂAÂ¥_u]Â°Â±\\rÂ1AÂ—.yÃIZÃ™ÂŒ4ÃÃ´Ã°\\bH>yÂÃª29Ã®ps2Ã¿g Â­Â§Â¢Ã®^Â‰Ã†/Tw@%ÂƒÂ¸Â´uP+iÂ£9Ã¸(Â‹Âï¿¾Ã½Ã„Â‡Â›X\\tÃ¬ÃœÂ‹Bq r*Ã˜qÃ­"ÂœEÂ¶CÂ 3Â¼IÃŠÃ‚TRÂ»\\b2Ã¥Ã‡Ã’Â»$ÃÂ¦Ãº9\\nÃ'Ã«Â›oqÃ—}ÂªoXÂqÂ§Ã .ÃÂ—Ã¡ÂÂ.Â¢*Â¢Ã°Ã¨Ã\.Ã‡M.Ã¼Ã¦y:Â³lZÃŸÂˆaÂƒPï¿½UÃÃ©Ã‰'Ã˜L\\rYbÂ‚ÃÃ‰bÂ¤Ã“y%Â‘Â‰Ã‚Ã´Ã¤|ÂˆÃ›\\b7\\nCÃ±A>Ã¸,Â¹\\bÃ3Â¡Â–Ã¶K@4ÂœÂ¬mÂ£ÃjÃ½GÃ´2Ã¯Ã–sAÂ˜ZÃ¹Â¡Âµ oÃ¨Ã¨+NÃ†3Ã‡=ÂºFÃ¯Â“ÃÂ™Ã…ÂÃªÃ¶ÃŸÃ³Ã§Âº}Ã—hÂ‹Â²Ã³yÂ®ï¾šabm6>ÃÃ–{]Ã­ÃœÂ³? [\\fzFDXÃ‘Â‹Â½Ã†GLÂ‰ÂŠMÃ„ d|*Ã£mkÃµ8YgÂˆÃ¨Ã„*ÃÃ¾)ÂÂ—wÃ—Â¤Ã&Ã’GÂ»Â‹Ã”mÂƒÂ‚Ã›umFÂ!Ã’Ã\\n\\fÂ—Ã«QKÃªÂÃ©Â¡Â Y7{Ã‰Ã VÂ¤CeÃ‡\\bmÂÂ±Ã–3SR+\\b%.Ã‘Ã…:R%Ã³QÃ­Ã¹ÃeÂ¥Â»Ã©Â£;Ã¸,vÃ¼qÃÂ… ÂºÃ­ kÂ Ã¬kÂ¸ÂªÃ„Ã­,Â°i8OÂ§[~Â§Ã’IÃªÃ«ÂrÂ“mPÂ¶Â’Â‰\\rÂ®KÂÃºÃ•*Âˆ=B5ÂÂ«Ã”Âš#^5Â¦>&ÂŒjÃ˜Â®Ãˆ/V\\fÃœ:Â«SA\Ã¨%^Ã„xDYÃªÂ¦Ã¸Ã‹ÂVÃºJ\\tSÂ³ÂŠ)9ÃµMÂ’Âº~Â¤Â»wÂƒÂ¨Â¼;@Ã¹Ã«ÃrÂÃÂ¤Â·Ã¹xEÂ£*Ã¤ÃfÂ*ZTÃŸ|pÂ¥Ãœk/ÂºÃµ,WÂƒ@BeÂ‹7Ã„Ã›Ã¼pÂ„ÂÃtÂ¯ï¼”Ã´Ã®ÃŸ;Ã™Ã±.Ã¿ÂšÂ†ÃÂ›J Ã‘Ã¨$RoKJÃÃŠÃ•Ã‹."RÂ˜Â„:Â’Ã9Ã¢ÃOlÃªUÃ´yÂ˜:ÃŒ)Â¡YÂ¥6oÂ‚;Ã¦Â‹E~ÃÂ©Ã¥Ã!JÃŸÂ•Ã·:Ã…ÃšÃŸÃ :hwwÂš\\rÂ›Ã¨lÂ²pÂÃºÃJÂ…Ã½SÃ¤Â¦``h"Â–Â„Â»Â†Âˆ. mTÃ‰Â¬ejTÂ¬tÃ¿UAeI\\bÃ Â˜Â†Â›6Ã‹Â¿Ãš/Â DtÂ¿dÂ§][Ã¦Ã£ÃªÃ‘Ã±Ã½}QÃ‹*Ã¾ÂªÂˆÃ£{Â„"MÂ¤Â©Â¨Â³Ã¤dÃ†Ãµw_jLÃ¼bÃ„Ã˜Ã±Ã•~}6Â…Â£TJ:Â…Â¬*'Â™!Ã¾[LÃ•Ã¥/Â‹ÂºÃœ'Â£Â¬Ãµ^AÂ¦`Â€Ã©u];OMÃ¼Ã³OÂ—iÃ¶)ÂÂ›ÃŠÂºÃ¤ Ã¡IwÃ¬'Â‰7ZÂ›f5Ã•Ã›Ã˜Ã³Â–Â“=Â gÃ¬7Â©/jÃ™Ã³Ã—$Ã„ÃŠÃ•{ÃŸÂ Â—0Ã¶Â…0Â²<Ã™0ÃšoÂwÂ„Ã Ã#)ï¼‹ÃŠÃ™mÃ“Ã˜Â¯Â©DÃ†Â¾Â¤Â• Ã£Â£3Ã•6Â…Â£lfÂˆXÃºxÃŒY\\bhnÂ…o4Ã’Â=RÃ¡NÃŠÂ¦NÂ‡ÃaÃÂ–\\bÃ¬Ã“Ã¾ÂƒÂ„jÂ½Â¯ÂŒÂ†ÂˆÂ»Ã£/4Ã‚zÂE6Â‰Â³\\r*ÂŠnÂ°Ã¬Ã´/xÃ—Â»]#Âª>G)yÂŸÂ†ÂµÃÃ³Ãƒ&cÂ½\\nUÂˆVÂ°uÃ‡Ã”Â§Â¬(Ã¸ÃWÂ­Ã¦fÂ— Â¾Ã(TÂ‚Â³Â¡Â´Â˜0Â«}CK:`Ã¯Ã‡Â™ÃŸ<rÃ¾)$9ÂŒÂÂÂ½Ã”Ã±ÃÂ˜Ã±QÃ¦ÂƒÂ‰Ã©Â¬Â²tgYÃ„U"$;btÂ¹Â¯zÃºÂ±Ã¼6XÂ©Â—ÃµlÃ½Â¢CÃ±Ã‰\\bÃ˜+Ã¤Ã€Â§Â²Â¯ÃÃ Â‰TÂ…ÂªHÂ²xÂÃ¨Â¡Â¦Â‰& Â¼8SÂ›Â·GÂ€ÂªÃ‹Â™,Â¨Ã¡Ã±*9Â˜Â¬ÂÂAÃºÂ¢vRÂ¼2ÂŠxOmNFÃ™ÃªÃ¸Â„Â¶Â£f)Ã¯Â Â¯ÃºUÃŒÂ‚Â±,ÂYÂ¿ÂÂ_ï¾ igzÃpÃ ÃŒÃ®Â…Ã‹Â½ÃŠ:Ã¥Â'Ã¨Ã–Ã¦\\nÃ™ÂƒÃGÂ¬ÃµkÃ”$Ã‘/Â™Â§Ã—ÃˆÃ•kÃ<ÂšÂ¾p"[Ã§@ÂµÃ­Â†Â®[+qXg\\f^ÂÂŒ8sRÂ³rÂ¢Â°~-Â Â¡,ÃŠÃ‚Â–Â”"\\bpÂ®Â‚\\rÃ´ÂªÃ¿eÂ"Ãï½¡Â„?ÃÂ½ÂÂÂ”Ã¤Â¯Ã´)6Â»ÂˆÂ™Ã½woÂ“Ã¥Â‚Â—eÃ•Ã»Ã«jÃµ,#5ÂŸÂ°DÂ…j?o"FÃ€ÃµÃŸlÃª\\nÃ•sÂ²Â€Ã´\\n=Â­A;Ã£Â¥Ã’-ÂºhsÃ¦XÃ“Â„Â…Ã“Â›Â¾mOÂœÃªÃ wÂÂ¬Ã£SHÃ€Ã¿AwÃµÂƒÂï½¸>"Ã§ÃƒS!mÂ¥Ã‰Â“Ã«Ã¶6Ãº1Ã’ÂºmÂºVÂÃ’ÃÂ¸ÂoÃ¾NÂ€gÂ¨ÃŒÂ¼ÂˆÃ´Ã“ÂŠÂ¨ÂšP@Â“Â±(Â±@Â‰Ã¡Ã‘0Ã½ÃˆmÃ Ã7RÃ¡|Ã•Ã¶Â¤ZÂƒÂ»%Â¥Â¸Â†Ã©YAIO"Ã¸Ã§Â«Â·[(Mï¼½Ã¶Ã‘ÃmÃ½Â¹ÂpÃ¸ÃŠÃ§Ã¶Â¥v\\tOÃ’y,9Â“ÃÂ¤Ã”Ã™Ã¶Â€Âµ_Ã‚Â±PÃ¥Â¼6Â„ÂªÃ‚0Â¬Â¼gÃ†ÃÂ”Â…Ã°Ã•ÂºÂ¿Ã§J Â–V}Ã—8m\Ã„yuPÂÃ³KÂ›ÂŸÃˆFÃ’Â“:wÃªÂŒÃœÂ¡3Ã¿Ã®Â‡ÂŠEÃ¬Â¶ !ÂŠÃ¡4C4Ã¢Â%ÃµaÂÂ¶Ã‡Â³ÃƒoiÃ•ÃœÃ®ÂºÂ®ÃÂŸK!hÂ»$9/EiÃ¼Ã‹ojZÃ¬ÃÂ¡Ã‚ÃŠÂ™eÂ¥Â²Â“=cÂŸÃeÃ³Ã•Ã”qbD&Ã³ÂŸ=Â£vÃ¨ÂiÃœ}*bPÃ¡Ã•aVÃ¼FÂ‡MÃ½Â•ÂÂ™\\nÂµÂ¢ÂºLÂ‰Â¼Ã€N9ÃÂ¤'NEÂšx0:dÃ“Ã¨|ÃƒÂªÂ„{Â„ÃÂ»\\bÃ¹OÃ•v'~Â¯Â¯RB\\nÂ¼Ã¦g5Ã¶bÃœÃšÂ·Ã€ÂˆeÂ–$~w]Ã§Â¯ÃŒ`t__Ã¾Â¨qÂ¬\\fÃ vÃ«ÂZÃ³\\rÂºÃ¦5BÂªÂ’ÂŒÃ˜nÂ±Â»*,Ã«ÃšÃ•Â‘ÂƒÃ•Â ÂauaÃ¶Ã¢bÂ‚OÂ¹Ã¯Ã=Â±ÂªÂ^Â”EÃ´Â§qÂ‹Ã¯JQÃ«Ã˜SÃŒÃ£fÂ©'Â–Ã®:Ã±HÃª\Ã‰Ã¥Q2Ã¬~kÂ˜>Â—vÂ Â¸Ã˜PWÂ¸Â±Â…Ã€ÂÂ‡xÂŒmDvÃ‹Â*u\\fQÃµ3ÂÂ¿6ÂÂ°Ã²XLFÂ»Âœ5Â®Â€Â†(\\fSÂ¡=ÂºÂ•Ã³Â©{ÃÃ¹Ã‰Â«Ã|Ã«UÃ“Â†ÃºÃ«Ã¢$ÂÃŸÃ•7Ã…Ãœ&PÂ¦N]ÂLmX$(Â£Ã±Â­UÃÂ—UÂ±Â…@^ÂŸÃÃ¡Â—f=Ãª |Ã½Â–<\\fg;Ã”wÃ˜ÂÃ–ÂŠmÂ'ÃˆBÂ³_(Ã¡JÃÃTÂˆÃŒ7ÃˆÂ®l@ÂŒ8Â¤Ã$Â£Ã°Â”Â ÃEÂœÂ¥Â˜NÃ‘Q\\t$Ã”Ã¢Â‰xÃ›FÃ¥IÂ©Â•fÂ–Ãˆ<HÂŒÂ¹/+Â©Â¤4>/Â¢Â½Ã•ÂœÂ«ÃªÂÂ®ÃaÃŒÂÂŸÃ‰`Fj:`/Ã£Â¹Z|ooÃeÂ³Ã¿.cÃ†!?Ã¬$Ã•Â¸Â•ÂÂ-ÂÃ¢qÂˆ>Ã½Â½rÃQÂ·Ã©Ã§ Âª^ÃÂˆÃ¹ÂŠoÂŸÂˆ2aÃ«Ã«Â‘Â]Â±Ã¡Â’PnPÃ®ÃÂ©Â¨Ã§\\fÃ˜Ã@Ã‹Â°Ã»Âv0+nÃ›dÃ…(ÂÃ¶<Â®Ã£BÃ‹2ÂR\\by\\nÂšÂŠÂŒ984ÃEÃ‰GÃ¢ÃÃ¶Ã§Â†ÂŠcJÃ¨Â¢V5\\r ÂÂ‘Ã‚.ÂŠlÂ¹5Ã¿!Ã»Ã®>RÂ°Ã½)ÃµÃ³\\fÃ…\\fÂÃ¶Â§Â¥Ã›Â«Â»+rÂŒ7ÂÂ•ÃŠ}Â‡cÃ†JÃ¥Â–Ã€ jÂ’DÂÂ±sÂ‹NÂ½Â¼ZÃ¸Â• Ã‘Ã¼Ã˜ZÃ°Ã•\Ã±fN@ÃÃ‚@9Â·+%t`Â‘]Ã¢Ã¨GD*DIÃ«Â«Ã˜Â”ÂƒÃ‹ï¿€Â«mÃ­|Â¢Â‘Â·Â¯Â»ÃœLEÂ±Ã¹Â”\\tÃ©)Ã¾T0|g-Ik-Ã¾Â·ÃŸÃ—7ÃµsÂ›Â"]&aÃZ\\rÂ„0rÃ™pÂ§3Ã”Ã±^H|nnÃ’Ã­1eÂ‘\\fQÃ«~Ã“ÃÃ„ÃÃ¶Â¶ÃŸÃ‹o`Â¤Ã£Â”ÃƒMÂºÂ©Ã‘Â•|Ã¡Ã•ÂÃ+Â¥1Â³Ã¬Rx?Ã†Â€6ÃŸ@ÃŒSÃ¡Ã‹ÂœÃ˜Ã€Ã‰Ã—:ÃªÃƒÃ³ÃŒ0Â¦cs9Â¦hÂ·Ã¯TÂŠÃº3}T@Â•Ã‚Ã [|d*tÃÂÂªÂ­.Â•Â±bdÂ—Â‹Â‰Â§Ã‚zeanUÂ³Ã‘Â¢Â¾!8Â´ÂªbÃ­aÃ=ZÂœÃ“^Â¶geu!rÃ‹:FjÂ€Ã™Â·]\\f4Ã³Ã™ÂŸÂ–+Â‰Â§cÃ¬~?ÃƒnÂªÃ¾Ã”ZÃ­ÃAÃ¹ÂÂ¬XÂ¾|Ã»01Qm=`Ã Ã»xÂ¢Ã™Â°Â¿Ba\N3RÃ· ÂµÂ‘Ã”0eEQ\Â¨Â›Â˜Â¹^Ã«x1Â¼{{Ã„%N QtÂ½Â²Ã`$Ã’ÂƒÂ‡(Â§Â¦uoÂ½Â–/Ãº"ÂªWÂ­ZÃ³Ã¶Âˆ"2Â—Â‡Ã–/Â‰Â‚ÂÂŸÃ¼Ã»Â™J>hÃ¼Ã—Â…FÂ`Âz$Â© Â`XÂ¼wÃ Ã†aÂ¯Â¢Â› KÃœ}BÂÃ¹M\Â™ÂŸ6ÂPÂÃ—Ã‹Â¼\Â¡<Xja4-Ã·L0Ã”b-CÂª\\rhÃªÂ¼Ã®Ã$O~Ã¨_Ã fÂ½pÃªUÂ’`^Ãƒ8Ã½Â„L@Â¯Â¢ÂºÂfÂ¼Ã†SÃ°mDÂ¿GÂŠKÃºÃ‹TR\\rÃ¾(Â’2H?oÃ©Â©Ã•#Â™<\\nÂ¨Â¾Â¤,Ã’Â¤ÃªÃ¼1Â¡\\t-Â³0lÂ‡nÂ¿ÂšMÃ·Ã—Â•ÃÃƒÃ’8^lÃ™Â¡\\rÃC\\t"hÃ§ï¿°yÃÃ‹Ã¥ÃÃ°aÃ‡Â‚Ã—Â¯Â¢ÃŠBÃ–Ã”Ã™_3ÂÃ©6Â–ÃŸÂÃ²RÂªGÂŸÃˆÃŒzbÃ¿Ã«ÃÂµ\\bHÂ±ÂŠÃÃ‡Ã¨v ÂÃ>H)ÂÂ•Ã‹Ã•!Ã›Q;-FÃIKÂ©Ã¬Ã¡CÃ¬Â¡Ã…Ã½ÃˆÂ˜Ã¤+Ã´\\tÂ¢Â½&Ã¬Z]FÂºÃšÃ•&{Â¥Â«uï½‡Ã¶Ã hÃ¦HÂ–GBpÂ˜@Ã£[SÂ’Ã‚Â» Â˜Â¢Ãœ)Â­Â›Ã$:ÃiÂÂ®Â˜ÂªÂ€|Â¸Ã³TA_ÃuoÃ’ÂU3+Ã’+\\b+Ã›ÂÃ²W\\b@k^Ã¾Â¤Â¢ÂŸmÂ–Â‰Ã¹Ã Â»Â•ÃÂ¥Â„Â‹;Â¼ ÃŒÃ·MÂ².Â¶Â¦Ã»Ã´7A\\tÂ°\\fpÃŸÃ£Â‘Ã©\\tÂ‘ÃÃˆÂ¨Â¯hÂ¯IHgeÃ¬hAÂ”Ã¹Â8sZÃ±j?VNÂ˜ÂŒÃÃ®ÂœÃµ!Â¯Â‘fJ/Â¯fÂ¢ÂÃˆ/Â›ÃŠtlÂº4Ã¼ÃƒQÃ¡Â¶cÃLÃ§9Ã¥ÂªÃ‚3>CÂgÂ½[Â°+tÂ± 0oÂ¼EÃ¸Ã“ÂpÂ³30xiï¼£Â¯JÂ£fÃ¸Ã¡pÃ«,Â½Â¿LÂ˜Ã™Ã¯Â·U]HM|Â­ÂÂ™AÃÃ‘iÂ”U>Ã¬Ã¤KÂ¸Ã¸\\f<Ã¼ÂªÂ§Â‹<ÂÃŒÂ±ÃÃ¤Ã¹JuÃ†Â´Ãƒ$ÃÂ­ÂšÃ›ÂµÂ¢x\\b}Ã{ÃƒÂ­Â»Ã¾ÂµÃŸÃ¸ÃŠÃ‚;Ã„Â¨|HB$Ã¡Â»Ã›5Â‘QA)jÃ¶QÃ³4Ã¾Â¿4Â Ã˜?ÂU/!>!Ã¿Â±Ã’ÂŸÂ£ÃˆwÃšÂ€Â©AÂÃ‚Ã?&}nNÃŒÃ cWÃ”P#%Ã½Ã¤MÃ©Â“Ã‹\\nVÃµ!A}Ã»Ã¿Ã›`ÃŒÂ¢ÂÂ«{ÃšÃ²Â¥Âª\\r5Âµ+3Â•gÃ®ÂºÃƒÃ—Ã’s3Ã„Ã½Â‰Âš0ÃŸÃ©Ã›Ã‚Ã”Ã™Â¥Â·Â¢Ã™Â”uÃ©Â¶ÂŒÃºÂ‘?ÂªÃºÃ.TÃ¤Ãƒ8q:Ã¯^Ã‘Â°Ã»Ã‰Â©Ã·Ã¼odÂ…6^ÂVÂ•Ãˆ\\n uÃ§Â§\\tÂ‚ÂšÃª] Â®ÃlÃ)Ã„Ã¸Â“"0\\f>\\fc1SÃšÃ‹Ã‰ÃÂ—Âƒ`zÃƒÂ§qÃ·b}Ã„Â§Â²yLÃ—AÂ…Â¢Ã™Ã›Â±ï½ÂµÂ»Ã‡Â³%ÂÂ¢~\EÃ´=0ÃŒÃ¤Â´Â¬Â³oÂ™tÂ©\\t*ÃÂ¿Â´YÃ¢Ã°g<Ã¼Â¾ÃÂ…ÂªÃ“e:Â½Ã³[Ãº`CÃÂ†Â©hÃ•Ã‚fÂ³Ã„Z}[Â‡<nÂ®ÂÂ—Â¡p8]uÃ†[Ã’AÃÂ¬PÂ¿[^jÃ™Â‹Â–cÃ©Â‹XÃ£e0Ã¶ÂŠ`QÃ±&ndÃŠÂ={Ã¶ÃœÃÂ¨&Ã°Ã˜OÂ•Â£Ã’D9Ã¡Ã†[Â„JÃ`ÂŸÂ’Â‰ÂšÃ¹Â‰Â•-{Ã²U\Ã¶Ã‘ÃÃC^ÃÂ¼q:/Ã§9Ã£ÂxÃ£Ã°-ÃÃ‰Â“U_-Â³Â±Â³wÂ¢Ã¥Ã¡Â­ÃÃ¦RkdÂ­Ã§Â¬Â·Ã´Ã¸Â®$|ï½Ÿ\\nÃ–Ã·{KJSÃ¶Â·Ã8ÃÂ²/Â£ÃÃ‰bÂ£Ã—Â´Â†Ã•Â…Â›I9eTÃ¡HNÂ£Ã‰q8Ã³2Ã”:7+ÃÃ\\nqHÂ„ÃŠÃ¹Ã£e_B->Â°Â²|FÃ‚Ã¬AÃ³Ã©%Â´fÂ“Â¬H %ÂŸÃ3o31Â¶Ã¾\\bÃœÂ…Â«ÂµÃ¦?Â ï½›KH)F_Â5Ã®ÃšÃÂ~Ã»Ã–B&Â¼ÂªÂƒÂ˜LÂœ)ÃTRÃ®+,Ã€Â¡Ã¼ÂªgÃ¸Ã‚c4Ã“ÃÂ²Ã³Â‚sÃ†Ã€ÃŸÃ¿;XÃ–ÂÃ¥:_Â±Â»ÃH Â’Ã¡Ã¿\Ã¤2Ã†BA}Âœ"hO1B[Ã‚Â Â®ÃÃ§ÃƒÂ´wï¿ƒÃ®.Â¯ÃºÃ˜EÂ©9Ã£Â½`j]Ã¤(\\nÂ©Ã‘>ssÃŒm=(Â½Â¸Âš!]Â¬LÂ„ JÂÃŠOÂƒ1kMÃœSÂ»{S!Â?ÃÃ„ÂµÂÂÃ‰Â¹g?K^ÃŒÂŒ'#Ã†u/!Ã—u3Â¸R6XÂ‡G)\Is=Â›mÃ¹mMÂ¸0Ã¨ÂƒÃšÃ„Ã¿x<ÃƒÃ…SW:.OÂšÂ‰Ã‹-Ã—[ug<Â¸Ã˜Â¨Â—ÃÂ™ÂªÃ§Â‰Ãsjfp hXÂ·ÃŠ2$Â£Ã‚6Â‰*ÃÃÃ¸Ã¸2nÃ€RÂ¥Ã¥Â½Ã—Â”Â†Â”`ÂŸ\\b^4Â­Â£Ar7Ã¸\\bDnSÂƒÃœÂ±Ã¼&\\fÂ¿Â‰_ Ã‘+Ã²/Ãƒ>>-Ã¥ÂœRÂ¹Â¼cÂ¦pÃƒ|Ãƒ+Ã…Ã¤x~,ÃÃˆvÂŸa.Â½? lÃ§bÃ¡ÂƒÃƒaÂŸ{1_Â«Â¸ÂŸQÃ—ÂvL{>Â¦@szÂºOÃ±2ÃˆÃ‚Â£ipÂ°dXÂ«FÂ„Ã¸Â²Â½zJQ|\\fÃ‡Ã¾Ã–Ã†eÂ°PÂ³kÃ™Â˜;Ã˜MÂ˜Ã’ÂÂº-Â°Ã°ÃœÃœÃ£ÃŠÃ 5ÂµÂ˜Ã‰ 4LzzwtLÃ¡l0Ã‰@yUNaTÃ }ÂfTRÂ½Ã¸Â·bÃŒÃš!CÃ¼cÃ/Â gTÂ·ÂƒÃÂ«Â‹yÂ²0Ã€Ã°Ã–J+zOÃ˜EW=Â¥\\nTÂ»]/G6Â³OÂ°Â‹Â»ï¼°Ã²ÂºÃ¯Â­Â°Ã±ÂÃ°ÂŸÂ”'Ã™Â‹oe3Â·Ã§xdÃœ;Â¿Ã¶ÃšXÃ£Ã’Â°\\tÂœÃ¸TÃ©d,\\fbÂ€7c,KÂ—P\Â¸ÃÃ¸wÂ¡$Ã™Â¹Ã HnÃ–Ã¬+Â¦rK\\t+Â™Ã’Â Ã?OÃ¥Â¬:UÃ¼ÂÃ‹.ÂœÃ¢Ã†[Ã«"NOÂ§OÂ¨VÃÃ‰Â¥yÃÃˆE}Ã©Ã²f_,0Ã¿^ÃŸx.Ã‹Â¦y^Â¯ÃŒÃ«Ã°ktÂÂ˜"Â´Ã¸ÃÃˆ ÂºmÂ˜a\Â¢Â¹Ã…QM3Â–Â‡Ã§Â½=Ã´OÂšÃ‘n/]Ã\\bw9UÃºÂ²Â‹Â¤Â‚$ÃÃŸÂ€UÃ¨pÃ‹Ã¶Â©Q#ÂqÃ€Ã¿Ã—UÂ…]Â®($xÂWÃ¯Â±Oï¾’Ã®Ã³ÂªxÂ¹tÃ¸xÃ»RwÂ½KvÃŒ\Â™Ã¯@Ã–Â¡,Ã»Ã®Â‘Â¼Â‘_,\U/EZÂÃ‹Â»< Â»!9Â„=ZWÃ”N>3Ã±M=SÂ‰Â³+Ã´Ã®Â‰Ã°Ã‰Â‰QDÃŸÂ®AÂÂ²Â›NÂ¢]Ã‹Ã›ÂŠUÂ„Â»;_Ã—[Â‰jS`Â¤Â…@ÂºÃ‘OÃ¾ÃÃ¡ÃŸÂÂÃ…Â»ÂˆÃÂiÂ¨L&Â”}JÃ¢Â¥:TdY Ã²Â¯XÂ¡Â¢Ã…G\\fU=3Ã‚Ã°5dÂ¾Â…Ã³\\nÃ³,ÃÃ¸Â¢Q;Â’>hÂ‹$.Â¢Ãµ"0Â£Ã·ÃˆÃšÃ^Ã·\\fÃ¤Ã¶1Â˜Â³Â¢\\t4ÃŸ,'Ã¿Â–Â,Â»Ã£Â¨e'Ã¥Ã³GÃ 2Ã³DÃ¸&Ã¼Â‘Âe_ckÃ‡ÃÂ˜Ã¢Ã½Ã’Ã„Âº`+Ã–Ã¢Â—uÃ±mÃ”kÃ°Â°ÃeÂÃŒv;Âˆ`MZ9hÃÂˆÂ²ÂµÃ–ÂÃ’Â½ÂÃ¬_Â‰L,Ã»Ã‹Ãˆ/&lÃ”RÃ§aÂ¥J7ÃŸÂ£'jÂƒÂ3Ã¾Â„Ã®Â¦gQÃ Ã¶Â€Â¼%Ã¥Â£\\nÃ¯Ã™SEÃƒovÃ²u!SeÂ¥*ÃoÃ—Ã±Â±4Ã¥9eÂ¤Ã›Ã©Â¸Â‰m?ÃÃ—ÃƒhÃ„Ã¾#Ã%ÃšÃÃ³Ã¥VÂ¿{Â¼Ã¤n>ÃºÂ¡Â§Ã—Ã¥C-Ã¼+5Ã«QÃ¼Â¹Â¯Â©Â€Â¥Â£Â¥7Â¡SÂ¤dÂªÃœÂ¨Â’Â†KÃºÂ´Ã¨ÃÃÂ­EÂ”Ã…z5Â‚+Â·Ã´$Ã°>Â¬ÃºÂ»Ã¯Ã²Â…Ã£WÂ¸\\rÃfÂ£ÂŒ*Â½2ÃªÂµÃ%Ã­\\rSÃ·Â ÂºÃ³=Ã…&Ã¿H\\fÃ¡J*+3Â…h9>Â¡Ã±bÃŠ\\tÃ‹eÃE'cÃ­'ÃºÃ±HÂ·6Ã˜Ã‹Â¹Ã¬Ã\\r$Ã‡Ã”TÃl} Â½l[Ã‚ÂšR[.l\\fÂ¬Ã²RÃ¤CdÃƒ$Â‰Â¢KÃ“Â¥,Ã»Â½<Ã¨\\nÃ’Â»Â©[Ã£ÃÂŠÃšÂ Ã¿xÂœÂ¡&PÂ³\\rÃ©pÃÂ¸Âº=Â‡y#Â¶Â•Ã“Ã£fCÂ¡Â²\\tÂ³ÃÂ—Ã¸Â±ÃÂ„Y{$Â˜ÃÃÃ Â¦Â¼Ã’Â°!Âª=MÂ¦S8Ã…OYï½¨+D\\bÃŠÃÂ»Âµ8Ã¸KÃ¼Â›Â®Â™EÃ°Ã€vÃ¹Â¨UÂ‹Â”Â“V|[Ã¯Ã¯Ã†&Â¤Â©Ã¡wÃ±Ã¬Â±Â©Â½=Ã›Â­ÃaÂ…Ã¥Ã«Ã€nÃ¯[Â²Â¯lÃ¤07Â˜Â¥Ã†Â±ÂˆEG8Ã°.Â•Ã¨Ã¥Â¢0%'Ã—Â©6lÂ¥Ã–RÃ‰Ã³ÂkÂ£Ã¿Â´}Â‰Ã²7ï½œcÃ—Â™Â¨LUlÃµÃ½Ã¤;Ã¶~tÂŒÃ¡6hÂ´Ãƒp=Ã£Ã´Â¨Ã¢IÃ:OfÂ©Â€Ã¯ÂªÂdyÃŒÃ¬uÂÂºÂŸ<Â¾Ã¡Â­zfÂ¿GÃ£c_=Ã¦Ã¯Â‘Â˜]TÃ¶42XÂšfÃ±r-\\b\\rÂ\\rÃ¯|Â¬|E~Â°4ÂµÃ•Ã·ÂÂÂ’Â¾Dï¼©ÃIÂ°Ã„Ã–@Ã~uGeOÃ™&UÃ˜WÂ±Ã¾Ã·Â—'ÃÃ’\\bÂ¿Ã®Ã¦?gÂÃ€ÃÂ¬lÂ ÃÃAoÃ‡LÂšÃ’ÂŸÂ„Â‹Â¬Â‘TÃ¸Ã¥^0cM<ÂœÂ±Ã˜ÂœÂªÂ¬tyÂ›Ã‘Â–Â—JÂ­ÃŒÃÂÃÂ½ R8|TÃ‘Â‰Â…Ã Â“xÂ¹bÂ¨Ã’ï¼†r;K@Ã¢Â…>Â¸}ÃÃ‰ÂˆxÃ¨(\\r'Ã«Ã‚ÃªÂ‚Ã·Ãµ`ÃªÃ†Â§Â´ÃÂ±Ã¥Â·Ã¨u0Ã“5Ã·Âº Â·Â€Ã\\bÂ+Âœ$Â=ÂºÂºÂ±pÃ‰HÂªÃ¬Ã·^Ã“Â¬WTÂŠÃŠÃ«Ã”CÂ“Ã›Â½Â£#CÃ¾Ã‡01W5.Â»Âƒ\Â‘X-xoÂ±Ã¯Ã¼Xï¼Šh".Ã”]ÂªÂµ&pÃ²ÂŸÂ¯Ã¡&ÂÃ¬ÃªÃ¦Ã Ã½Ã›ÂÃ†<[Â’Â›hÂµÂ“wÃ§&ÃÂ™ÃœMÃªÂ²@3ÂªÂ­UÃ„Â¶ÂƒÂ® UÂ†Â·l\\b}Ã›Â‚oÂŠ[Ã±ÂÃ—\!ÃŒwÃ™=FÃ†aÃ¦Ã¢Â¿DÃ¨XÃ‹Ã·ÃµÂ¢ÂŠNÃ¹d\\r]Â¾Ã²Ã‹D#ÃˆÂ±Â„FzÃ†Ã Ã¾Â©Â¸Â¤RHÃˆÃ–Ã€?nÃˆÂšOSÃ±Â†Ã¡_6Â¬Â¿Ã¹Ã­ÂŒÃ Â™OlPÃšÃ™Ã¬Â€sÃÃ…Ã³[|ÂŸÃ…\oÃ„Â³gÂÂ¹Â£ÃœÂˆÂ…UÂ¬Ã¾Â¤5Â„ÃŒÃ·|ÃŸÃ¤iÂ a']\\nÃ 7Ã«\\fÂŒÃ°Â©.ï¾‰*(oQLÂK%Ãˆ;SÂ9ÃÂ¢Ã§Ã“ÂŠ\\nÃ¥ÂÂŸ;AÂ¤Ã™+_\\nÂ”Â„Ye Ã¡Â¯XÂ½Â¼Â‘tÃ°Â”pQÂ¿Â²Ã²ÃÂ° HÂ¹Ã½Ã·<ÂÂ±/Ã€Â?@gÃ¦Â©bÃÃ…DÂ¯oÃÃÂ¸Ã‹\\bÂ¥uÂ½ÂµÃ¬;Â©a=;ÂŸ"ï¿x!}Ã¨IÃ¼Â™sÂ›Ã‡Â¥ÃcÂ´VJV?fÂª)Ã¹#Ã›Â†ÃƒÂ·V;oÃ´Ã¸Âˆ,4Â¾J)ÂKÂŒÂŸ\\nÃ¢RÃ¤ÃµXÃ›ÂÃ†`;7Ã“Â»ÃºÃ¨[Â‡Vb+DI_ÃºÂœ\)!\TÂ•ÃÃª#Â½\\tÃƒÂšÂ†GÂ¦Â£ÂŠÂºÃkqÃªÂ•m}Â–'Ã½Â™BÂ=Â¼Â„ÃˆZ[RtÃ’*(Â›Ã¢zOÃ¹Â½ÂƒÂ²ÃÃˆÃ–Â‘Ã‚`Â Ã›Â¨rÂ¾7Ã‹IrEÃ™Ã«Â¼Â°rxÃ¬ÂÃ¤Ã©Ã´<`Ã•Â®Â‡Â¶Ã¨Â¯RÃ‚qÂ¹Ã­Â—Ã…Ã–W^Â¨#\\nM?Ã¯Ã‚Â¬Ã3RGÂ™_Ã­;I;ÂÂ«%Ã‘`Ã¡Â¹SÃœÃ—Â™yÃ¡ÃœÃ¥ÂÂ§Ã»Â±_bÂ¶MÂ>Â¬Â£Ã‹Â®Â²ÃšÂ¼WÂ¢I:XXnnÃœÂ½PÃ³Â„%ÂµxÂŸÂ€Ã¾PÂˆkNÃ¸ÂŸ]@wÃ”ySÃ¶Âœ4!@%Ã™eÂ¦WoGÃ.Ã¸Ã›Â«b_Ã¦Ãœ+Â®\\fÂšyOÃ¿KÂ¢Ã¶__<Ã–I(ÂpMÂ´ÃªÃ’C3RÂ»\\tÂ°Ã€`ÂÃ±Â„Â•Ã›ÃÂ“Â™Â¼MÃ«Â½Ã†Ãš^Â›Â®Â•Ã¾Ã‘Ã¾Â›Ã²vGÂ•Â¶ÂœÂ gv$Â‹m\\nFÃªÃ˜\\fÂÃ¥OVÂ©Ã½&ÂŠÂ³yÃ•ÂÂºÂ`ÃqÂ«Â©Ã”Ã¦Ã‚Â†Ã½Ã€\\nÂ™Ã•ÃAÂ­+Â‚Ã€9\ÃÂ¾Â»ÃŠtÃœÂ¶GSeÂ˜Â°ÂµnÂ˜MVÂ©~xÃ=&kQbÃÂ¯MÂŠÃÂ‡VqÂ |Ãxc}'_Â˜$;Â¬47?ÂˆÂ¶Ã¶Â Ã‰KhÂ˜;\\nÃ¨ÂŠÂœe":^Â±%Â†Ãƒz$Ã”Ã˜Ã¬_!|ÃœÂ Ã•Â¢Â UÂœÂ°Â˜ÂšÂ‚SÂ¶Ã¢ÃQ\O.lI8Â’Ã‹%B~Ã•qSÂ±hqE%Ã…ÂÃªÃªlyÂªfHÃ§Â³tÂ»ÃˆÃ°EW4CÃ”,RÃ»Â«Ã²{uAH_*Â¢$Ãš1Â›Â¡QÂÃ´Â€PÂŠÃ—(Ã¶Ã½Â»ÂœÃœ!Â`Ã”Ã†gÃ« ÂŠ~"\\nÃ¨YÂ«Ã›Ã´5Â‚Â±ÃÂ¦]3ï¼­9^8ÂƒÂÂ„Â¼\ÂÂ½YÂ„ÃµEÃ†Ã“WXZÃ¾Â¿z ÃƒÂ»Â£:Ã•Ã¼Ã¶vÃ§ÂœlÃ TÂ]Â”Ã½Ã²4+-Â‘y3eÂ¢ÃƒÂ…FÂ“/J6Â¿ÂƒdÂ†6_\\fÃ–ÃÂ¹ÃµFÃ›d\\rÂ¦kÃ¬ÂŒÃ¸Ã›ÂªPÂ§1Ã‹Ã°II5`XÂ¢Ã—Ã·Â‰iÃ™ï¿†;Ã«EdÃ“iÃ·ÃÂ²Ã¢ÂŒÂ¬HÃ¨\\b|KÂ±Ã½Ã ;Ã†Ã£VfLÃˆj{\\nÂƒ3Â‘Ã²ÂšaÂ¢&Â†<Ã˜Ã¹xÃ•Â¥wÂ‰Bq&ÃºÂ±ÂšvÂ±ÃÃ•:2L\\bYÂ·)Â©Â¨\ÃµÂMÂ¨YÂ†WÃ¸9WÃ„G )Â¦Ã˜ujÂ²Ã‚P0Ã“ÃµÂµÂªr9ï¿¢Â¥Â©Â²+Â°Ãczk[Ã§Ã€*RÂ¾Â‰;Ã’ÃˆÂ¢ÂŠ[>Ã¾\y'Â§eÃ¾8Ã¿Ã€Ã£Ã£sÂÃÂ‚~\\bOÃÂ¦\\rFÂMÃ³ÃµÂ®ÂˆÃoÃ]Ã‰Â°WlÃ‹\Ã‰ÃÂ®.,<sÃ“Â‰bÃ³Â¶.Â˜`ÃºAeÂ¹d@ÂŠÂŒÃ†|Ã‡ï¿¹Ã‚mÃ¼Â‡bÃÃ°Â«Ã©g:Ã‘Ã’lÂ‚-Â…Ã…Â¡!Ã‘~SÃ¨ÃÃ³RÂÃ—UÃ•Ã®Ã•z>JÃŒ"ÂÃ¹Ã²Ã¬_.GÂ“ÃB1ÂƒÂ»Ã«Â²#ÃºÃÂÂ‚Ã™dÃ¹A)Ã§Ã‹ÃªÂ˜Ã¶Ã¨ÃšÃ\\nÂ£Â¸ÃšÂšOyÂ‹lÃ˜|Nr`Â…ÂªÃÃ«ÃŸ5~uÃ§Ã°Ã¿cÃ¶Â±5<Ã¢N\\b0ÃŠ\\nÂ-=ÂˆÃ‡ÂšÂ­[Ã„Ã«ÃœxÃ„Ã—lÃ½Â¢Â—OLÂ‹Â ÂŒ;:AQÂ™Â¦NÂµÂ€uÂš{Ã¾ÃŸÂ»Ã«mÃ™Ã›JRdÃ¶Â¿{Â8-Â²8ÂÃ²GÂºÂ˜Ã–Ã•]Â¡\\ne.Â¾*Ã† ÃJÃœ'\\rÂ¼Â Â¼ÂŒÃ´JÃªÃo\\tÃŸÂµ-Ã³ÂŒhÂ’ÃÃ›$KÂ²HÂ¬Â”Ã£\\rOÂ¦NÂšÂ¼+AÂlÂ‰ÂŒÃ†ÂŸÃ£Â xÃ¬=Â£ÂÂ—]: ')Ã§/a+QÂ”*Â‰ÃŠ-UÂ[|"*aÂ‹ÃÂ¬Â«hÃ¤ Ã›-:}+\\b<Â—>Â’Â­ï¾µÃ’{.ÂœÃ„Ã²7ÂÂ—OoÂ»`Â¯Â­!ÃšGÃ¬Ã³/\\tXÂ“Â»Â³Ã·DmiÃŸsÃ¿ÃŠÂ¦PeÂˆÃ¶Ã¿Ã¿ÂšÂ«JÃ”/Ã·Â¶)Ã‹Â«Ã­8/ÃÃ¤Â±lh*C#VÂ´ÂŠÃ‰Ã•Â½BiÂ¶Â¸\\t0Â‹ÂÂ·Dc7Ã‘!WÂ“Â£IÂÂ¿(ï½›Ã­)vÂ³Ã®oÂ°Â½ÃˆÃ Ã˜Ã‘Ã¦Â‹Â¾LZÃµp|ÂˆdÂ¥Ã•3Ã©DÂ’ÃŒÃ¹Â¢eNÃ¼Â5bf5Ã«Â«2Â›ÃÂƒkn<Â±ÃƒÃ®r\Ã‘Ã’Â›8Ã½Ã¼ÂˆÂ¶@S\\tÃŒÃˆc)K:ÂxÂYÂ\\rÃ»\\b/Â¶}AÂ¸9ÃµÂ•IÂ¡Ã¥ÃµÃ‚JVÂ›Â‹ï¾¹Â«eÂ£Â¶Ã€[]Ã°S"Io(ÃªÃÂ±Â¸ÂƒÂ‡d|Ã£Â»=@;ÂªtlÂ„<Â•Ã‚Â¸*ÃŸÃ£Ã—kÃ¯Ã¼ÂƒÂ¢HÃ¦Ã E:?HÂ»Ã¼Ã°V)Â½ÂœÃ€HÃ²b`^Â‚Ro7Ã£Ã›ÂªÃŒÂÃ´Ã±Ã»ÂƒÃŸjÂbÃ®ÂšÃ–Â›ÂŒÂ¢Â‘;Â¿Ã¿Ã˜Â¥Â˜ï¾€)?ÂƒÃ•Ã€Â‚IÂÂ¸ÃµÃ¡d|Â*h`Â‚o=7Ã¹Ã¸Ã®ÃšÂ°wcÃ˜!ÂÂ´;\\rSÂq1QdÃ‡OqÃÃ‹:Ã¹hO4KÃºÂ—AÃ½%Ã¼Ã¡Ã”Ã¨<JfÃ¨A4ÂÂ’V>>Ã‡Ã’Ãˆ?Â£ÂŸÃ¢Ã…Ã¡Ã§sÃÃ£>+Ã«AÃ¬Ã¯Â¸Â¶\\fTpuÂ‹ï¾¿^FehÃ¹Ã—&BN\\tÃ‹=6Ã¢6,Ã>Ã—!Ã~Â—1Â°ll@ÂªÃ«.uÂšÃ½gÂªÂ•\\b)Ã‰Ã†[Â±^Â¯}^BvÃ£?\\fÃ¬Â¥Ã™Âœ<gYÃ…Ã¾Ã„<ÃµÂ™cÃ¿Â†ÂšÂ¿ÂÃ³Ã¢aÂšÃ‘ÂœÂ¬ÂŒÂœÂŸ-ÂµÃ¥H|'ÃÃ¼pÃ®Â¼}yÂ¹Ã°;ï¿Ã¢Â²Â´Ã¹Â«Â•Ã¿Ã¿Ã©m Ã£ÂŸÃ‹Ã†6ÃÃ½Â˜Â¥_d4ÂƒJ]{cÃ´Â«Ã³Â¦zÃŠÃÂ ÂŸÃŸÂ¸\Ã–o8$Ã–%Â}Â—Ã‰ÃÂ­UzÃŠÃµÂ¥Ã½Ã½Â½[Ã›Âˆ>_Ã°Ã¤Ã·@Ã¦cÂ–Ã¯Â§ÂŒÂ¿ÃÂ Ã•v`Â¹ÂÂ–Â„DÂ›Ã£Ã¸Â¿ÃœeÂ½ï¼“Ã¯AÂ¯hkNÃ¢Â” Ã²Ã»Â©\\tÂ®Ã»9x@/aW`9AÃ‚OÃƒÂ…Â»RÂ¤Ã·Â–Ã¿>:ÃÂ³*Â–Âˆ}Ã¹Ã†ZFÃ¶Â‰&cÃÂ¶8\\fÂÃŒuÂ¡Â–ÃŒÃ”/Â„Ã‹Â Â»"ÂˆÃ­?Â°Ã™(Â™Ãº#ÃŒdÂµÃ¸KS$|Â’ÃŠÃªÂ³eÂ²'ÃƒÂ„.Â¹Ã¯_Ã¥`Â¿Ã‹LÃŠÂ£yK9Â·6Â‹Ã¥KÃ…Â¯zÃ¥2$Ã§Â±Ã¡3Â¹Ã±ÃMÂ½rÃ¹Ã·Ã¿Â©>\\nÃ¸Â¨1Â¸nÃƒyÃ¢uÃ¦r^Â­Ã‹Ã¶xÃŒÃ¡Â²Â¥ÂªÂˆÂ¥:Ã Â†gÃ¦Â¨=S^fÃ‘ÃƒÂ®ÂÂ·Ã¦/bCÂ°Ã‚Ã’Â¼Ã¯ÃµÃ–ï¿–ÃºkÃ¨^eCr~| ÃµÂ¶v*Â©Â¼cÃ„\\tÂªÂªÃÃ•Â¸ÂªÃ¹\\fFÂ“mÃµFÃ¼^SÂ–Â–Ã³ ÂKÂ­FÂ‚Ã…Â³(Âq9\\t&Â„ Ã‚ÃšÂŠ^Â[[Â¤r{Ãš~rÃ§Ã£Â¿Â·Ã†Ã…Âœ?Â%^!ÂŠnÃ¿`V>JÂ¾Â¨Â™Ã»Â T;RÃ„Â°aÃ&f%Â©jÃˆÃDÃ»Â”Ã= qÃµÂ¥*Ã˜nÃ£ÂÃ±Â™Ã°Ã…LÃºS6Â¬8Â¼Â€Ã˜fÂšÃ€Ã¦GÂ³w,Â¨Â£d^ÃŸ6Ãz^Â®Â’Ã»Â¸\\tÂŸÃŠvÃ²Ã·ÂŸÂª[;YXÃ Ã…Â‚rzÃ°@ÂµY$Ã˜Ã’wï¼’kÂ”Â†1Ã’RÃ…Ã¨Ã9Ã³zÃƒ\\fIeÃ€NÃšTÂ³Â½Â‹Â…XÂ€Â‡\8Â¬\\tÂ¿Ã·Ã€?Ã¤9Ã¼Â­ÂœÃ‹p\Â³_Â›ÂºÃÂ¼ TÃ”Ã Ã¯Â±ÂÃ®Ã™Ã˜\\t6hÃ¢jÃ¡\\r{s:QÃ¿{cÂŒÃ­Â€9\\nÂ 9Â·Ã³Ã«_Ãœoz*ÃªÂÂ‚Ã,ï½‚ÃšFDÂœ Ã¬Ãˆ/Ã³uÃ½Â›Â‹PÃ§6*Ã½Â™uMÂ”\\fÃ¶Â´Ã©Â¯ÂµÃ ÃºJÃ±Ã»A5?ZÂ©Â©Ã†p\\t`Ã¬jÂ‰Âµ=Â—Â¾Ã»Ã­ÃÃ©Â—Â‰Âœ^gnÃ£WÂ´)Â”Â‹Ã’MÃ®Â‘\\fÃ«ÂšÃ™lIÃ‡>ÃKd7fÂÃ®'Ã¦k% Â¤Ã©EÃ¹ÃŒ|Ã¯kÂš<Ãƒ`ÂŒÃ©*Ã‹ÂµJÃ–dXÂ¯qÂ„5Ã¿mOÃ‰\ÃœoÂŠÂ·Â‘Ã£!;Y@j,d}TÂ˜Ã·zUÃ¡ÃŸÂŸÃ«Â‰*\\n$ÂšÂÃ§}Â»5:Ã­Ã«Â«ÂœÃŒÂ„Ã³ÃŸl6aÃŠÂOÂ°Lf\Â™5gz|Ã¢rÃœÂ¿Â¿ï¾±u,Ã½&^Â4Â“{FÃ“Â®Ã™Ã±Â·Â¹:Ã¾Ã%qÂ›Ã¹Â„Âˆ`K~3Ã™ÂˆQ Ã›Ã±Â¡)TÃ°vÃ qqiÂ§\\nÃ±dÂ§ÂFÂ³XQA?DÃ’ÃšEhlÂ¶Ã­Â›)8 '!Â½Ã§bÂ‘Ã„;Â¡]Â¾ \\fÂ…Ã²ÃÂ…Ã¾Â‰]\\nÃ¤TÂÂ·Â¸R'2oÂª*4Â¨Â°Ã¬Ã€Â“Ã¾ÃÂ"_MÃ¬ÃÂ¹YJ}dA'Â™YfÂ®Â§Ã¬Ã…dÃ·Â¼Ã’pÂ«NÂ¦Ã»hÂ‡(Â’Â®Ã«Â¼sÃ¸Â•>Y wÂ¥0Â³ÃŸÂ“Â’Â¿Â½Â ÂÂ³(ipÃˆÃ¿ÂU[Â¯ zÃ«Ã®ÃÂ­Â“Âª}!uÂ§Â¯Ã¤Ã‰hÃ¸5Â¿Ã–ÂÂ±Â¢a%Âƒ'Ã‘Ã‰/Â±1\\r3ÃŠÃ§ÃÂ¡*kÂ·ÂªÃ›H!ÂEvÃ—;Â§Â\Â¿Ã“ÂÂŒÃ›OÃÃ”Â¬ÃS~ÂºÂ©=Âµ~dÃ°ÂŸÂ–Â„PÃ®ÂœÃ¿QÂŒheS}tÃ±UÂ»Ã–Â¾Â€Â‚Â·yÂ’Ã¯*ï¼£&nÂ¶2ÃÂ¢HkÂÂœ#Ã€>ÃÃÃÃ˜\\t>hÃ²tY?V\\tBÃÃ¡HxÃ»Ã­ÃƒÂ£h:Âœo\\fÃdÂ·\\tÃ•Â‹Â’ÂŠÃ¤Â´lÂ•uÃ±Ã 0\\bP#Â¦Â§Ã€/IbÃšIÂ°>Ã³rÂ–Â‚C)Â»tP+Â—Ã’Ã}Âº\\roÂ†Â€Ã-Ã±ÂºÃ‡~\\nÂ­"\\n\\f*Ã§#BÂ„FÃƒÂ±Â¢GÃˆr5|Â¤oÃ§->ÂÂŒÂªÃ‘Â”Â©Â¥Ã³Ã¬Â±Ã‡\\nÃ»Â¨>ÂŸÂ¹e[Ã¡Â«\\fnÂ‹Ã¦$Ã¯Ã¾?iDÂ†Â¦#Ã¦<Ã†Âº\\fÃ¶OÂ5Ã€ÃºÃŒÃ²_Â•cWÃ·)!rÂ™`YÃ‘Ã„!Â¥Â¬Âµ:Â‡Ã‘ÃÂ²Ã˜\\nÃ•Ã“2Ãº9Ã’Ã–Ã¬^I$Ã¼Â»Â„Ã»Ã©Ã˜ÂµÂ°Â¿ÃˆÂ‡rÂŒnÃ²Ã¦O6Ã…ÂŠÂ†G?h,Â†Â Ã±NÂÃˆ9Â£-Ã€,"Â¶Ã¿'HSÂµ"NÃ“Ã¿4Â(\Ã˜VÂ³ÃSÃ›:woNÂ‘Ã¾ï¿²Â€Ã¹_re;0S]mÃ ÂÂ²')<n,Â†Ã²Ã…'ÂµÃ„Ã†<1Ã†Ã¢i_mLÃµkÃŒÂ)ÂšÂ¢'Ã¢4Ã°Ã’Ã—Ã¸<)Â¶$oÂ–\\fÃÂ°5TÃ»i?ÂÂ“Ã‚RÂ*ÃˆÂ7Ã¿ÂÃÃ®ÃŒÂ½ÂZÃŠÃ™Ã«Â¥9ÂƒbpY>Â·Tï¼±ÂÂ¯(8Â¬Â’Â­Â…{QDbÂ¥ÂÂÃŒÂ™Â‘Â“PÂŒÂ¤Â†Â¢Â­Â§Ã¼Ã¶MÃ·%>Ã Ã{JÃ³ÂÂšÃ›ÂÂ®wÂœÂ¦Â›|yxjÃ´MÂ¦1Â”Â¾-_Ã"Â†Â£Â¤AÃ½J:~hÂªÂŸÂƒ] Â¢Â¤Â¹cÂ¹yxÂ•ÂÃ‹Â½Ã€Â¨Âª(oÂœÃ¸{bÂ¯Ã™Ã¹IÂÂ…u2Ã£WÂÃŠÂ¯EÂ¹Ã¨C1Ã°NÂ‰kÂœÂ¥Â‡Ãº" ZÃ«Ã£DÂ°|cBÂ—Ã³Â9HÂ¥8?Ã€Â—ÂÃ‰ÂÃÃ«5Ãˆ7"5Ã½ÃÃ½0Â…Â´DÃ†p7ÃÂ½ÃÃŸÂ«9WÂ‘Ã‚Â¬\\bCÂÃŒÃ‹Ã½Ã‹}DÃÃ²ÂƒÂ¦Ã½Ãï¿«ÂšÃ¨#ÃŒÂ„Ã€Â¬M,Â–"Ã«Ã·Â¿mEÃ©R(:Â‚Â»ÃÃ¬ÃÃ–Â¸k<|r+Â–qÂ–sÃ´ÂŒaÂ¦Ã»ZAÂˆÂ’eÃ¢Â«-(ÃÂ¡u\\nMÃ©BDqÃ¹Ã’Ã¡Â½HÂ­MÂÂº,Â„Â¬ÂÃÂ«Ã¿2WjÂ²2_aF!\\nbÃ¡Â¬y?Ã¿2Ã¯Ãº'sÂ„\\fXÂ¡Ã‘Â«Â¦Â9ÃºOÃ—?Â¢Â†>Â²\\bÃšolHÃ¥bÃÃ‡Ã¡$Ã®Ã´Ã™k#DtkÃ¯([Y\\fÃ Â°Â¶ÂŸÃ¢Ã‘Â‰RÂ‹DhÃ‘Â£W(Â³Â¦Ã›Â–Ã³Â¸Ã¸Ãµ\\rÂ°`Ã–ÂŸÃ“ÂHÃ«ÂÃŸ)Ã•ÂˆPzReÂ¡Tt>ï¼°/-.aÃ 3Â’0Ã¾Â‘\\bÃ«Ã­Â‚\\nÂ·ÂµÃƒÃšÂ“Â¶uÂ {Ã»Ã¨1Ã§bÂŠÂ¹Ã¨Â‰Â·Ã‰Â™#Ã¿+Ã˜Â¬_Â Â­I-ÂµÃšÃÃ†0Ã—_Ã»IgÂ„`Ã£Ã†Â³Ã«LeÃ—ÃÃ”2Ã¸fÂ‘Â¢ÃŠÃ€l ÃŒÂ¨ÂÃ§ÃƒvÃÃƒÂŠÂ•Â†Ã¨CÂ™ï¿PÃ(Â«Ãº"Ã†ÂŸaÃ•Â›Â•Ã¯Â´ÃœZ?RÂ¬cÂ¬EÃÂ«Ã²Âª}mOÂ¢Â˜Ã›Ã¦Â(ÂºÃ¢lÂÃ l#\Ã‚|ÂœÂÃÃ‡ÂŒ9SÃ…<Ã²3{Â£p@Ã‡xÃbr0Ã¢EÂ¦mÃ¶Ã Ã¼>\\rZu8ÃÂ‡\\r'Â±wÂ³Â±cÂˆauï¿ŸÂ“Ã,Â¡Â‡!.\lÃªÂrj9Ã©Â Ã…\\nÃ‡}Â£@Â†ÂŠ8&SÃ‚Ã¦Ã‰#KÂ²zÂ‰Â£Ã¿cÃ†|$Â“mfÃ•Â Ã¯m7Ã“Ã•ÂÃ»Ã›Â¢Â‘\\rÃ•Â°qÂ‚Ã·BÃ¶?9Â¼Ã„Ã@Â¾oÃ¾%Â!ÂÃ›q%Â¦Ã¥Ã¦\$.ï¾­-ÃªhÃ†Ã¾vC]TÂ¦Â¶ÃŠlÃ©Â³Â¾Ã¬Ãº'n<Â¥Ã¤Â¦\\nmÃ¹Ã´5ÃÃŸqÂœgÂ±!_-_Ã¨CgLÂ§f=Â¡Ã†a,Â·Ã§ÃœÃ²WvÂ²vÃ¢EÂ„Â–Ã¦kF1ct'ÃÂ´\Â»bRÂµÂR:ÂVÂ€yÂ…Ã¼EÃ¾$Â¨Ã®Â’"RZ)ÃSjJSÃ¯ÂšÂ…xÃ€Ã›ÃÂƒÃ‘ÃÂ£Âœ+Â›vÃ‰ÃœFYÃ³,]u*\\n+Ã¢zÂ¿Ã‰Â…NÂ‘oIÂ•Â±Ã¨{Ã«g.ÂtÃ—ÃªÃ«CPÃ»"Ã‡Â²Â‰Ã§6{Â€s\\rÃƒÂ†Â—Â¹ÂÂ¼CLÂ·Pr:Ã‡dS'Ã™Ã¦:LND[ÃšÃªÂ¤Ã’Ã·Ã„Âšï¾nÂ”Â’Â£5Â¡~Ã…Ãˆ6Ã¤mhÃ²Ã¹p\\nqÃ¦\\tÃºÂŒ8\\rÂ’ÂœÃ\\rH/Ã§YÃ£JÃ Â¿sÃ¿7s!Â¬3PjÂ‘Ã·I&Ã¿q.Ã¡Ã©/Â‰vÂ¿Ã¸K|O\\r,ÂŒ3Â¢r" Â“UÃÃ½Ã“Â·i}Â™Ã©Ã¥Â¬ÂšÃ½n]ÂÃ©EÂÃ©OÃ‘Â¿Ã¨Ã¡XÂÃ„Ã¯ÃªÃ½Ã…`Ã®RÂ…Â™4Â·Â¿Ã­2~Ã«ZÂ˜Â¤Ã•ÂÂµ\\fV(Ã‰>OÂ§Â¾Â¾Â³7,Ã´Â’ÃŒi3Â´ÂuÂ±ÂºÂ¼Â‚Âˆ1"ÂŒÂ“Ãš2V:Ã¯'Â¡ÂÃ@;sÃ´ÂšÃŸ Ã´ÂˆÂ¸Â»Ã¼`Â¨]JÃ°X\\n\\bcÂÃ™Ã?\\bAÃ˜QÃ…\\t7VIÃœÃˆeÃ­[Ã‰Â»\\tj`Â…Ã‡cÂŒGÃºÂ±=Â–Ã¬Â†$Â­1tÃ·aÃƒÃ»*7XÂ‘Ã›y:EFGÂº>Ã [cqZ|p;ÂƒBp*+Â¼wÂÂ†Â¡<Â³mÃ™Â—@ÂŠÂ±GMÃ‡n%Ã²&Ã°Â©Â²A7Â´TÂšÂE&1Â¸;Ã‹YÃµGÂ¿UÂœÂ˜Â»nUpEÃ‹ÂŠS|Ã¾)ÂŸÂ‘n7\\n@Â•Âª*ÃŸÃ²Ã´rÂ»HqÃ£Â±2h&lÃ·5Ã‚8,vmXcÂ¿Â±nnx_4Â¨;Â¶JEÂ®3Ã¥cÃ–IÂ;Ã›Â½`Ãº`Â†0ÂÂ8Â—Â´Â²Â‘Â‡Â†ï¾›8vÂšÂ©AÂŒÂˆ/qÃPuÂ•ÃLÃ•Â¢Â¬,Â±7Â DÂ’Â³Ã—Â­Ã >ÃˆÂ‚Ã­d/zÃˆMDÂ®Ã¥(Â˜t|QÃ‡`Ã©Ã/Â¤BÂ‡(Ã…Â«Â¤MÃ¨Ã¬FbÃ»Ã·4hLMÂ°ÂŠÂŠNÂŒ`-aÂ¹Ã“Â¸VÂÃƒÃ¹ÂÃ®EÂ½ÃÂHNÃ®Ã·rÃ°0cÃ°.Â¬Ã™Âº#`Ã“KÂ£Ã¼Ãº\~_cÃ¦2Gu{0<ÃÂ§pÂÃ¿ÂŠÃ¡hÃ“Ã’\\tÂ§Ã¼bÃ†H(Â³/UUÂ¤Â¾ÂœomÂ‘Â¡Ã…\Ã¼Â†fÃ‚zÃœI"Ã¢^Â¾Â·Â”Â™Â¾Ã”cÂ…ÃÂ Â¹ttï¾šÂ¦8ÃœÃƒÃ¸(Â¾\Â"Â„Ã³Â‹-ÃœH4Â¿ÃÂ—s8Ã£Â«Â¢1Â¥lÂ¨ÃµÂ¹2eÂ¬1Ã½&ÃÂ¼ÂÂ¼ÃŒÃŸ\\tkÃŒEz#ÃªÂ®Â‚)Â¤Â‹\\rÂ’Â§dÃ¦Ã„Â¹Â‰y"jÃ”5Ã„4Ã¶ÃÃGÂ²Ã¤Ã±`Ã¢Ã¡Â‘Lq"tÃ¢Â—ÃŒj\\tiï¿¯ #MÃ¹ Â„ÃŒ[ÃŠ?pÂˆOÂŠ\\bÂª+ÃÂ¯PÂƒÂŸ&-oÂ¤Ã£Â¼q=)QÃ¿Ã€0pÃ•Â‚6; CÃ/\<Â°Â¨0'JÃŠ/LÃÃ™aÂŠÂ³ Ã¤ÂÃ‡7ÃŒf3Â¯[MÂ¬VhÃˆÃœÂ¨ÃÃ¿=ÂšÂ§\\r@Â¤NÂŠTÃ½ÃŸoC-Vï¼Ã°ÂÃ¦Ã‹Â¶F'Â–Â©UÂ–]Ã¯Â¬Â¾\\fÃ¦ÃŒÃ¥&Âµc$Â€Â—_Ã¥Â‡ÃƒÃ¤ÃƒvÂ¶Ã½Ã˜7AÂ½@Ã®Â‰Â…ÃÃŒÃ¾KÃ‡1PÃ‡qmÂ³\\tÂ<4Â§Ã’Â«+Ã¦Ã¬Ã˜-=Ã” C\\rÃ`WÂºÃµÃªÃºaÂ•Q"}soÃºï¼ŸpÂ˜Ã»Ã¹Ã½RgÃ¤Ã¬Â\\b.7ÂÃ¨Â’Ã¥usÂ‡Ã«B:Â;Ã†Ã£_ÃŒQ7Â©SjUÃ¯ÂÂ…Ã„Ã©Ã“bÃ‘Ã_ÃŠÃ?vÂ“ÃƒtÃ¾8`Â´GÃ¤Ã´Ã«Ã…8Â‹p_Â“Ã²HÂ¬Â‰Â»ÂŒÃ£sItgSMÃ­Ã Ã Ã½eÃ¯/*gÂ¶Ã¼,KÃ¾ÃŒÂ„Ã•Â§Â¬ÂRÂ‹Â†>]Ã¸2Â¹Ã˜Â‚~ÃƒÃœ,Â™[Ã³<9Ã™Â³Â™nÃ´^cÂ¸ %\\tÃ±Ãª)lÂ‰Â‘Â›Â‡VwÃ•Â½>Ã¶ÃµZÂ©~Â•Ã…PD0b=Ã¨4@Ã€s"|ÂÂ¦Â³ ÂŸ\\b}|Ã²Ã•\\f$ÃµÃŒÃÂ½oÂšHÂ»}c;QÂ¸bÃ Â”2Â‰dÃ¤Ã¾Â¡SÂ˜Â¸Ã¥fÃ­Ã™ ÂµÃª)eÃ§Â­gW6xWeBÂ´s(Â¶BÃ®>}8Ã½ &Ã§Â¶ÂºnÂ°ÂÃ‚m ÂœÂ–Ã’Â‹Ã‡YWz,Â¡\\fSv&Ã«ÃƒDÃ·X)Ã²Ã»Ã¸Â`{Â½}Ã©;Â´PÂ©Âƒ9DUï¼³EÃ™ÂÃ¿Â£ÃœyÂ"Â¡ÃdW-Ã¬v!Â†HÂŠ,EÃ»Ã¤Ã BaÃ·ÃªW\\rÃšiÂ´Ã½Â¡Â©Â˜=Ã4Â—=Ã¯^Ã±ÃªzeÃ’OyÂªÂ„Ã2;R?F*ÂDBAj5Â‡Ãª>Âµ5Â–ÃŸKÃ˜ÃÂ¹Ã­MA;Â²Ã¼Â·mJ!`Ã†Ã¾;Â€r\\f31\\fÃºÂ‚Ã®ÂŠÂ¡EÂ¢~Â•ÂºÂ¿rÃ£ÂœÃÃ¥~Ã…2weÃ”$Ã—Ã—Â„\\rvÃ‘yLÃ‡Â§Â«SdÃ¥Âµ Â³Ãºq~Â{Ã”;E0Ã©tÂ‚'h}Â\Ã‹Ã³Ã‡TÂ¼|e'Ã¤Ã†Â“ÃºUÂµJÃ‹ÂÃ»3Â¿uÂ¹ÃÃ†5Â2ÃšOÃ¶CÃ¸hjÂºÃ’z^Â—ÂZÃœÂ¼7$Ã«FAI\\nÂ˜~Â–Ã—Ã¢9Ã•Ã³T&WÂºÃ¹Ã´Ã³VÃ½Ã…ÃºMÂºqlE-k6Ã„Ã¦;*Ã©Â„QÂ®Â½Â¡O\\t/Ã‰Â“Â€O[y\\rmÃ­,ÃÃ²Ã—hmU4Â£gÂ¡ÂÂ¬Â›Â¼m/QÃ§Ã›Dï½¿\\rÃ›EÃƒ=Â•wMÂ Â€Ã‘FÂ–TB\\tÂšÂ¨Â³Ã©Â³Â¿\\ruOÂªhÂ¿ÂÂ€(]ÂÂ˜ÃœÂ«Â”Ã¢PBQÂ¡WEÂµsÂ‹6gvÃÂ‚ÂˆXÂŸÃ„Â´Ã°Ã®}>RÃ´\\rÃ…ÃŒÂ¼Ã¬Â‡ÃÃ“ÃÂ¿Y}Â¬Ã«Ã®Ã³Â¨Ã¼hÂŸÂÂŸÂ§ï½‰Â«Â±8{Â•9Ã©yÂŒ6k)Â°Â‹+CÂƒÃ’Ã Ã–\\bÂÃ¶ÃÃ+2ÃÂ‚Ã™ÂrÂ¢6ÃƒCÂ"Ã³ÃYÃ¡r@JÂ³Â¼Â†pU@VÃ½ybOÃHÂ‡V<Â†Ãº$JÂŸn&Ã€Ã•ÃQÃ®}Â¼Â½Ã˜Â¡ÂÃ¯Ã’Â®Â©ÃÂ­^ÃœuÃ¶Â‡Â»ï¼¿p|ÃÃšÂ±"}Â‘Â²U,ÃªlYW2Ã“rÂ½Â’ÂƒÃ‡Â¢0,Ã¶Â¤Â“Â«6Â¯Â®s_Â…EÂ¬Y\fÂƒÃƒÂ¶ÃŒÃ»-Ã³\\bÃ©Ã‰Â‘$Ã•.Â¡Ã¥=BLÃ¥2Ã¹GÃÂš<(Ã¿:ÂœBpÃ†Ã‹\\t6CÂ¦ÃœÃ‘ÃŒX,ÃšQ\\nÃ…Â±ÂÂ“Â¹=Â§Â“Â§"AY[Â´Ã¾eS,tÂºiÂ®KUÃ¬Ã±3Â„Ãp:3Ã°OÃ‚3:Ã Â¡qÃ–KÃ®ÃšQ4ÃƒÃ”\\n-krÃ‚&Ã•Â™Â°"yÂ´ÂªÂ¸ÃÂ¬Ã•Â•DÂ¨y 88Â­Ã¥J=Â±Ã´cÂºÃ²\\nssÂ>Â£ï¿‚,<Ã>!ÂÃ±Â“Â°Ã†Â…nÂ—Ã‹0xÃ¢Ã¤Â¾ÃƒBÃƒÃŠÃ‰]}Â¼dÂ”Ã½Ã€Ã£/Â±Ã)U\\nHÃÂ·8Â¥I(bTÃÃ¸Ã•Ã½Ã‰/nÂªXjÂ»Ã·Â¾Ã¶ÂšYfÃ‹OÂ‰Â¹ÃÃ·Â«Ã¾ÂSÂ”Ã„kÃ–ÂªÂ8ÃœpÃ©Â‘tÃÂ‚EDIlÂ¾ Ã¸ÃºÂ½Ã¿c*Â´UÃœw4Â¿Ã†Â£Â¨Â•ÂI:gÂ¶Ã§Â€ Â»ytT$`Ã»ÃÃ·ÂºzÃ¯Â¦Â‚Â‚Ã•ÂÃ¨Ã¶Ã¡BÃ·\\bÂ¸Ã«OÂÂ¸Ã^Â”fÃÂ(Â¡vÂÃªZÃ¾;$Â’ÃÂ´Ã™Â­ÃÂ¼\\tÂ´LÃŸÃ“Ã§Ã­Ã¤xÂ™2WÂ¢Ã£Â¢Ã¨3|Âš[ÃÃ©Â‰Â¸Â¾Â§wÃ‹Ã£ÂŸÂ¾S}WÂ„Â£Ã¡tÃ—Â¨Â¸lÂ†Âˆ$vÂ›Ã…dAÃ¡ÂÃ„ÃÂ¯Ã‚NÃ Ã¶ÃŸÂ‡%Ã¾EcÂÂ„Ã¶7`-xÃŠDDÂ§GÂ­Â¾Ã”Ã¶Ã'Âœ\\rGÂ› #Ã¸Ã’\\tÂ¶P4kÂ‰EÂ§GuÂhÂ“DÂ¬xÂœ`Â±ÂÃÃšÂ¢Ã·uÃ›Ã.Â„hÃœ*Ã©Ã—Ã±ÃYÃˆ7ÃYÃ§Ã¦Â˜qgÂškZÂ˜2Â¡Ãº*DÂ”|U9\\rÃÃ&ÂœÂš:=yÂ¡Ã·8Â«{Ã‡Ã¦Ã…Â Â¿,Â¶Â¸Â <Â;ÂªÃœfMÃ¾Â–Ã‚Ã†Ã‘BÂÃ´Ã“Ã—Â«jÃ»XÂš+(6Ã—Ã»Â„qÃÂ¢cÃÂ©Ã‡Ã‚Â¿0Â–ï¿Ã’%-Â·&{_Â€ÂµÃ†YÂÂªiBjÂ¾Âº,mÃµyxZÃÃ©`Ã§Â“Â€\\rÂ³Ã‡ÃDÂ±Ã–8Ã‹\\bUÂ­Ã£ÂÃ‹mÃ¬;Â’Ã­Ã¯Ã‚'FÂ XÂ¶Âµ@#UÂ{ZESÂ‚\\fÂ—Ã•\\t RÂ—nÂµÂ”,Ã·WÂ¶hÂ´Â¥ÃªÃ‘Â¬Â¿Â’CÃ³ÂˆVÃ†Â‰^yMÃ»e\\bÃ¥}Ã½Ã§{kSÂ‘\\b'Â‘oÃªÃÃ°ÃˆÂ ,FÂ­Ã–[Ã™Ã¸FÃŸÃ©3Ã¦lÃ¿Ã—Ã¢+ÃˆÂ”BÂ”Â³Ã·Â¹Ã—LÃ®7nÂ©ÂŸWÂ®Q[Ã©uÂ¢Â¸PÂ´Â‚Ã¨Ã—Â²[m"Â©Â¦ÃÂ­@s1Ã„WoFÂ½cH4?AÃ©ÃŸÂÂ“=Â™Ã¹!PÂ™Â¬2$hÃ¼#Â‹\\fÂ»{B[_Â¸ÂšÂ£WPÂ£ÂŒÃ…5Ã´ÂeXYÂ¹Â¤zÃ«KkYÃ€,Â‡Â‹IQÂ…;,T Â–Ã‰Ã²Ã€;a\\r=Â§E#Ã¾Ã•ÂÃ€(PÂ‘ÂœÂ²Ã©Ã¤Â·rÂ‹ÂŸ-.ï¾‰kz+Ã¿Âƒ]ÂvanaÃ¡ÂÂ»Â§ÃŒÂ…}Â†8Ã­4,Ã«a{,s\\n_PÃ­Ãº]Ã¥ IÃÂ”{DUqÃ„Ã­Ã³)ÂµÂ½Ã¸ÂªÂ²$^X\\bqÃ¡ÂœÃ£Â˜ÂˆÃ—]ÃªÃ·mÂ·"?)Sho|Âº.Ãš\\rÃ ]Âš\\tÂ‚0TÂ·Â‚J=Â«Ã¼WÃ¼ÂÂ¹gOK\\feÂ®ÂµÃ¬;Ã‡ypÃLÃµjqÃ–Â‘Â¾zNÃlÂ—Â‡Â€8Â€Ã†ÃÂ»Ã—Â³OÂ±Â€Â°Ã©TF Ã‹Ã–Ã’Â—VÃÂZT-Â¶Ã«ÃSÃ¹Â³Ã‰Â£ÂƒÃ‰NnÂ‚Ã…4GÂ¥Ã‚ÂšÂ³Â°@v,Ã¥'LbÃÂ‰Ã¤yÂ¶Â„Ã’Ã¯RÃ¾ Â¬ÃˆÃ£ï¼ŠAÂ»5Â”Âˆ"-\\tÂˆÂ‰Â¨UÃ¢Â‘ÂŒÃµ/Ã\\rÂ™Â‚)Ã³FÃ»"i$"uÂ£kÃ¤oÂª^`Â¯\\bJÃ±Ã­Â¦Â¢Ã“Ã‰Ã¦Â¾Ã’l?Â˜Ã—2Â¸PÃŸÂ±ÂšÂŸÂŒÂ¨Ã‘sÂ¢|Ã Ã‰y}bÂœyÃ¦Â¡Â©#m/=Â¤Â¢Ãš@)M?+Ã«j qÂ•ï¼²]Ã¸Ã’ÃÃ‡Â™YÃ•ÃŸiÃ¡Â†Ã·WÂšURÃaÃ³_Ã²UÂ·Ã–TÃ RÃ¼Ã‡;Â¯ÂŒKÂ„Ã€Â™ÃA?Â§Ã¤Âƒ,0&Â—ÂÃ”Â«Â®ÂœÂŸÂ‰c_Â¢ÃŠaÃˆrÂ¢bhÃZÃ‡&xiWyXfÃ°Â¾Â€Ã¨Ã—Â¼Ã…ÃÂ¶jÂ‘Ã®Ã•AMï¾Ã› Ã’Ã¢67BÂ¾CxÂ¡Â˜Â°IXÃ¯Â¥~Ã²:Â®I\?ÃÃ’ÃœÃ¤\\nÂŸ$ÂµVÃ¨| y]y?0Âš"WBÃ¤Â·Â¥@Ã€VÃ¶ÃÃÃ”pÂ\i@7Qy!ÂœÂ‡ÂˆÂ£Ã¸lÃ¯q"Â­ÂÃ6ÂƒÃ•ÃµBX(ÃµOn5Ã¸ÃŸÂªe}cÂ¨Â±Ã†UÃ¿Â‰Ã–Ã·eÂÃŸ$Â’Â·Â¯<Â•"Ã®Ã›CoÃ”Â©_Â¹/Ã‹Ã²Â±s<Ã”ÃÂ®ÂÃ¬@HjÂ# \\r?Ã‚7ÂƒG+ÂÂ…hÃ›ÂŒÂ»Ã—+ZÂ€XiÂ»Ã­@ÂŸÂ#t\0Ã´rÂÂ±ÂºÃ¥HAtÂÂ¹5Â’ÃÂ€ÃœDÂ³ï¼ŒÃ“ÂŒ+\\nÂ›!SÃ—Â—ÂÃ˜rÂ‘DÃƒÃ²2-jÂƒ?K iÃ®Â‘WÂ”Â¯ÃsÃ‚#ÂªH=ÂºÂ¯ Â˜PÃ«Â¨<PÃ­*_D&ÃˆÃ ÂÃ Â³Â¦Ã”ÂšÃ¬RrÃ·Ã‡oÂ–Â¿\\rÃ±UÃˆ Ã¶Ã"CÃ‚NÂˆÃ¡Â»{Ã­Ã•Ã ÃÂ»Â[Â¶BSp(iÂjÂ€Ã´bÃ—Â´+(Â®Ã«vÂ™Ã§Ã„Â¶Ã†G)Âƒ)Ã‹Â˜Â—Â°Ã¼:Â‹<Â¡Â§Ã¸<7ÂIÂ¡}ÂÃ¶Ã½ÂŸ"(vÂ¡.c.b3Ã—OSD(Â–ÃÃºÃº]TÂœtÂ¶sk&Ã ÂµÃ°QÃ’-wÂ¥3Ã¥Â‹jÃ¼ Â‹2QÂ°iÃ¹wÂ±GÂ¤Â³Ã•q7EyÃ™5ÃÂ€%"#ÂÂ•,Ã„ÃºÂ…ÃŸÃ¬Ã­Â…aÃ¿%DÃ§Ã¼Â¼)N|Ã‰Ã’YÃŒ>Ã‡Â£Â\\fÂ~Cj>ÂRIÂ½AcÂ­Ã´Ã»>wB,Ã…ÃÃ“ÂšÂ¾Â°aÂ™Ã¬IÃ\\fvÂ³jam\\rÃ¶bgaÃ†ÃƒÃ“Ã‹ï¼ \\bÂ›ÃƒtUÃ½Â´ÂŸqd$Ã’ Â[\\n+ÃºaÃ¹Â†Ã‡4Ã¾hÂ¤HÂÂ—Ã½ÃÂœbÂ˜]Ã®Â 8ÂÂ´Ã¢Â·Â‘Ã¢S*\\rqÂˆyVÃ†Ã£QÃ»SÃ†GÂ¬ÃºÂ‘[OÃ„DÃ¬IÃvÂ´jSnÂœXtÂ‹Â»Ã¯ÃŸqÂ…)[CÂˆÃ­ï¾ŒÂŠÃÂ™Ã˜fÃˆ8pXÂÃ¥W`yr}ÂUÂ”!ÂeÂÂ¤T]Â·Â³Ã»Â‡Ã•Â–Ã Â»Â—Â™@Â¯Â¤\\fyÃyLÂ’^Â±sÂƒÂšÃ¶8cÃ‰Â¤VxÂ½_Ã€@wÃˆ.KÃ®Ã¢Â©Ã—ÃÃµJÂ¿LG">ZÃ™M=Â‡RFÂŒÂ°Â±qyPsÂ:&Â§Â Â‚Â‡1Â·Ã¢+RÃ‘Ã±Â™fbÂ“eÃ€ÃÃ¬iÃ“Ã¿7.Â„Â¿1Â¢Ã¶\\nSaÂÃ‘Ã‡{:**=UÂ±Ã¹C$yÃ'%ÂÃ©Ã€Ãƒ@i9Â”ÃºÂŒVÂ¸ÂÂ¹SCÃŒÂ‘Â»Ã¯AÂ¨Ã¤*Ã…~6 Â°l~Ã„lmÃÂ…8Ã”Â°ÂŸÂ”Ã˜Â¯ÃŠÂ°nHÃÃ£Â†OÂ•Â®Â¾Â¹Ã³ÂˆÂ¾Ã’KmÃ¦Ã½ÃœÃ¹=Ã5Ã¾Ã·Â†Â±Â—TÃš=Â®ÃÃ•Ã¼1KÂ²XÂ€ÃºÂ²=9Â€MÃ£65'Ã´rx\\tÃ˜^ÃŠÃ§xÃ¦'MWeÃ©Â¬Â…!Ã‚$=_EÂ“ÂÂƒ\\nÂ¿6Ã½Â– 'ZÂ¯Ã¾Ã½q7ï¾Ÿ.Ã‹ÃŒP)0ÂÃ…'Ã¸wÃ¦c@Ã‡\\bÂŠÃ¬Ã¦Â¯Ã`ÃµÂ±ÃÂ¬Â²TÂ¶$Â€17S=<xÃµÃˆjÃ˜Ã‚Â¹Ã¡yÃŒÂ¬Ã–0Â¾Â†Â§(Ãš3Ã„d9Ã©=8Ã–UÂµÃ±w"Âƒ;Ã©'ÃÂÂ½DÂ€ÂÃšÂÃ·Â·\\tI+Ã¹ÃŒKÂ‹\\ty}Â°>ÃÃºÃ•Ã©}:Ã¨&Â¸Âª9|-8w&7\\t;Ã§Ã“dx\\nÃQÂ˜Ã¡\\bÂsÂ¾bÃ˜xÂ@Ã«Â‚(Z1rÂ²Â„gÂzÃ’*]5ÃŸb\\rUÂm%Â•>Â‘FÂ¢Â•]OÃ´"]rÂˆgÃ­Ã¯bÂ©Ã€Â¦Â…Â§UÃ…EÃ¥fÃ…YÂ©4Ã#DÃ¥Ã‚Ã°Ã»u9Ã¦&!ÂŒÂrÂ´Â¦OÃ¥KnqÂ€qÃƒSÂ±spÂ˜Ã¡`Ã¿&Â®*{a-IÃ‰aqÂ¼Z@SBÂªÃ§Â‚Ã€ÃÂ…Â§(`Ã  Ã”KÂqÃ˜Â¹Â‡Ã‰u5ÂˆÃœÃºKrÂ®\\bÂ²Ã°Â‹/`Â¾Ã”Ã—Â—\\fÂ–Â¶%Â³Â‡wï¾®ÃƒÃ‚_ÃÃ¢6ÃªÂ¬5LÃ¥Ã@Â¿B}Â¸Â‡\\bbÂ¡oÃ‹2Â¦Â°Â„$/Ã‘beÂ¥\\b@Â¸0Ã«Ã¨ÃÂÂ½Ã¦Ã™~Â±*='TÃ¬G\\f-Â‰]Â„B5Ã«7)Ã›Â”ÃºÂÃ·Ã»ÂÃÃ¨BÃ¶ Â«Â—WÂŸÃ‡ÃšÂ¡6ÃÂ¼OÂ±LK.ÃµÂ‡'Ã¬ÃÂ 6_u.Ã•Ã”Â‰yÃ‘ÃGÃœÃ½BrIÃ´ÃµÃ»Ã‚ÃˆÃ¡Ã‡!Ã€Â€Ã³mAÃ©pÃšSÂ…Ã©#$Â¿ÂœÃ¢Â¦ Ãœ'Â¾Ã«{KÂ–='83TÃ‡bÃ¦ÂÂ˜#Ãƒ4oÂµ g\Â€yzÂ¦Ã Â§`Âš&ÂÃ‡NÃµ{Â€KÃ–Â«Ã¶Ã­Ã©'
    //   10: dup
    //   11: astore_2
    //   12: invokevirtual length : ()I
    //   15: istore #4
    //   17: sipush #16195
    //   20: istore_1
    //   21: iconst_m1
    //   22: istore_0
    //   23: bipush #56
    //   25: iinc #0, 1
    //   28: aload_2
    //   29: iload_0
    //   30: dup
    //   31: iload_1
    //   32: iadd
    //   33: invokevirtual substring : (II)Ljava/lang/String;
    //   36: jsr -> 141
    //   39: aload #5
    //   41: swap
    //   42: iload_3
    //   43: iinc #3, 1
    //   46: swap
    //   47: aastore
    //   48: iload_0
    //   49: iload_1
    //   50: iadd
    //   51: dup
    //   52: istore_0
    //   53: iload #4
    //   55: if_icmpge -> 67
    //   58: aload_2
    //   59: iload_0
    //   60: invokevirtual charAt : (I)C
    //   63: istore_1
    //   64: goto -> 23
    //   67: ldc 'Â§Ã8Â–\\nÃ½TÂ—Â£Ã‚Â†Ã¥kÂ¹>_TyÂ®Ã¿ÃŒÂŠQÂ€ÃˆÂµÂš`Ã§B^8Ã™Ã©3Ãª4ÃŠe*Ã»5yÂ”UxÃœ^+Â«Ã„ÂµÃ¦jÂŠÂˆÃ‘_Ã™f[Ã¿BÃ¢Ã²ÂŒ|OXÂ­Ã½Ã®Ã®Ã·Â“Â¹hÂ•Ã†DÃ°HÃ²Ã‘Â†Ã£Â£\\fÃÃ°Ã„(n\sÃ£Â»yTÃwÂ¿Â¼Â¥Â‚Â·Ã¹8i_Â¡ÃˆÂ”Ã¹Ã«ÃÃ£HFÂRRÃˆ`Ã‰EÃº.pÂ'Ã‡Ã‡_4Â¡WÃ‚?Â¿Ã•\\tÃƒvÂ‘ÂŒNQÃ¬Â£Â¤MÃ€#Â…Â—Ã”ÃƒÂ­aÂ“\\nÃÂ©kxÃ·V3Â±MÂ’Ft$\\rÂ´] Â¼Ã±Jï¾“Ã›Â™V2PdÂ¥]hÂpÂ­&ÂÂ–Ã·Ã™-ÂˆÃƒÃƒlÃµ!Ã¦ÂŠviÃPÃ¬Â›g>HÃ‰ Â­pDpÂŒÃ‹Ã¹Ã¯Â’Ã±ÃµÃŒÃ¨55VÂÃ‰Ã¶\\nÃ¼Â€$m+yÂ™~km'VÂµÂ¨Â•Â¥Ã´?Â³Â‘Ã¿v45Â¿Â¿Â­Â¶Â±/U&2Ã±Ã—Â™Ã¼Â‚lÂ¨`oÃœÂŸÃ£Ã¼fÂ·ÂZÃ¹A,*QD{Ã ÂµÃ™mOÂ¿Ãw7DYNÃ³1Â£Ã‰Â­Â«.Ã‚Â„YÂ¿\\fÃ‘Â Â‘Ã‘Ã­Ã¾ÃŠu&Ã Â•ÃŒÃ¥fOÂ–3Â›EÃ’Ã‹%q9vÃŸWAÃ¬ÂšUÂšÃ—;cÂ™Â—g\\bÂuÂ§OO4QJpÂœ~iÂ®0FÃ‡Ãœ'Â¥wHÂ‰Â˜Â–Â¿Â´7Ã¦; nÃ¨Ip}GYÂ·xÃ¯Ã Ã·Â¹ÂšrÃ­ 4Â–ÂŒÂ½Ã®^Â¨ÂªÂÂ¹0Â…RÂ»ÃœÃ‘Ã#fÂ .Â5[vÂ™?v4=ÃŸÂÃÂÃ´Â±@%Â²Ã¦Â¨Â½Â›w\\rÃ±ÃµÂVÃ+Ã‘Ã£2JÂ®|4ÃfÂ±Ã™Â‹\\tcM7r+Â·Â«-C\\riÂ‰~ÃÂ¨Ã­ÂÃŒÂªÃ¹Ã»GÂŸeÂ¼`ÃƒxÂ Ã®OÂªÃ„@Ã¹Â¢RÃ²Â„Â¤Ã%gÃ“lÃ‰Ã Ã«Ã˜Ã¡Â…Ã‰Â”Ã^Ã™Ã›Â¿ÂµÃ€xÃ§jÂ‡g\\fÂDÂ­Â¼FÃ“Â†Ã¬ÂªÃ¡PÃ¥3Ã€xU9Ã‚ÂƒÂ¿Ã¶Â‡@Ã‚xÂ¸Ã´Ã¢Â‚ÂªcÂ‰Â¸BÂ§zÃ´eÃ¨SÂÂ›Â…6!Ã­ÃƒÃ©w Ã¼Â‘/Ã†dÃµÃµÃªÃ›JÂ‚Ã§Â§DSÃ¿Ã–Â–2dÂ\\rOÂ‡u<Â¿|Ã´\Ã«Ã«]EÃµÃ—\\bÃÃ—39Â•Ã¨Ã¿QSÃ’=CÃ¹^(7Ã˜Â€Â/Â‰Ã´Ã¿Â|f-Â Â«[ÂŠ3*Ã·zÂ¾Â‹]LÂ‹ÃÂ˜Â«Ã…jÂ£Ã†h(*Â¾zÃ°Ã—wbÂ–ÃŠ ÂœÂ±XÃ»Â›[YIÂ‘OkÂ›sETEÂ¹ÂÃ Ã†uÂ²Ãµh [4'@Â„Â Ã¹[]ÂœÂŠ Ã³ÃŒZHÃ®Â¸~OuÃµbÂÃ‰k@Â±Ã³Â•<%Â‡ÃÂŒ[Â¸Â„ÂÃ¬PiÂ‰Âˆ\\fÃ”Ã±.Â•Â¸ÂÂ³XÃ¤Ã…&ÃšÃ3IÃÂ€ÃºÂ¿Â±ÃºÂ®\\t[|Â—kbÃšÂ½Â¡3Â¯|Â”:Ã•Â¿>dÂ¼Â‘RÂ Ã…Â±Â¿Â¹5Â¹L8rÃ«VÃ‘Â‡Ã­Ã§Â©<<_K<9Â“Â‹R-Â“?qÂ³Ã FFÃ‡Ã„UÂŠCKEg8Ã’MÂ“Â¡ÂƒÂÂ—ÂÃ±Âˆ&Â ÂºxÂ«Ã†}ÃšÂ‹Â‹Â˜Ã˜5nÂ½ISPÂ¨Ã›Ã–V,GÃ¸QÃ¼ Â‡Ã¤Ã§WÃK|Ã¬Ã®Â®e[\\bÃ—.ÂªVÃ¾Ã²QÂ”Iyj\\fÃ¦Ã Â£Ã¢Â¤Ã§Ã” \\bJÃ·ï¿œÂœÃÂÃ¤hLvÂÃ”ÃÃ”7TÃÃCcÃ±Â©?)WÂ»FUoÃ±MTÃ¶_ÂºÃ©tÂŠÂ·'Â†H"^Â‚sÃŠ.Ã—BÂ­|^ÂÃ¡Â»Â§@Â­ÂˆpJÂ‹8?Â·1Â­Ã°Â§"Â¯xhÃ¢ÃŒHÂY|AÂ„78Ã•Ã´#ÃŸÃ¹Â®Ã„Ã¡xï¼™Â¦cÂ‚ÃšÂ€\\bÂ”Ã­HÂ´+ÃÂŠÃi'Ã‹*"Â¯Â±Ã™`UÂŠÃ¤ÂTbÃˆÃ´ÃŠÃ’Â‚4Ã°hÃ¦Ã¿ÂŠP7]HAÂ¯tÂ‘ÃªÂ³ÃºÂ§Â¢Â€4Â¡:Â–<Â¡Â³Ã©Ãµw6ÂÂ‚nÂšÂ¼Ã¹p,ZÂ¬&Ã€Ã¯8Ã³Ã„ÂŒ*{Ãµ^Ã¬GÂ…\\fÂ”ï¿³dzAÃ›Ã®ÃÂ€Ã‘Â£Â£Ã¦m.*ÂŸÃ¯SÂ·ÂÃ´Ãƒ-Ã‚q=JDÂÃŠ)PÂ™]Â­XÃˆÂšÂ¾ÃŒÂ™\\tLÂ½Ã¬ÂƒZÃÃ@Ã Â³:Ã¸Ã¼Ã‡Ãˆ(0Ã•_.<IÂ’Ã¹ÃÂ“Â™Ã¨ÂÃ´;ÂxÃ¶Ã²LÃ»YÂ¹W6Â‘,>}(Ã“Ã¼Ã›ÃµÃºÂ‘Ã­ï¿‘Ã‰Â‚Ã™eÂŸc-Â°Â¸Â¢Â[@#nÃ\\rfjHCMÃŸfÂ´aÃ¦yÃ“\\ndÂ§Ã”Â›Ã”Ã Ã•\Â°Ã€Â¥bVÂŒÃ¨cÃ´Â™RVÂ…ÃÂ‘Ã•-VvÂ¯Ã¬Â²Ã—ÃÂ Ã„ÂŒIÂ›Â„Ã€Ã¸ÂšÂ¼lHV1Â²ÂzÂ¸Â¯0h>Â¬Ã¸ÃÃÃ¤'Ã«Â†Ã¦cLÂ§9IÃ«nÃ’jIÃ¢hÂ§Â‹3Y,ÃsÂŸÂ¥Y"Â¸Ã¯T;KxÂ·ÂDÃ’Ã«ÃÃ³Ã’Â½QJÂ¡&Ã Ã·Ã‘vÂ¿Âœ85Â“Ã£Â…ÂšÃ«TÂ³Â²BÃŒÃ™<Â˜ZdsÃxÂƒÃ€ÃšÂ¬Ã¯FÂ“Â‘mKÂ¨Â”3Â§'s9'Â–Ã¼VÂ‘Â›Â=Â³Â¾ÂŸZÂš8Ã­ÃÃ°Ã°ÂTwÂ­cÂ±{ÂªÂÂ®ÃƒCÂ§`ÂŸGWÃ’\\fÃ‰Â°Â…Ã•9ÃÂ™-.#0ÃµtÂ®Ã”2Ã¿G$HÂ›Â˜(Â§nÃ©k)LÃÂ±pÃTs)Ã”Ã½JÂ­*Ã¬Ã“Ã‹tÃ¹Ã¿dÃ¶<Â“iÃ¡Â³(i,ÃƒÂ³Z0Ã Â¯l\\rÂ£\\b1ÂºÃ€cQÃšWÃ‡ÃÂ´Â†\\nÃ‚;Ã­Ã¿Â£Â‚Â£Â†a#DÃ68ÂÃ¿0Â†ÂP1Â§L+9=ÂˆÃ¶Â«L0|*Ã’Ã¨Â®Ã¿"jÃº72ÃŸa8Ã¡jwÂ‡ÂÂˆVNUÃ„Ã­Â£ÃŠ&Â™7Ã—ÃŸÂ§Â…\\f[hc1aÂ°Â¿Ã Ã´*zÂ¶<l)Ã¹ ï¾£Ã²lÂ‹rÃ™YtÂ\\fÂ…Ã¨`_\\tÃºÂ…q9FÂk\\tÂ¬Ã Ã‡oÂ |8;Â©ÃŸÂŠeÃ…Ã—Â˜Ã¬Ã¡ÂÂ¡E2Ã“YÂ™Ã†VÃ¸OÂ˜6)Â\\tÂŸ3FÃ‰Ã"_Â¾Ã¸oÃ“JLDÃ“Ã²!Â¨\\bÃ°|Ã”8Â‹Â¦Ã£Â²Â¯Â—*P ÃÃ¨Â’Â¯nï¼Â¹Ã+Â£LÃ¿Ã‘Â±FÂœiÃ‰r#L:Ã—ÂœÂ–Â‡7ÂšÂ£Ã‘Â…Ã’Â¶XÃ–Â«IÂÃ‰.Ãµ'2WÂƒ |ÃÃƒÃÂ±WÂ—Ã„Â˜?03Â4Â™ÃŸÂ‘Â¦Âƒ+Âº/Â”r.m^\\nÃ‰Â›Ã½R)Â´_yÂ‰Jd?Ã¦K6MrÃ1e0dÃŠc\\tÂ¤rÃ…SÂÂ³Âœ~.Ã¢\\bÃƒÂ™Ã£Ã¤jÃ±Ã“Ã¨Ã‚Ã™ÂºÃŒÃ¼Ã¥FÂ”Ã‰Â¿Ã¾RÃ¨R0Â¼ÃšHQpÂ”Ãªf:Â¼Ã§ÂÂ¯;ÂÃ™Ã‡Ã¡ÂœÃÂ¿UuÃ­Ã’Ã’Ã«1Â¤yg@Â£ÃŠoÂ€Ã†Â¼ffÃ¶ÂºÃƒÂ¢Â„Ã­WU.?Â¼Â \\rk:1Â¹Â‚Â°Ã¥^bÂ†Â©OÂlR~ÃœOÂÃ›Â²\\fÂ;Ã¢ygÂ¿32VzÃ¦TD(cÂ–Ã±oÃ»xcNeÂ¡Ã :AÂ³Ã]Â§Â±zÂ¥Ã°ÃªÂ°\\bÂ¯|XÃ®RÂ‚(Ã£-Â‰Ã“'Â¯Ã]Â·Â©E`|rÂšÂ„Ã¡}Ã–ÃŠNÂ¡Â“Â£~Ã»Â—$!ÃœÃ’ï½‰Ãˆ#8YZÃ¶Â¶kmÃ©Â£GÃ­;Ã•Ã·i.Ã’CÂ«Â®Ãºg+Ã¡ÂœÃ»qÂ·Â¹kÃ¶.|-}\Â„Ã©9Ã¥Â‚ÂÂƒÃ»Ã˜PÃ•Â³GÂ~}NÂ²Â@ÂÃ©JÂ”SÂŸhÃ‹OoÃ‡Ã’ÂÃÂ¶Â–Ã˜H(\\n%Â³ÂÃ“Ã£Â€}Â­jÂµÃ–$`ï¿–ÃºÂ“ÂŒ<Ã XÃ¬xw\ÂºuÂ•R~ÂŒÃ¸8ncÃ®Â¨Ã¥Ã…F\\tÂÂ°RÂ­yÃ”yÂÃ˜6j9MÂ—ÂŒTQWOÂ”Â§\\n;Ã›Ã–sÂ›Ã‘kÃ”Ã“J}=`\\tÂšZÂ·Ã›ÃÂ›Â¹WN\\tÂ€ÂÃ„NÃ¹g\\fgÃ‹ÃšÂ½Ã´Ã´EÃ§)VÂ¼Â0+ï¾²Ã¾Ã–Ã„Â¿Â½Ã‹Ã£Ã„UÂŸÂ;Ã‚}43zeBÂ±Â›Ã¤Ã²[\ÂŸÃ†9\\nÂ„Ã…Â7?wÃ“{ÂÃ4Ã©Ã¾Ã’Ã·Â½\\nÃ¸Ã¿Â…Âš2KU}*+ÂÃ¤ÃœÂ@.Ã²!]}Ã³ÃšÃ§Ã• Ã¼Â¯Â³Ã„ÃœdÃ«Â!Ã.ÂkC\Iï¾¡Ã¢GÃ¨F%Â©Â†Ã•!ÃœÃ¤Â”H4Â¯Ã¿XÃ¡FÃ¿Ã¤Â©)9ÃÂ¹Â¯Â€Ã›Ã…Ã˜ÂÂ¤gÂ€Ã…Â–Ã¾Ã›Â®E2m|e]0Ã‘^Ã”ÂÂŠ(Â©Ã¦Ã‡qÂµÃªJÂ´&KÃ–Â•ÃµY\\rÂ·j }\\f7ÃŸkÃ´b}-Ãˆ\\fÃ·Â‹Â“Ã¼ÂÂœÂ¦wï¼¶Ã°Ã¤{Ã»Â«bÃÂ¯Ã§cÃ¦pPBqÂ®Ã9ÂˆÂˆÂÂ§Ã¼5Â²z:VÂ…Ã¬ÃÂ­cÃ AF:5ÂÃ©Ã™Ã¯Â®k?nNÃ¸Â@2pÂƒÃœÂ¢+Â¹Â¡\Ãx_!Â¶Ã«\\fÂ£Ã¤!Ã¸ÂÃ 6Ã¦abÂ‘1@Ã•Â‡Ã’Ã€Â³(Â°}Ã™\\bÂ²MÂˆÂƒ%Ã‘dÃ«Ã¨ZÂ«tÃ–,wÃ“)Ã¨ÃªÂ—S#W]&YÃ€ÃÃ¢w8Ã?Ã„Ã’Â¾tÂ¾~ipoDN\\bvÂ›Â«Â€IlÂ€Â²ÂˆÃ‡Ã»Ã‹s\\nVÂŒÂ¼mÃ¹Ã)ÂŠÂ±dÃ•Ã€.6Ã’pÃ¢Â„bÂ§iÃ³jÂ‰hÃ´dÂ°Â¤Â²!n+\\beï¿–ZÂ©Â wÃº0Â•^hUÂ¼ÃªÃ¶Ã™3Ã®\\rÂ‡oI LÂLqT6Ã½.Â˜Ã¬Â«Â¡Â¨Â¥j&5QÃ‘\\rGÃ³\\tÂŠÃaÃ©Â¢C7Â‡\\n\ÃSÂ¢%Â™ÃÃ¯Ã¬c&B\\nÃ®ÃÂ»EÂ¡dÃµI]Â˜Â¶Â©Ã¯Ã”Â¶Kï¾¹Ã³.jÃ±Â˜w$^C~.7Â³C\\ffÂºUÃ–Ãˆ4Ã›ÂŒÂÃ‘Â®|o)ÂšÂµ'UÃ’~Â´Ã‘[@Ã‚]%ÂªÃ³zCÂ­Â¨0zÃ°Ã€Ã…YC\\tÃ¯ÃµcÂœZÃ”Ã±=Â½Ã¥DÃ‘Â¨ JÃ¼Â¼'ÂœÃ™4Â¸oÃ¶\\fÃ¤Â«Â™>VÃ»Â E`Â†Â‘~Â™Ã¥pyL{Â­KD|Ã²aÂÃŠ\\nÂ¿ÂÃÂ¼KZÃ‡4Â²ÃÂ­ÃÃ‰\\bMÃÂ”ÃµÂ‹vÂÃ kÃ°Ã¡ÂƒÃ±>Â’eÃºÃ©-OÂ¤Ã›Ã‘Ã¢\Â¹Â”.\Â¨mVÃ»"Ã¨Ã³,Ã–PtÂ½Ã†Ã±ÃŠÂˆÃ¡s/Â±?Â§[Â¡uÃ·"Â›Ã±ÂŸÃ§Â‹Ã¾qeÂ•]Â‰viÃ¿Â¯)yÂ€}ÃÂºÃ´pÃ€TÃ¬}Â™\Ã¤XÃ·\\f{Â‡Ã¥R3:Ãœ9Ã–Ã{oÃ6Ã‡-Â‹Ã»ÂªÃ¶ eÂ½Ã¯ÂŸÂ·ÂÃ›Â«Vh\\bzÃ•Â°Â¶Ã‡Âª@Â²Â¯ÃšÃšÂ…Ã™Ã…ÃªÃ©ÃŠÃÂ³TÃ¯Ã¥Â¼ÂµÂFÃ¼EÃ˜NhÂ—AÃ»Â¬dHckÂ„>cÂ“VpÂ¿Ã¼8LÂ°*AÃ“ÂªzOÂšÂ‘Ã“hÃ„O3<Â´A3Â»ÃŒÃ‘Â\\t2)^ÃÃ’Ã¼vÂºnÂ»~vÃ™ÃŒÃ¯Ã˜\\t^y\Ã•d5Ã¹2ÂˆÂ¾Ã€\\n&Ã…2|r\Â©.Â ÃŸÃ²Ã‘Ã¬Â®Â¹Â€-Ã‘ï½ƒÂ“Ã­Ã‰]qMÃ¾xÂ¶Â™\o?5(Ã¤#fÃ–J0ÂeÃœNUzÃ…:Ã¥Â…Ã“Ã’ÂœEUÃ»Ã‹\Ã™GÂ‡ÂÂ¾hÂ’>]Â›\\nÃ­fÃŠÂ£Â–Ãµ&ÂÂ®1Ã€Â–Â©Ãƒ_#Â¥Ã9Â‡?Â’Â¤yÂ™Â\ÃºÂ†*k`LÂ´byÂ…Ã›<Âˆ1Ã»%ÂºN'rÃ™oÂ’ÂƒFÃªX3:ÃŠÂ7GFÂÃ´lÃ¤Â—Â¨ÃŒÃˆÂ¶Âˆ\\nÂ‚M@Ãº)Ã‹~{Ã¢ÃAu*ÃŒÂ¼.Ã®Â•MÂ¦SÃ™8Ã«ÂÃ^ÂŸa>!Â§Â˜Ã¨Â„AÂ•5Â‹\\f'|Ã¤Ã—Â‚Ã¾MÃŠBÂ€/Â»Â¶IÂ³uÂ›n_Ã‡ÂµÃ¡Ã¤ÂµVÂ™Ã­ÂÃ¥Ã”Ã£PDxÃ®Ã˜zoÃ¸RDÂ¦Â®Ã¹`>Â’Â¶Ã¨Â½Ã±Â®ÂºEÃ…Âh=pÂ€ÂˆNNNvÂ¤(ÂÂÂÂÂ˜Ã‰=Ã“"Â‡OÂ¦ÃjuÃ°`ZÃ‚Â„7Â¸ÂÂ¢ÂÂ©=Â½,}Â‹yÂ¸orKÃÃ’&Â•@Ã•ÂªÂ¿Ã‡ï¾¶Q6Â•{ LÃ¤Â ÂÂºÂ/+rVÂ¶Â²<AÂƒÃˆÃ¡}Ã§;ÂºbrÃ”ÂŠ5Â«Ã­Ãˆ1Â¡8H Â½/Â‚0Â›Â®/eÃ°BÃ£8Â‡Â§]Â©ÂÃ›Ã‘vÃEÂ¬C{Â¼Ã€&o2Â¼Ã ~Â¾`fÂ¥,1ÃŸZÃÃ Â»eÃ‘zVdxa,p>Ã¿Ã‰HÂ¬mÂ¢kÃ‡ÂšÂ´`(Â‘nÂ4Â¡IÃ›Ã˜Â‹Â€{Ã¾"Ãª  Ã£RÃ¦Ã„egÃÃ¯XÂ¦Â–Ã¤`!Â¯Ã; Ã€ÂÂ°ÃÃ‡Ã©ÃƒiÂŒÃºÂ¯-Ã±YÂ„Ã„}Ã³Ã§Â;&Ã”_Uo\\bÂ‚ÂÂ¹Ã²ÂŒÃ¨Â”Â­:Ã»Ã¸Â²Â¸Â—A6Â¢+ï¿’{ÂV|Â‡Ã©Ã‚Ã¬Ã§$Â±fÃºÃ¬hÃŠÃŒÂ€Â¥#[Â¶?Â®ÃÃ¼iqÂµÂ£Â·9Ã¤o"$Ãš3Ã¯#Ã•Ã‡ÃÃŒÃ£Â†ct|PÃÂ³ÂˆÂ«Ã²ÃTnÂ­ÂµTvÂ±$ÂµdNÃ²Ã—JÂ¾Â‘NÂ±Â¸]ZÂ¯Ãµ+AÂ‡uÂ¾5i0Â´Â–1Â:Â¬zÂœÂÃ³xhÂš!Â¢Â‰D}ÂšdÂ§Â¼Ã‚MÂ˜<ÃO25Ã¹(dÃ5qÂ¨sÂ²Ã½Ã¡Ãª7Ã‚ÃqÃµÃ|ÂŠ[XÃ³.ZÂ©0nÂ©Ã™g Â§Â¦Ã]Ã„/[tÃ$_RÃ kÂaqÂ­Ã‘Ã49-Ã¥GÃ‚Â¹Â¢Ã­Ã½}oÂ·Ã©Ã«+Â­Â©Dn Ã®Â€Ãª>oÂ‰\\bÃ¥OÂ€ÂŠ~_Â«Ã°Ã†Ã¿=6;H#Ã‰tÂ´pÂŒ)Â–\Â§ÂŸÃ€3Ã§Â¢]Ã©Ã£Â”FÃÂ‹Â¹Ã„NÂÂ‘Â¶Â·Â7Ã¡{wÂIÂˆÃ¶Â½Â­C.Â‡@ÂªÂ³Â”%7Ã¹7Â–Â©Â@ÃAO*ÃvÃ»Â¢UÂ¶tYd/ÂˆÂªÃ Ã”Â²?Âƒ#*Ã„EÃ¸TÃ€Ã¨Â–6Â‚ÂÂ¨PÂ¥SGÃ­#Ã‘sÃ´Â…ÃÂ•@KÂ¬Â¥Â¦Â£$|<,AKÃ‹dÂˆ\\bÂoIÂšÂ¸^Ã¸j2$Â€ÃˆÂ›Ez`Ã¶?oÂ£MÂ±Â¿Ã§ÃŠÃÂ³sÃ­Â·Ã˜Ã¨Ã¸4Ã¨Ã¦jIZÃ¸<Ã­dFÂ§Â¦ÂªÂ•ÃŸÃšlÃ Â²Ã³ÃŒo0Â²:Â–ÂºEÃ•9|rÂ”Â˜Ã¼Ã˜Â½Ã–ÂÃ¶ÂÂÃ¢Ã¬`?Ã£Ã¨-ÃŸÂœF/9Ã¶Ã™Ã‰Ã²Â¿iÃŸÃ¶Âƒ.Ã—;Ã’\\nÂ»Ã¨Ã¸;EÂ‚Â¸Â¹Â€Â ÂaÂ Â·ÂªÃ«|rÃ€Ã«Ã…ÃºvNï¼¶ÂÃ±Â¼Â¡Âƒ~Ã±Â•4tÃÂ¨H)rxSÃ˜Ã®ÃŠBRÂ²lÂ±4Ã…Â°?ÃƒÃÂ¥ÃÃˆmÃ›Â‹8\\fQÃ¼Â¹\\nÃÂ¤ÃŠÂ¬Ã¹Â¡Ã“Ã„Ã¦Ã³Ã°Ã‰Â…$Ã‹%Ã‹Ã‰gÂN3#gÂ—ÂƒD.\\b7Ã©Â¸ÃÂ³0Ã¢JlÂ[ WÃ£0ÂˆUï¿›Â´VÂ£Â ÂµÂºÂ¢CÂ—Ã‹Â†Â©Â¤ÂÂ‘Â¯ÃHÂ¢JÂŸwDQÂ„ÃµÃ”Â‡bÃ«-Â‹Â“ÂŒÂŠÃŠÃ’Â "ÂÂ‘XÂ°Ã†?Â°BpÃ›7Ã¯Â±Â¨Ã¨Â¼ÃœÃµ&Â³9Âœ$HÃµÃ­Â£Â¦%gÃŒÃ™Â„Â›{T+oSÂ´ÃŸÂ€>Â‰Ã«Ã¤Ã‘.Ã‹ÃŸÃ¢Ã¸Ã½ÂŠÃ±ÃHÂ¾Ã˜Âº\\nA)j?FÃ§TpÃœÃ¯A>Â£Â¼Â¢sÃ°Â¡\Â‘\\r \\rrÂ¬Ã²Ã…Ã•Â¡Â·lÃ•Ãµ|Ã¿UÂ“pÃ—Ã‰/Â»ÃŒÂ•sÃ‰Â™Ãš!Ãº=(mÂ•ÃVÃÃšÃÃ™zdP3ÂšÃ–`yÂŸÃ„"GÃ3\\tÃ¾ÃŠÂ³,Ã†Ã¼;ÃÂ¨Ã´Ã¥Ã¹cÃ³bÂÂ™Ã’Â±Â®Ã¥WÃˆcNÃ¿%*Â¼R;ÂºlÃ®@Â®&;k[Ãª}Â‹ÂÃ‰Â¦@-\\bÂ¢VÃ*Â™X>cgd8#ÂÂœÃ±>ÂcÃ¶vnÂ¸wÃ´ÃÃ¢Ã¸r!ÂœÂŸÂ­Ã½FÃ¦VÂ“Ã-Â–.Ã²}xÂµRÂÃ‰RÂ«@ÃÂ†ÃµÃ¶ÃÂ¶ï¼‹\\bÃ´h5"\\fsÂ„ CÃ±+Ã¯PiÃ–>Ã’Ã²`lÂ£Â©Ã‘Â¸j{Ã­OhÃ´Ã“AÃ¯K,L?rÂ¦Ã¯LRrupÃÃ’I#Ã»toRÃÂ£Â‰Ã±Â¤Ã/Â’Ã“Â›Â°X&Â¬LÂ Ã•\\t#pÂœ4fMtÂŸvK0fÂ¬#Ã‰kÂ‡ï¼—bNnÂ¤Â KÃÃÃ“Â°"'NÂºxiÃ”arÃ¸ÂœÃ¦ÂAÃ\\tÃ¿8 ÂSÂŠ\\t%>Ã¥Ã—Ã¶\\tÃÃ†ÂŸOÃŒfAÃ¦Â¹iz6^Â’Â¹ÃÂ°l#ZÂ_Ã–S]Ã£Â•Â‡PÂ²?^Ã Ã£Ã½\\bÂ§ÃÃ¶Â8_Ã…Z^&ÃªPXÃÃ¿Â PÃ¼MÂ Â”Â¦Ã¤%kÃ‰X*Ã¦Â§ÂµKÃ·Ã›ÂŒÂ’Ã¼Âœ)bÂ ÂÃ!Â‰PÂºÂ€CÃ‚Â³Â¨}DÃ­`Ã‡Ã¢Â­Â³Â½YvÃLÃšÂ‰j|Ã”k6gAÃPÂ½TÂºÃŒÂ­Ã{uÃ¶7hÂ’xÃŠÂŒ@Â´+Âˆ\\fÃ—Â–=Â¢ÃµÃÃ´mÃ“6Â³Â¨ÂµÂ’zÂ¡\\n4Â¯9,Ã¬/gÃ¿ÃˆÂ“*Â¹OÂ†Â•ÂŸÃ 8:Â¼~Â‡Â§Â¥ÃˆÃ“ .NÃ«0Â‰Â˜Ã«Â¶ÂºrTÂ¹qÂ­Ã¶Â‹Â/Â†Ã³Ã¤Ã†Ã½Ã‚Ã€Ã¾Â·IyÃŒpÂ„Ã¡Ã©Â© Â­Ãƒ.\\tÃŠÂ¶Â«Âšr]FÃ¡ÃÂ¬\\f0AÂ±OHÂ¤Ã¾aÂ€Ãª=IÃ‚Ã¢ï¼±Ã²Ã¼.>ÃINÂ—Ã¾4ÃŸn@Â’NÃ¤GÃ‹GPÃ¬Ã‡ÂºqÃ”Ãœ[ÂŒÂ•`Ã½Ã±Ã™WkÃ¥/Â€pÃ´ÃÃ¨OÃ¨BÃŒÃ™ÂÃ“Ã.[ÂªwÂ¼eÂ²ÂºÂŒÂXpÃyxÂ¼2aÃlÃ˜BÃ‚Â…Â·Ã»Ã°Â¯\\b,LÃw7'ÂÃ¾ÂÂ²I3Zï½…Â•Âµ_Â¸L\\nÂ¼]&uzHÂˆÂƒÃ–Âªd1Ã#ÂƒÂ†+Ã•Â‹]ÂƒÂ©Ã¥?+cCÂ¯Ã³EÃ¬Ã½Â‡ZgAÂ¨*SÃŸÂšÂÂ¡NÂ¼Ã¦Ã©da Ã”Â’Â“nÂ¾#Â·pal\\r>ÂˆVÃ˜Ã§UÃŸÂ§Ã¡Ã‘=Âƒ^Ã¾YÂ‘prÃ‰Ã±MÂ¾Â¡Ã™{GÂ·wk|Â»Â¸Â£Ã‹o.nÂª Â¸/Ã·Â­3Â³Ã‘qÃ‰ÃµcVtUE:M.Ã«Ãœ'gÂÃˆÂ°Ã½X3\\tUÂ¨Ã¸Â¼AÃ«QÂ£Ã‘Â´Â¿ NÂˆÃ˜;"ÃªÂ«&Â—ÃœhÃ§Ã¿Â !Ã¯OÃ¤Â°nÂÂ¯])Â‹dFÂ‹Â¢NHÂ¤Â¡Â¬Â±Â¬{ï¿­ÂÂÂ¾Â³Ãq'Â¬Â“\\rÂ„cÃÃ±L6lQÂ•Â»ÃšÃŸÃ“Â«}$Â´Â“4R&Â‹qÂ³-FÂ­Â©HjZÃ²Ã‹Â¤Â )ÂµÃÃ‘I\\nÃÃ’Â½ÃÃ¶$Ã…"Â±Â±ÃªIÃ¥Ã´Ã™Ã JÂ´Ã²Â’Â¡Â‚B-cÃ•ÃœSÂ€Â¥kÂ‘Ã3GÂ®k[ÃœÃÃ‚Ã€ÂœÃ™ÃƒÃ—Â†;Ã°uÃ¸Â‰lÂ´Ã’nÂ†<ÂÃªÂšÃ„Ã¡'ÃµÃÂ²2ÂŠÂ°\\bQ)6qÃ˜ÂŸÃ‹ Fqg8ÂŸÃ“ÂµÃÂ±Â¶lLÂ¢_~4ÂVÃ‚eGgÂ\\nÃ¤<ÃŸT)Ã¨ÃµÃ¬eZ|ÃÃ›Ãª_@ Ã¡,6Â®nÂ´BÃÃš7Ã§hÃ†[Â¶TÃ°8Â¸ÂµÂ¾Ã¢0Ã©Ã @ÂoLÂ“5ÃºÂ…Â‚2Â´Â±$z`Â˜Ã’Ã±A/-Ã½\\niÂ©e-ÂÃ£Ã³[ÃÂ´Â«Ã²ÂªÃ”Â¼Â\\fÃ©`Ã¦ÂµÂ¼ÂªÃ¯ZÃ’Â‡Ã£YÃ¾3Ã²vÂ“.Ã”(qÂ©Ã Â·ÃšÃ™ÂˆÂ–Â’eÃÃ‡Â—K!13ZIÂ—Ã¥Â£wÃ—Ã1mÃ¨TÂ°bÃ±ÂºgÃZÃ¡=Ã©Zt]Â¢}Ã€ÃºZÃ³Ã°Ã±ÃÂµ7Â†Ã¾ÂšÃ‰ÃÂ›Ã«Ã¡.Ã±?Ã‡\\nÂ…B~ÃºÃœÂ¹Ã­Ã©Â¦`|Ã16Â´Ã†%L;ÃœCÂƒK@ÃEÃŸ9Â®{<B]Ã‚hmr'4Ã¾ÂšÂ‡ÃµÂ¦Ã·Â¶FÃ Ã£Ãš\\nÃ’PKÂŒÂ¼ï¼¬Ã£ÃœÂ„azÃ©fÃ„Ã€Â­ÂhÃ›Â˜Ã¶{"AÃ½=Ã„g:zÃ«AÂ­0Â³\\f5x:%5Ã¬9ÂÂ8dÂ¥ÂÃO5Ã¾NY\\rIl\\f(Ã­(Ã•Â¸Â©Â›Â‹Ã§'$sYiÂ«ÃLpÂºÂ†Ã»ÂÃ›ÂšySÂÂ~kÂŠÂµÃ®Â«iÃ‡ÂŒN]Â°Â Ã‘pÂƒÃ¼Â‘NÃ¦-Â²Â­Ã³Â¹Ã¼a(_VÂ»ÂªÃŸÃÃ¦Ã”3Â¤+Ã·nÃ´ÂŒÂ€Q^Â¥Â³Â¯Â…(eÃ¾Ã„mÂ¤Ã²t:Ã Ã¶ÃÂ—Â©Â•Ã 8Ã¥2;ÂºÂ†.\\bÃšÃœÃÂ–ÂÂ›Ã¡i.P8KÂ¸p!u%Ã•Â„ÃŸÃ´fÃ‘yÂ½Ã¶Â»ÂgvÃ¢Ã„Ã±ÃŒIÃ¨RÃ™Â­Â–Â5{Ã²\\bÂ·Â†[EÂ•Â» ZÃÂ’Ã„\\nsÂ²Ã¹Â‘~Âš(Ã€Â·Ã±/ÂµÂÃ‚ÂŠ6]zxÃ²=\\n%Â¡pÃ†ÃšÃ«|Ã\W&rÂ‘ÃŸÂ±BÃ¸_ÃFÂŠÃ¼>aÃ½Â‘Â‰Ã¾Ã’Ã·Ãµ)pxÃˆÃ”(MÃ³GsÃ›Âˆ~ÂÂ¼Â™Â†xÂ KÃ‡|HÃ”Â£Ã»Â¶ÂˆÂ£Ci5Â–OÃ™Â˜ÂªÂƒÂÂµÂ¤Ã¬Â»Ã‚Ã‘Â¶Â¸0ÂºÃœ*DÃ€nÃÃ´ÂŒÃ¤Ã¿ÃÃ—#ÂÃˆVÂˆxÂ‡AÃ¾Âƒ\\fLÃxÂ±Â3tÂ¿ÂVFsÂ¿?Â¯Ã›GÃˆ$Â»J}DTÂ˜V6Ã¦Ã‘IÂ‹\\rÂ’}Ã¿dï¼«"Ã°KÂ=$Ã¼Â½Ã“Â©DÂŒ%T2:JÃ£ÂªÃŠÃ§Ã¶9V>Ã„K@ÂÃˆ/Â˜Ã“Â“ÃÂ…P&Â…?Â—uÃ„2Ã„Ât^ÂeÃ‡bÂ¦06ZÂ”Â´MÂ£ÂŒÂ©Ã‰ÂªBÂ‡ <k7??\\bCWÃ€Ã¼Ã¢Ã£Ã¦Ã›vÃÃ“Ã¨sÃI&Ã€Â¸ÃºÂ„IÃ¬ÂœÂ“?`Ã™Â¦ÂƒÂ£\\f}Ã”ÃºzÂ¤\\tÃ¤Ã¦Ã²WÃ§\ÂÃ•-Â­Ã€AIÂ³Ã©Ã§Ã¦Â¶Â–Ã–jÃŸÃ¯!ÃƒbÂ¡Ã¡Â˜ÂŸ]Ã«`[Â„Ã™Ã¬b)Ã³GMÂŸÂ‰ÂÂ…mÂœÃ‡Ã›5{Â˜&Â‹R6Ã¥4zSÂ»Ã…AHÃ®Â·Â²ï¿„"ÂˆÃ¡\'Or _Â¢Â“LÃ\\rÃ®ezÂ¯u3gÃ·Ã¿8Ã™Ã>gÃ²fÃ“MÂ¬ÃÂ”Ã¢Â½Â°-Ã”Â¶m_Â©lÃ¢Â;Â‰Ã–[\\fÃ¬ÃŸ_Ã­Ã¹)Â”Â \\rÂ‰Ã“9,ÃÃ[gÂ»ÃšMcÃ™Â•DÂŒÃÃ·ÃDjÃ–Â”1Â¢Â‹LmRÂœÂ¨Â­Ã¯Ã³Ã‰Â½PIy#Ãª<Ã®Ã¡ÃÃ€ÃÃÂšÂ‡Ã© \\bGÂ‡Ã©Â±\\nÃµC\\rÃ‘{Â¸Â¬ÃµÃ—72'Ã„Â¯ÃÃÃ½ÂŒÃ»ÂÂ¹Ã‰Â«Â¤Ã†" Ã¾I>c'Â‡Â•0ÂœÂªZreÂ¨Ã´dÃÃ‘8kÂ±!EÃ¤OÃ‡Â gLÃ±Âˆ5Â½Â›gÃ£\\nÂ¨Ã Â©Ã‹Ã¬Ã‹Ã’ Ã5=Â©<%Ã…Â†bÂ¥Ã‘8ÂºÂ§Ã³Â©YÃ”Â½Â‹2Â¥6kÃ¡Ãƒ8}Â²`ÃƒÃ¸FÃ…0zÃ§VÃ®Ã²+kwÂ¿@ÃªqXqÂ»Âš"Â¸Â’,CÂ‰T\\tÂ™Ã¨uÃ¶;Ã§Â°Ã±Ã‚Â©? Â bÃ]Ã³yÃ¶Ã¦TÂŒpÂ…ÂªÃ…Âª}Ã¾ÂƒÃ£ï½§\\bÂÃ¡Â¨ÂœÂŸÃƒÂ‹!Ã»AÃ’Â¶Â´yÂšÂ™Â½/Ã–Â½Ã¨8ÂŒv~ÃÂŒÃ¿Â¨ÂˆÃˆ)jÂ–Â¼_+dÂ¢Ã€gÂ‚IqÃZVÃÂ¨SÂ‘Â¤rÃÃ´PQSgWÂ¾Â‘ÂŒÂ…Â¯Â©CÂ¬Â³\\nÂ–><ÂÂ€CÂ˜Ã¯Ã›vdÃœÂ™Â„Â…Ã‰ÂšÂ˜ï¾½Ã˜Ã¼Â¼+ÃÂ½Â†\\t?Â£7ÂœÃ–Ã¸Ã´Â‰QnÂ¸oÃ™\\bÃšÃ¦Ã™NÃ¡NÃ¨{ÂºÂŒÂ†6Â¦=VeÃºy(}1Â’Â¹Â¡ Ã³Â€Â¼ÃÂ²Ã„Â´Â©Â§;\\nÂˆÂÃ¿Â•(FyÃ‡.Â†Ã‡Â¬Â <)ÂƒMÂ¨aÃ¨Ã¹\\tÂ˜~dÃˆÂ¤=eÂ•Y(?Âº1Â‰ï¼ª(<Ã!Ã¥WÂ™oÂ§Ã‚Â€ m9ÃšÃ´Ãƒ7jÂ4Ãt)Â—SÃ™:}c\\rwG6Ã/;Â[Ã\\r>Â°Ã–ÂµÃ—Ã¯MÂƒÃ Ã–PÂ™Ã¿DÃÂ² tfÂ¬xÂšÂ›-,Ã»|Ã¥ÂÂ‘Â½\Â·2ÂšPfÃ‚Â˜Ã¡Ã‹Ã°:Â‰CÂ¸Ã¼Ã¯Ã½ÂÂ‘Ã»Ãƒ:Ã–Â›Â‡ÃªÃÂ2ÂŒ!Ã¡yqÂ•Â‘Â“ÃŠly}pÃ½'Ã¤,Ã+ÃÃ¨SAÃ»Â™Ã½Â¶Â»xÂƒÂ„T.iÃ·Â¢8#Â–,Â’Ã•ÂªÃ¥ÃŒÂÂ»/`hÃ®/Â¼WÂÃ¡Ã‡5x :Â²ÃˆÃ PÂ‚ÂO<qÃŒÃ¥JÂ»Ã€1Â¨ÃˆÂŒÃ«Ã³ÃÃƒ5Ã·Ã·Ã§ï¼…%rÃ°G(|Ã¦V\\tw+ÃºÂ¼Ã•.Ã‰Ã†Â¢Â·YÃ9Â¦Â·[Ã²pÃ“}Â»uÃÂ¡xÃ¤Ã³Â Â­ÂƒÃ©%Ã§0ÃˆÃ‡ÂŒÂ­Â¾q\Ã¯Ã§<Â”$Ãš8Ã®Â©Â¦Â©Âƒ"Ã€\\bOÃ‘Ã¡Â¶UÂ‡TXÃ¼C\\b%ÃŒÂ›ÂˆlCG/Â°cÃ€>Ã”Âƒ#Â¸Ã¯Â¨%Ã·Ã—MÃ§Ã°VWÃ°_|lÂ´Â¯ÃŠoÃ¼Â¿Z4Ãµ gCrÃ«Â¸c%Ã‡Âš`YHd\\f)]oGÂºdÃšÂ0hÂª~Â†Ã´aÂ¸'WÃ»7Ã¶Â…a ÂÃÂ•ÃŠq\\nÃ oÃ¯>'*Ã™Â·Â‡Â¤Ã·ÃŸ@dÂŒÂŠuÃ±Â½Ã¡6Ã˜"Â£+Ã’Â·ÃŒÂ„Âjgï½ByEXÂ²Â·]Â®zaÂµÂ°o"4v<Â…ÂšÃ†Ã¢|kÂ Ã±ÃÃ‹ÂƒvÃÃŸKÂ´wbÃeÂ Ã¶Â•\\t0Â¢Â¿Â˜TÂ•Â£Â’Ãƒ/j>Ã§Ã­!\\b.Ã´{PzÃ‡ÃŠÂ¥xÂ‡Ã¼Ã¬ÂmÃ­E:Ã·[Ã³Ã¸Â™Ã·Ã¥Â€Â„rÂ½zÃ ÂªÂÂ±\\n\\rZfJ%Ã»Â°Ã½1A?Âw!Â*\\rÂ³Ã SÃŠ0sÂ´aÃ«Ã¹Â­ÂƒÂ§Ã’Ã“\\thBÃ€)6EÂ®UÂ¯PÃ‹ÂƒÂ‡#SMiÃªRiz(Â¦Ã¶1AÂ«Â¦)jÃZCÂ›%GmÃ¹UÃ„Â®\WÃ›zÃ†ÂÃ#Ã 1Ã™ÂV`Â—ÃºÂ¤nÃ Ã›h3Ã»3Ã•vÂ‚Ã™Ã¨ÃÃ‹ÃœÃŠÃ¶ÂÂ’ÂÂ¿ÂÂˆeÃAÃVÂ²Ã’ÂÃ¦Â¶Ã„\:*;Â‘Âˆ,Ã²Â“Â…H?Ã‘ÃÃ´Â€Ã¤Ã®Ã¼-}KÂ­NÃ»q\Ã†ÃÃƒ\ÃºjÃ¼\TÃ¯|Â¤yÂ§Ã Ã©gÂ—2ÂÂ¥Â“Â–ÃšEmÂÂª=Â·ÃºÃ–'Ãgï¾˜ Ã«Â·ÂÃ¡Â…Â»Â’\\bVDLÂ‡Ã¬Â†Ã«Ã”ÃŠFÃ¥eÃŸXÃ½Y+ÃµÃ‹ÂŠÃ¢ÃÂ¿ÃˆÃÃ…Â–rÃ¾Ã«ÃŸÃm[Â«Â¹5Ã˜~.ÂŒÃ³Â…mÃ²Ã•]Â›ÃÃ¿Ã´ZÂ•A7ÃŒ)0[Â‰\\rZjPÃ²ÃœÂ¼Â‘<Â¢Â½Ã³Ã…C,ï¼ŠÂºUÂ Â±Ã¢Ã­SÃ§Ã§!Ã£Â»ÂŸq\\bÂ¥Ãº65\\fdÃ¢"ÂkmÃÂÂºÂ±Â·)Â‘ÂƒÃ—Ã²Â¨Â“$?:Âœ'ÃŒÃ»Ã´\\tFwEÂ•"6Â­X_VkÃ™Ã‘Â½DÂ¦?\\r}VÃ¦ÂšÂNaÂ¨ÂµÂJb'(ÂŒÃ§BTÃ¾|Gb(Â¥ÂMÃwÂ­C3ÂŒÃ°Ã‚Â¾<wjÂ„Ã¶Â—Ã¬zÃµÂ¬~Â¾2\\fLÂƒqÃ®Â¼fPTNÃ“Â£EÂŸ\\tÃ²IÃ„Ã°r8Ã’6ÂºÃ´#Ã¦ÂŒÃ´Ã‚raÃ½!RÂ‡Ã™Â¹Ã•Â¾Âˆb<Ã°Â©yhÂ»Ã¾Â®DÂªÃ‡Ã\\nÂ’'Ã©Â£Ã¸Â•;Ã‰\\nba\\fZÂÂ±wÃ«|G&1{Â’Â‰QÂ£QÃ±Ã¨\\nÂ•Ã¿Ã¸7ÂÂªÂ¼Ã¢EÂ‰7Â§ÂœÃŒÂ«oÃÂ“ÃˆÃÃÂ½Ã½\\tNnÂ—ÂœPÃµÃ¸Â³'Âš%1gÂ³VTÃ Ã¥ArÃiÃÃÃ‹u:ÂŸ/Ã·Ã’Â” Â°Ã¾&Â¢Â¿RIÂ•Â´ÂÂ¨[Ã¤Ã¶Ã‘Ã´Ã¿Â­bkaÃÃwÃ•Ã€Ã†ÂÂ¶ÃˆQHÂ¨Ã¸Â¿ \\fÃ¯(Ãœ=Â¡rQbÃ§WlÃ„Ã«qÃ¨Â¦ÃºÃ†qKÃœÃ~wsÂœÂ•Â_YS9Â†5PcÂ’Ã”Ã›tÂ¥wÂÂµÃ¿ÃJh^jlÃÃ™Â˜C[ÃTÂ€Â¬ÂªÂ†=:\\r~Ã¾Ã•'Â…ÃÂÃ»ÂÃ“z@Oï½¶Ã°ÃÃ”ÃÂ°HÂšÃ­\\fÂŸ'Ã²Ã‘ÂŠÃ‡JÂ§Â©9Â¾C<gÃ‘]PnfÃ±Ã®\Â¹*ÂªÂ…Â†E-ÂÃ®(Ã¢P[ÃŠIÂˆGÃ§Âº;Â‹Ã™JÂÃ·aÂµ=Ã‹Â—Â…?1Â†xÂƒÂ”Â±Ãª# Â¬Ã(ÃšÃ³yÂO.ÂaÃ‡yÂ†Ãtt`\\fÂšÃ•ï¾½3ÂˆFÂ¹Ã°Â‹Â¬zÂŠÂªÂŠ9Â½%BÂ—Ã¬Ã¸Â¡\\t\\f\\tÂºÂ˜Â­Â£)Ã‡@ÂˆÂ¿%Ã›Ã­Ã¢Ã—ÂœÂ\\fÃ&AÂ†<xÃ£Â¡Â‹6(~Ãª@Â˜7ZÂµÂ‹yW(oÂ­Âœ\\rT2ÃšÂ­ÃµÂ§ÃŒEÃ™/\\fUÂ‡vÃºÂ—[Â‡=Â¦EÂ¬Ã„Ã§C'
    //   69: dup
    //   70: astore_2
    //   71: invokevirtual length : ()I
    //   74: istore #4
    //   76: sipush #8405
    //   79: istore_1
    //   80: iconst_m1
    //   81: istore_0
    //   82: bipush #101
    //   84: iinc #0, 1
    //   87: aload_2
    //   88: iload_0
    //   89: dup
    //   90: iload_1
    //   91: iadd
    //   92: invokevirtual substring : (II)Ljava/lang/String;
    //   95: jsr -> 141
    //   98: aload #5
    //   100: swap
    //   101: iload_3
    //   102: iinc #3, 1
    //   105: swap
    //   106: aastore
    //   107: iload_0
    //   108: iload_1
    //   109: iadd
    //   110: dup
    //   111: istore_0
    //   112: iload #4
    //   114: if_icmpge -> 126
    //   117: aload_2
    //   118: iload_0
    //   119: invokevirtual charAt : (I)C
    //   122: istore_1
    //   123: goto -> 82
    //   126: aload #5
    //   128: putstatic me/rerere/matrix/internal/av.i : [Ljava/lang/String;
    //   131: iconst_2
    //   132: anewarray java/lang/String
    //   135: putstatic me/rerere/matrix/internal/av.l : [Ljava/lang/String;
    //   138: goto -> 271
    //   141: astore #6
    //   143: invokevirtual toCharArray : ()[C
    //   146: dup_x1
    //   147: arraylength
    //   148: dup_x2
    //   149: pop
    //   150: iconst_0
    //   151: istore #7
    //   153: goto -> 247
    //   156: dup2
    //   157: swap
    //   158: iload #7
    //   160: dup2_x1
    //   161: caload
    //   162: swap
    //   163: iload #7
    //   165: bipush #7
    //   167: irem
    //   168: tableswitch default -> 238, 0 -> 208, 1 -> 213, 2 -> 218, 3 -> 223, 4 -> 228, 5 -> 233
    //   208: bipush #19
    //   210: goto -> 240
    //   213: bipush #90
    //   215: goto -> 240
    //   218: bipush #34
    //   220: goto -> 240
    //   223: bipush #110
    //   225: goto -> 240
    //   228: bipush #93
    //   230: goto -> 240
    //   233: bipush #50
    //   235: goto -> 240
    //   238: bipush #57
    //   240: ixor
    //   241: ixor
    //   242: i2c
    //   243: castore
    //   244: iinc #7, 1
    //   247: dup2_x1
    //   248: pop2
    //   249: dup_x2
    //   250: iload #7
    //   252: if_icmpgt -> 156
    //   255: pop
    //   256: new java/lang/String
    //   259: dup_x1
    //   260: swap
    //   261: invokespecial <init> : ([C)V
    //   264: invokevirtual intern : ()Ljava/lang/String;
    //   267: swap
    //   268: pop
    //   269: ret #6
    //   271: ldc 331
    //   273: putstatic me/rerere/matrix/internal/av.k : I
    //   276: ldc 'SHA-512'
    //   278: putstatic me/rerere/matrix/internal/av.a : Ljava/lang/String;
    //   281: ldc 'UTF-8'
    //   283: putstatic me/rerere/matrix/internal/av.j : Ljava/lang/String;
    //   286: ldc '\\b'
    //   288: putstatic me/rerere/matrix/internal/av.f : Ljava/lang/String;
    //   291: ldc 'java.security.MessageDigest'
    //   293: invokestatic forName : (Ljava/lang/String;)Ljava/lang/Class;
    //   296: pop
    //   297: ldc 'java.math.BigInteger'
    //   299: invokestatic forName : (Ljava/lang/String;)Ljava/lang/Class;
    //   302: pop
    //   303: ldc ''
    //   305: getstatic me/rerere/matrix/internal/av.j : Ljava/lang/String;
    //   308: invokevirtual getBytes : (Ljava/lang/String;)[B
    //   311: pop
    //   312: getstatic me/rerere/matrix/internal/av.a : Ljava/lang/String;
    //   315: invokestatic getInstance : (Ljava/lang/String;)Ljava/security/MessageDigest;
    //   318: putstatic me/rerere/matrix/internal/av.b : Ljava/security/MessageDigest;
    //   321: new java/util/concurrent/ConcurrentHashMap
    //   324: dup
    //   325: getstatic me/rerere/matrix/internal/av.k : I
    //   328: invokespecial <init> : (I)V
    //   331: putstatic me/rerere/matrix/internal/av.c : Ljava/util/concurrent/ConcurrentHashMap;
    //   334: new java/util/concurrent/ConcurrentHashMap
    //   337: dup
    //   338: invokespecial <init> : ()V
    //   341: putstatic me/rerere/matrix/internal/av.d : Ljava/util/concurrent/ConcurrentHashMap;
    //   344: getstatic me/rerere/matrix/internal/av.d : Ljava/util/concurrent/ConcurrentHashMap;
    //   347: getstatic java/lang/Byte.TYPE : Ljava/lang/Class;
    //   350: ldc 'B'
    //   352: invokevirtual put : (Ljava/lang/Object;Ljava/lang/Object;)Ljava/lang/Object;
    //   355: pop
    //   356: getstatic me/rerere/matrix/internal/av.d : Ljava/util/concurrent/ConcurrentHashMap;
    //   359: getstatic java/lang/Boolean.TYPE : Ljava/lang/Class;
    //   362: ldc 'Z'
    //   364: invokevirtual put : (Ljava/lang/Object;Ljava/lang/Object;)Ljava/lang/Object;
    //   367: pop
    //   368: getstatic me/rerere/matrix/internal/av.d : Ljava/util/concurrent/ConcurrentHashMap;
    //   371: getstatic java/lang/Short.TYPE : Ljava/lang/Class;
    //   374: ldc 'S'
    //   376: invokevirtual put : (Ljava/lang/Object;Ljava/lang/Object;)Ljava/lang/Object;
    //   379: pop
    //   380: getstatic me/rerere/matrix/internal/av.d : Ljava/util/concurrent/ConcurrentHashMap;
    //   383: getstatic java/lang/Character.TYPE : Ljava/lang/Class;
    //   386: ldc_w 'C'
    //   389: invokevirtual put : (Ljava/lang/Object;Ljava/lang/Object;)Ljava/lang/Object;
    //   392: pop
    //   393: getstatic me/rerere/matrix/internal/av.d : Ljava/util/concurrent/ConcurrentHashMap;
    //   396: getstatic java/lang/Integer.TYPE : Ljava/lang/Class;
    //   399: ldc_w 'I'
    //   402: invokevirtual put : (Ljava/lang/Object;Ljava/lang/Object;)Ljava/lang/Object;
    //   405: pop
    //   406: getstatic me/rerere/matrix/internal/av.d : Ljava/util/concurrent/ConcurrentHashMap;
    //   409: getstatic java/lang/Long.TYPE : Ljava/lang/Class;
    //   412: ldc_w 'J'
    //   415: invokevirtual put : (Ljava/lang/Object;Ljava/lang/Object;)Ljava/lang/Object;
    //   418: pop
    //   419: getstatic me/rerere/matrix/internal/av.d : Ljava/util/concurrent/ConcurrentHashMap;
    //   422: getstatic java/lang/Float.TYPE : Ljava/lang/Class;
    //   425: ldc_w 'F'
    //   428: invokevirtual put : (Ljava/lang/Object;Ljava/lang/Object;)Ljava/lang/Object;
    //   431: pop
    //   432: getstatic me/rerere/matrix/internal/av.d : Ljava/util/concurrent/ConcurrentHashMap;
    //   435: getstatic java/lang/Double.TYPE : Ljava/lang/Class;
    //   438: ldc_w 'D'
    //   441: invokevirtual put : (Ljava/lang/Object;Ljava/lang/Object;)Ljava/lang/Object;
    //   444: pop
    //   445: new java/util/concurrent/ConcurrentHashMap
    //   448: dup
    //   449: getstatic me/rerere/matrix/internal/av.k : I
    //   452: invokespecial <init> : (I)V
    //   455: putstatic me/rerere/matrix/internal/av.g : Ljava/util/concurrent/ConcurrentHashMap;
    //   458: new java/util/concurrent/ConcurrentHashMap
    //   461: dup
    //   462: invokespecial <init> : ()V
    //   465: putstatic me/rerere/matrix/internal/av.h : Ljava/util/concurrent/ConcurrentHashMap;
    //   468: getstatic me/rerere/matrix/internal/av.c : Ljava/util/concurrent/ConcurrentHashMap;
    //   471: invokestatic a : (Ljava/util/concurrent/ConcurrentHashMap;)V
    //   474: getstatic me/rerere/matrix/internal/av.c : Ljava/util/concurrent/ConcurrentHashMap;
    //   477: invokestatic b : (Ljava/util/concurrent/ConcurrentHashMap;)V
    //   480: getstatic me/rerere/matrix/internal/av.c : Ljava/util/concurrent/ConcurrentHashMap;
    //   483: invokestatic c : (Ljava/util/concurrent/ConcurrentHashMap;)V
    //   486: getstatic me/rerere/matrix/internal/av.c : Ljava/util/concurrent/ConcurrentHashMap;
    //   489: invokestatic d : (Ljava/util/concurrent/ConcurrentHashMap;)V
    //   492: getstatic me/rerere/matrix/internal/av.c : Ljava/util/concurrent/ConcurrentHashMap;
    //   495: invokestatic e : (Ljava/util/concurrent/ConcurrentHashMap;)V
    //   498: getstatic me/rerere/matrix/internal/av.c : Ljava/util/concurrent/ConcurrentHashMap;
    //   501: invokestatic f : (Ljava/util/concurrent/ConcurrentHashMap;)V
    //   504: getstatic me/rerere/matrix/internal/av.c : Ljava/util/concurrent/ConcurrentHashMap;
    //   507: invokestatic g : (Ljava/util/concurrent/ConcurrentHashMap;)V
    //   510: getstatic me/rerere/matrix/internal/av.c : Ljava/util/concurrent/ConcurrentHashMap;
    //   513: invokestatic h : (Ljava/util/concurrent/ConcurrentHashMap;)V
    //   516: getstatic me/rerere/matrix/internal/av.c : Ljava/util/concurrent/ConcurrentHashMap;
    //   519: invokestatic i : (Ljava/util/concurrent/ConcurrentHashMap;)V
    //   522: getstatic me/rerere/matrix/internal/av.c : Ljava/util/concurrent/ConcurrentHashMap;
    //   525: invokestatic j : (Ljava/util/concurrent/ConcurrentHashMap;)V
    //   528: getstatic me/rerere/matrix/internal/av.c : Ljava/util/concurrent/ConcurrentHashMap;
    //   531: invokestatic k : (Ljava/util/concurrent/ConcurrentHashMap;)V
    //   534: goto -> 539
    //   537: astore #8
    //   539: return
    // Exception table:
    //   from	to	target	type
    //   291	534	537	java/lang/Exception
  }
  
  private static String a(int paramInt1, int paramInt2) {
    int i = (paramInt1 ^ 0xFFFFBB41) & 0xFFFF;
    if (l[i] == null) {
      char[] arrayOfChar = i[i].toCharArray();
      switch (arrayOfChar[0] & 0xFF) {
        case 0:
        
        case 1:
        
        case 2:
        
        case 3:
        
        case 4:
        
        case 5:
        
        case 6:
        
        case 7:
        
        case 8:
        
        case 9:
        
        case 10:
        
        case 11:
        
        case 12:
        
        case 13:
        
        case 14:
        
        case 15:
        
        case 16:
        
        case 17:
        
        case 18:
        
        case 19:
        
        case 20:
        
        case 21:
        
        case 22:
        
        case 23:
        
        case 24:
        
        case 25:
        
        case 26:
        
        case 27:
        
        case 28:
        
        case 29:
        
        case 30:
        
        case 31:
        
        case 32:
        
        case 33:
        
        case 34:
        
        case 35:
        
        case 36:
        
        case 37:
        
        case 38:
        
        case 39:
        
        case 40:
        
        case 41:
        
        case 42:
        
        case 43:
        
        case 44:
        
        case 45:
        
        case 46:
        
        case 47:
        
        case 48:
        
        case 49:
        
        case 50:
        
        case 51:
        
        case 52:
        
        case 53:
        
        case 54:
        
        case 55:
        
        case 56:
        
        case 57:
        
        case 58:
        
        case 59:
        
        case 60:
        
        case 61:
        
        case 62:
        
        case 63:
        
        case 64:
        
        case 65:
        
        case 66:
        
        case 67:
        
        case 68:
        
        case 69:
        
        case 70:
        
        case 71:
        
        case 72:
        
        case 73:
        
        case 74:
        
        case 75:
        
        case 76:
        
        case 77:
        
        case 78:
        
        case 79:
        
        case 80:
        
        case 81:
        
        case 82:
        
        case 83:
        
        case 84:
        
        case 85:
        
        case 86:
        
        case 87:
        
        case 88:
        
        case 89:
        
        case 90:
        
        case 91:
        
        case 92:
        
        case 93:
        
        case 94:
        
        case 95:
        
        case 96:
        
        case 97:
        
        case 98:
        
        case 99:
        
        case 100:
        
        case 101:
        
        case 102:
        
        case 103:
        
        case 104:
        
        case 105:
        
        case 106:
        
        case 107:
        
        case 108:
        
        case 109:
        
        case 110:
        
        case 111:
        
        case 112:
        
        case 113:
        
        case 114:
        
        case 115:
        
        case 116:
        
        case 117:
        
        case 118:
        
        case 119:
        
        case 120:
        
        case 121:
        
        case 122:
        
        case 123:
        
        case 124:
        
        case 125:
        
        case 126:
        
        case 127:
        
        case 128:
        
        case 129:
        
        case 130:
        
        case 131:
        
        case 132:
        
        case 133:
        
        case 134:
        
        case 135:
        
        case 136:
        
        case 137:
        
        case 138:
        
        case 139:
        
        case 140:
        
        case 141:
        
        case 142:
        
        case 143:
        
        case 144:
        
        case 145:
        
        case 146:
        
        case 147:
        
        case 148:
        
        case 149:
        
        case 150:
        
        case 151:
        
        case 152:
        
        case 153:
        
        case 154:
        
        case 155:
        
        case 156:
        
        case 157:
        
        case 158:
        
        case 159:
        
        case 160:
        
        case 161:
        
        case 162:
        
        case 163:
        
        case 164:
        
        case 165:
        
        case 166:
        
        case 167:
        
        case 168:
        
        case 169:
        
        case 170:
        
        case 171:
        
        case 172:
        
        case 173:
        
        case 174:
        
        case 175:
        
        case 176:
        
        case 177:
        
        case 178:
        
        case 179:
        
        case 180:
        
        case 181:
        
        case 182:
        
        case 183:
        
        case 184:
        
        case 185:
        
        case 186:
        
        case 187:
        
        case 188:
        
        case 189:
        
        case 190:
        
        case 191:
        
        case 192:
        
        case 193:
        
        case 194:
        
        case 195:
        
        case 196:
        
        case 197:
        
        case 198:
        
        case 199:
        
        case 200:
        
        case 201:
        
        case 202:
        
        case 203:
        
        case 204:
        
        case 205:
        
        case 206:
        
        case 207:
        
        case 208:
        
        case 209:
        
        case 210:
        
        case 211:
        
        case 212:
        
        case 213:
        
        case 214:
        
        case 215:
        
        case 216:
        
        case 217:
        
        case 218:
        
        case 219:
        
        case 220:
        
        case 221:
        
        case 222:
        
        case 223:
        
        case 224:
        
        case 225:
        
        case 226:
        
        case 227:
        
        case 228:
        
        case 229:
        
        case 230:
        
        case 231:
        
        case 232:
        
        case 233:
        
        case 234:
        
        case 235:
        
        case 236:
        
        case 237:
        
        case 238:
        
        case 239:
        
        case 240:
        
        case 241:
        
        case 242:
        
        case 243:
        
        case 244:
        
        case 245:
        
        case 246:
        
        case 247:
        
        case 248:
        
        case 249:
        
        case 250:
        
        case 251:
        
        case 252:
        
        case 253:
        
        case 254:
        
        default:
          break;
      } 
      char c = 'Ã';
      int j = (paramInt2 & 0xFF) - c;
      if (j < 0)
        j += 256; 
      int k = ((paramInt2 & 0xFFFF) >>> 8) - c;
      if (k < 0)
        k += 256; 
      for (byte b = 0; b < arrayOfChar.length; b++) {
        int m = b % 2;
        if (m == 0) {
          arrayOfChar[b] = (char)(arrayOfChar[b] ^ j);
          j = ((j >>> 3 | j << 5) ^ arrayOfChar[b]) & 0xFF;
        } else {
          arrayOfChar[b] = (char)(arrayOfChar[b] ^ k);
          k = ((k >>> 3 | k << 5) ^ arrayOfChar[b]) & 0xFF;
        } 
      } 
      l[i] = (new String(arrayOfChar)).intern();
    } 
    return l[i];
  }
}


/* Location:              C:\Users\Administrator\Desktop\Matrix_7.0.0_alpha28(3)(1).jar!\me\rerere\matrix\internal\av.class
 * Java compiler version: 5 (49.0)
 * JD-Core Version:       1.1.3
 */