package me.rerere.matrix.internal;

import java.lang.invoke.CallSite;
import java.lang.invoke.MethodHandle;
import java.lang.invoke.MethodHandles;
import java.lang.invoke.MethodType;
import java.lang.invoke.MutableCallSite;
import java.util.HashMap;
import java.util.List;
import java.util.Map;
import javax.crypto.Cipher;
import javax.crypto.SecretKey;
import javax.crypto.SecretKeyFactory;
import javax.crypto.spec.DESKeySpec;
import javax.crypto.spec.IvParameterSpec;
import me.rerere.matrix.thirdparty.org.jetbrains.annotations.NotNull;
import me.rerere.matrix.thirdparty.org.jetbrains.annotations.Nullable;
import org.bukkit.Location;
import org.bukkit.World;
import org.bukkit.command.CommandSender;
import org.bukkit.scheduler.BukkitTask;

public class pd extends xl {
  public static boolean a;
  
  public static boolean s;
  
  public static boolean u;
  
  public static boolean w;
  
  public static boolean f;
  
  public static boolean l;
  
  public static boolean r;
  
  public static boolean x;
  
  public static boolean z;
  
  public static boolean k;
  
  @Nullable
  public static BukkitTask v;
  
  public static boolean b;
  
  @Nullable
  public static String i;
  
  private static String d;
  
  private static final long e = o3.a(1017008951336862583L, 1879564378432863826L, MethodHandles.lookup().lookupClass()).a(90185918740640L);
  
  private static final String[] g;
  
  private static final String[] h;
  
  private static final Map j = new HashMap<>(13);
  
  public pd(long paramLong, short paramShort) {
    // Byte code:
    //   0: lload_1
    //   1: bipush #16
    //   3: lshl
    //   4: iload_3
    //   5: i2l
    //   6: bipush #48
    //   8: lshl
    //   9: bipush #48
    //   11: lushr
    //   12: lor
    //   13: getstatic me/rerere/matrix/internal/pd.e : J
    //   16: lxor
    //   17: lstore #4
    //   19: aload_0
    //   20: sipush #7349
    //   23: ldc2_w 6029132029960873295
    //   26: lload #4
    //   28: lxor
    //   29: <illegal opcode> z : (IJ)Ljava/lang/String;
    //   34: ldc ''
    //   36: sipush #16320
    //   39: ldc2_w 8416500618716726787
    //   42: lload #4
    //   44: lxor
    //   45: <illegal opcode> z : (IJ)Ljava/lang/String;
    //   50: sipush #21466
    //   53: ldc2_w 974228678448294422
    //   56: lload #4
    //   58: lxor
    //   59: <illegal opcode> z : (IJ)Ljava/lang/String;
    //   64: invokespecial <init> : (Ljava/lang/String;Ljava/lang/String;Ljava/lang/String;Ljava/lang/String;)V
    //   67: aload_0
    //   68: iconst_1
    //   69: invokevirtual b : (Z)V
    //   72: return
  }
  
  public void b(@NotNull CommandSender paramCommandSender, long paramLong, String[] paramArrayOfString) {
    // Byte code:
    //   0: lload_2
    //   1: dup2
    //   2: ldc2_w 116438873903646
    //   5: lxor
    //   6: lstore #5
    //   8: dup2
    //   9: ldc2_w 116511974072198
    //   12: lxor
    //   13: lstore #7
    //   15: dup2
    //   16: ldc2_w 84480766227863
    //   19: lxor
    //   20: dup2
    //   21: bipush #16
    //   23: lushr
    //   24: lstore #9
    //   26: dup2
    //   27: bipush #48
    //   29: lshl
    //   30: bipush #48
    //   32: lushr
    //   33: l2i
    //   34: istore #11
    //   36: pop2
    //   37: pop2
    //   38: invokestatic r : ()I
    //   41: istore #12
    //   43: aload_1
    //   44: invokeinterface getName : ()Ljava/lang/String;
    //   49: sipush #7787
    //   52: ldc2_w 7788943454001076550
    //   55: lload_2
    //   56: lxor
    //   57: <illegal opcode> z : (IJ)Ljava/lang/String;
    //   62: invokevirtual contains : (Ljava/lang/CharSequence;)Z
    //   65: iload #12
    //   67: ifeq -> 84
    //   70: ifne -> 81
    //   73: goto -> 80
    //   76: invokestatic a : (Ljava/lang/RuntimeException;)Ljava/lang/RuntimeException;
    //   79: athrow
    //   80: return
    //   81: aload #4
    //   83: arraylength
    //   84: iconst_1
    //   85: lload_2
    //   86: lconst_0
    //   87: lcmp
    //   88: iflt -> 343
    //   91: iload #12
    //   93: ifeq -> 343
    //   96: if_icmpne -> 314
    //   99: goto -> 106
    //   102: invokestatic a : (Ljava/lang/RuntimeException;)Ljava/lang/RuntimeException;
    //   105: athrow
    //   106: getstatic me/rerere/matrix/internal/pd.w : Z
    //   109: iload #12
    //   111: ifeq -> 132
    //   114: goto -> 121
    //   117: invokestatic a : (Ljava/lang/RuntimeException;)Ljava/lang/RuntimeException;
    //   120: athrow
    //   121: ifne -> 135
    //   124: goto -> 131
    //   127: invokestatic a : (Ljava/lang/RuntimeException;)Ljava/lang/RuntimeException;
    //   130: athrow
    //   131: iconst_1
    //   132: goto -> 136
    //   135: iconst_0
    //   136: putstatic me/rerere/matrix/internal/pd.w : Z
    //   139: aload_1
    //   140: new java/lang/StringBuilder
    //   143: dup
    //   144: invokespecial <init> : ()V
    //   147: getstatic me/rerere/matrix/internal/pd.w : Z
    //   150: ifeq -> 192
    //   153: new java/lang/StringBuilder
    //   156: dup
    //   157: invokespecial <init> : ()V
    //   160: getstatic org/bukkit/ChatColor.GREEN : Lorg/bukkit/ChatColor;
    //   163: invokevirtual append : (Ljava/lang/Object;)Ljava/lang/StringBuilder;
    //   166: sipush #18252
    //   169: ldc2_w 2327974441545842787
    //   172: lload_2
    //   173: lxor
    //   174: <illegal opcode> z : (IJ)Ljava/lang/String;
    //   179: invokevirtual append : (Ljava/lang/String;)Ljava/lang/StringBuilder;
    //   182: invokevirtual toString : ()Ljava/lang/String;
    //   185: goto -> 224
    //   188: invokestatic a : (Ljava/lang/RuntimeException;)Ljava/lang/RuntimeException;
    //   191: athrow
    //   192: new java/lang/StringBuilder
    //   195: dup
    //   196: invokespecial <init> : ()V
    //   199: getstatic org/bukkit/ChatColor.RED : Lorg/bukkit/ChatColor;
    //   202: invokevirtual append : (Ljava/lang/Object;)Ljava/lang/StringBuilder;
    //   205: sipush #29400
    //   208: ldc2_w 257230941755045322
    //   211: lload_2
    //   212: lxor
    //   213: <illegal opcode> z : (IJ)Ljava/lang/String;
    //   218: invokevirtual append : (Ljava/lang/String;)Ljava/lang/StringBuilder;
    //   221: invokevirtual toString : ()Ljava/lang/String;
    //   224: invokevirtual append : (Ljava/lang/String;)Ljava/lang/StringBuilder;
    //   227: sipush #16542
    //   230: ldc2_w 4113758273894926242
    //   233: lload_2
    //   234: lxor
    //   235: <illegal opcode> z : (IJ)Ljava/lang/String;
    //   240: invokevirtual append : (Ljava/lang/String;)Ljava/lang/StringBuilder;
    //   243: invokevirtual toString : ()Ljava/lang/String;
    //   246: invokeinterface sendMessage : (Ljava/lang/String;)V
    //   251: iload #12
    //   253: lload_2
    //   254: lconst_0
    //   255: lcmp
    //   256: iflt -> 305
    //   259: ifeq -> 303
    //   262: getstatic me/rerere/matrix/internal/pd.w : Z
    //   265: ifeq -> 2773
    //   268: goto -> 275
    //   271: invokestatic a : (Ljava/lang/RuntimeException;)Ljava/lang/RuntimeException;
    //   274: athrow
    //   275: sipush #2175
    //   278: ldc2_w 2573806152243908430
    //   281: lload_2
    //   282: lxor
    //   283: <illegal opcode> z : (IJ)Ljava/lang/String;
    //   288: lload #9
    //   290: iload #11
    //   292: i2s
    //   293: invokestatic b : (Ljava/lang/String;JS)V
    //   296: goto -> 303
    //   299: invokestatic a : (Ljava/lang/RuntimeException;)Ljava/lang/RuntimeException;
    //   302: athrow
    //   303: iload #12
    //   305: lload_2
    //   306: lconst_0
    //   307: lcmp
    //   308: iflt -> 317
    //   311: ifne -> 2773
    //   314: aload #4
    //   316: arraylength
    //   317: iload #12
    //   319: lload_2
    //   320: lconst_0
    //   321: lcmp
    //   322: ifle -> 375
    //   325: ifeq -> 373
    //   328: goto -> 335
    //   331: invokestatic a : (Ljava/lang/RuntimeException;)Ljava/lang/RuntimeException;
    //   334: athrow
    //   335: iconst_1
    //   336: goto -> 343
    //   339: invokestatic a : (Ljava/lang/RuntimeException;)Ljava/lang/RuntimeException;
    //   342: athrow
    //   343: if_icmple -> 2773
    //   346: aload #4
    //   348: iconst_1
    //   349: aaload
    //   350: sipush #19066
    //   353: ldc2_w 1567200232021249383
    //   356: lload_2
    //   357: lxor
    //   358: <illegal opcode> z : (IJ)Ljava/lang/String;
    //   363: invokevirtual equals : (Ljava/lang/Object;)Z
    //   366: goto -> 373
    //   369: invokestatic a : (Ljava/lang/RuntimeException;)Ljava/lang/RuntimeException;
    //   372: athrow
    //   373: iload #12
    //   375: lload_2
    //   376: lconst_0
    //   377: lcmp
    //   378: iflt -> 487
    //   381: ifeq -> 485
    //   384: ifeq -> 465
    //   387: goto -> 394
    //   390: invokestatic a : (Ljava/lang/RuntimeException;)Ljava/lang/RuntimeException;
    //   393: athrow
    //   394: getstatic me/rerere/matrix/internal/pd.s : Z
    //   397: iload #12
    //   399: ifeq -> 420
    //   402: goto -> 409
    //   405: invokestatic a : (Ljava/lang/RuntimeException;)Ljava/lang/RuntimeException;
    //   408: athrow
    //   409: ifne -> 423
    //   412: goto -> 419
    //   415: invokestatic a : (Ljava/lang/RuntimeException;)Ljava/lang/RuntimeException;
    //   418: athrow
    //   419: iconst_1
    //   420: goto -> 424
    //   423: iconst_0
    //   424: putstatic me/rerere/matrix/internal/pd.s : Z
    //   427: aload_1
    //   428: new java/lang/StringBuilder
    //   431: dup
    //   432: invokespecial <init> : ()V
    //   435: sipush #27636
    //   438: ldc2_w 2599746319864524002
    //   441: lload_2
    //   442: lxor
    //   443: <illegal opcode> z : (IJ)Ljava/lang/String;
    //   448: invokevirtual append : (Ljava/lang/String;)Ljava/lang/StringBuilder;
    //   451: getstatic me/rerere/matrix/internal/pd.s : Z
    //   454: invokevirtual append : (Z)Ljava/lang/StringBuilder;
    //   457: invokevirtual toString : ()Ljava/lang/String;
    //   460: invokeinterface sendMessage : (Ljava/lang/String;)V
    //   465: aload #4
    //   467: iconst_1
    //   468: aaload
    //   469: sipush #23647
    //   472: ldc2_w 8864313510231366498
    //   475: lload_2
    //   476: lxor
    //   477: <illegal opcode> z : (IJ)Ljava/lang/String;
    //   482: invokevirtual equals : (Ljava/lang/Object;)Z
    //   485: iload #12
    //   487: lload_2
    //   488: lconst_0
    //   489: lcmp
    //   490: ifle -> 599
    //   493: ifeq -> 597
    //   496: ifeq -> 577
    //   499: goto -> 506
    //   502: invokestatic a : (Ljava/lang/RuntimeException;)Ljava/lang/RuntimeException;
    //   505: athrow
    //   506: getstatic me/rerere/matrix/internal/pd.f : Z
    //   509: iload #12
    //   511: ifeq -> 532
    //   514: goto -> 521
    //   517: invokestatic a : (Ljava/lang/RuntimeException;)Ljava/lang/RuntimeException;
    //   520: athrow
    //   521: ifne -> 535
    //   524: goto -> 531
    //   527: invokestatic a : (Ljava/lang/RuntimeException;)Ljava/lang/RuntimeException;
    //   530: athrow
    //   531: iconst_1
    //   532: goto -> 536
    //   535: iconst_0
    //   536: putstatic me/rerere/matrix/internal/pd.f : Z
    //   539: aload_1
    //   540: new java/lang/StringBuilder
    //   543: dup
    //   544: invokespecial <init> : ()V
    //   547: sipush #4401
    //   550: ldc2_w 5898322892602021438
    //   553: lload_2
    //   554: lxor
    //   555: <illegal opcode> z : (IJ)Ljava/lang/String;
    //   560: invokevirtual append : (Ljava/lang/String;)Ljava/lang/StringBuilder;
    //   563: getstatic me/rerere/matrix/internal/pd.f : Z
    //   566: invokevirtual append : (Z)Ljava/lang/StringBuilder;
    //   569: invokevirtual toString : ()Ljava/lang/String;
    //   572: invokeinterface sendMessage : (Ljava/lang/String;)V
    //   577: aload #4
    //   579: iconst_1
    //   580: aaload
    //   581: sipush #23369
    //   584: ldc2_w 1286246436854586443
    //   587: lload_2
    //   588: lxor
    //   589: <illegal opcode> z : (IJ)Ljava/lang/String;
    //   594: invokevirtual equals : (Ljava/lang/Object;)Z
    //   597: iload #12
    //   599: lload_2
    //   600: lconst_0
    //   601: lcmp
    //   602: ifle -> 691
    //   605: ifeq -> 689
    //   608: ifeq -> 669
    //   611: goto -> 618
    //   614: invokestatic a : (Ljava/lang/RuntimeException;)Ljava/lang/RuntimeException;
    //   617: athrow
    //   618: aload_1
    //   619: checkcast org/bukkit/entity/Player
    //   622: new org/bukkit/util/Vector
    //   625: dup
    //   626: ldc2_w -0.125625
    //   629: ldc2_w 0.46075
    //   632: ldc2_w -2.396625
    //   635: invokespecial <init> : (DDD)V
    //   638: invokeinterface setVelocity : (Lorg/bukkit/util/Vector;)V
    //   643: aload_1
    //   644: sipush #12906
    //   647: ldc2_w 3369283812649776489
    //   650: lload_2
    //   651: lxor
    //   652: <illegal opcode> z : (IJ)Ljava/lang/String;
    //   657: invokeinterface sendMessage : (Ljava/lang/String;)V
    //   662: goto -> 669
    //   665: invokestatic a : (Ljava/lang/RuntimeException;)Ljava/lang/RuntimeException;
    //   668: athrow
    //   669: aload #4
    //   671: iconst_1
    //   672: aaload
    //   673: sipush #27958
    //   676: ldc2_w 534286197644487169
    //   679: lload_2
    //   680: lxor
    //   681: <illegal opcode> z : (IJ)Ljava/lang/String;
    //   686: invokevirtual equals : (Ljava/lang/Object;)Z
    //   689: iload #12
    //   691: lload_2
    //   692: lconst_0
    //   693: lcmp
    //   694: iflt -> 746
    //   697: ifeq -> 744
    //   700: ifeq -> 724
    //   703: goto -> 710
    //   706: invokestatic a : (Ljava/lang/RuntimeException;)Ljava/lang/RuntimeException;
    //   709: athrow
    //   710: aload_0
    //   711: lload #7
    //   713: aload_1
    //   714: invokespecial b : (JLorg/bukkit/command/CommandSender;)V
    //   717: goto -> 724
    //   720: invokestatic a : (Ljava/lang/RuntimeException;)Ljava/lang/RuntimeException;
    //   723: athrow
    //   724: aload #4
    //   726: iconst_1
    //   727: aaload
    //   728: sipush #10071
    //   731: ldc2_w 1208824371841048655
    //   734: lload_2
    //   735: lxor
    //   736: <illegal opcode> z : (IJ)Ljava/lang/String;
    //   741: invokevirtual equals : (Ljava/lang/Object;)Z
    //   744: iload #12
    //   746: lload_2
    //   747: lconst_0
    //   748: lcmp
    //   749: iflt -> 851
    //   752: ifeq -> 849
    //   755: ifeq -> 829
    //   758: goto -> 765
    //   761: invokestatic a : (Ljava/lang/RuntimeException;)Ljava/lang/RuntimeException;
    //   764: athrow
    //   765: aload_1
    //   766: checkcast org/bukkit/entity/Player
    //   769: astore #13
    //   771: aload #13
    //   773: invokeinterface getWorld : ()Lorg/bukkit/World;
    //   778: astore #14
    //   780: aload #13
    //   782: invokeinterface getLocation : ()Lorg/bukkit/Location;
    //   787: invokevirtual clone : ()Lorg/bukkit/Location;
    //   790: ldc2_w -0.5
    //   793: ldc2_w -0.1
    //   796: ldc2_w -0.5
    //   799: invokevirtual add : (DDD)Lorg/bukkit/Location;
    //   802: astore #15
    //   804: invokestatic getScheduler : ()Lorg/bukkit/scheduler/BukkitScheduler;
    //   807: invokestatic b : ()Lme/rerere/matrix/Matrix;
    //   810: aload #14
    //   812: aload #15
    //   814: aload_1
    //   815: <illegal opcode> run : (Lorg/bukkit/World;Lorg/bukkit/Location;Lorg/bukkit/command/CommandSender;)Ljava/lang/Runnable;
    //   820: ldc2_w 20
    //   823: invokeinterface runTaskLater : (Lorg/bukkit/plugin/Plugin;Ljava/lang/Runnable;J)Lorg/bukkit/scheduler/BukkitTask;
    //   828: pop
    //   829: aload #4
    //   831: iconst_1
    //   832: aaload
    //   833: sipush #10643
    //   836: ldc2_w 3586393319751691946
    //   839: lload_2
    //   840: lxor
    //   841: <illegal opcode> z : (IJ)Ljava/lang/String;
    //   846: invokevirtual equals : (Ljava/lang/Object;)Z
    //   849: iload #12
    //   851: lload_2
    //   852: lconst_0
    //   853: lcmp
    //   854: iflt -> 951
    //   857: ifeq -> 949
    //   860: ifeq -> 929
    //   863: goto -> 870
    //   866: invokestatic a : (Ljava/lang/RuntimeException;)Ljava/lang/RuntimeException;
    //   869: athrow
    //   870: aload_1
    //   871: checkcast org/bukkit/entity/Player
    //   874: astore #13
    //   876: aload #13
    //   878: invokeinterface getLocation : ()Lorg/bukkit/Location;
    //   883: invokevirtual clone : ()Lorg/bukkit/Location;
    //   886: astore #14
    //   888: aload #14
    //   890: fconst_0
    //   891: invokevirtual setYaw : (F)V
    //   894: aload #14
    //   896: fconst_0
    //   897: invokevirtual setPitch : (F)V
    //   900: aload #13
    //   902: aload #14
    //   904: invokeinterface teleport : (Lorg/bukkit/Location;)Z
    //   909: pop
    //   910: aload_1
    //   911: sipush #835
    //   914: ldc2_w 9106380961246872643
    //   917: lload_2
    //   918: lxor
    //   919: <illegal opcode> z : (IJ)Ljava/lang/String;
    //   924: invokeinterface sendMessage : (Ljava/lang/String;)V
    //   929: aload #4
    //   931: iconst_1
    //   932: aaload
    //   933: sipush #14087
    //   936: ldc2_w 6620944323108417566
    //   939: lload_2
    //   940: lxor
    //   941: <illegal opcode> z : (IJ)Ljava/lang/String;
    //   946: invokevirtual equals : (Ljava/lang/Object;)Z
    //   949: iload #12
    //   951: lload_2
    //   952: lconst_0
    //   953: lcmp
    //   954: iflt -> 1063
    //   957: ifeq -> 1061
    //   960: ifeq -> 1041
    //   963: goto -> 970
    //   966: invokestatic a : (Ljava/lang/RuntimeException;)Ljava/lang/RuntimeException;
    //   969: athrow
    //   970: getstatic me/rerere/matrix/internal/pd.a : Z
    //   973: iload #12
    //   975: ifeq -> 996
    //   978: goto -> 985
    //   981: invokestatic a : (Ljava/lang/RuntimeException;)Ljava/lang/RuntimeException;
    //   984: athrow
    //   985: ifne -> 999
    //   988: goto -> 995
    //   991: invokestatic a : (Ljava/lang/RuntimeException;)Ljava/lang/RuntimeException;
    //   994: athrow
    //   995: iconst_1
    //   996: goto -> 1000
    //   999: iconst_0
    //   1000: putstatic me/rerere/matrix/internal/pd.a : Z
    //   1003: aload_1
    //   1004: new java/lang/StringBuilder
    //   1007: dup
    //   1008: invokespecial <init> : ()V
    //   1011: sipush #26464
    //   1014: ldc2_w 5174907908302561399
    //   1017: lload_2
    //   1018: lxor
    //   1019: <illegal opcode> z : (IJ)Ljava/lang/String;
    //   1024: invokevirtual append : (Ljava/lang/String;)Ljava/lang/StringBuilder;
    //   1027: getstatic me/rerere/matrix/internal/pd.a : Z
    //   1030: invokevirtual append : (Z)Ljava/lang/StringBuilder;
    //   1033: invokevirtual toString : ()Ljava/lang/String;
    //   1036: invokeinterface sendMessage : (Ljava/lang/String;)V
    //   1041: aload #4
    //   1043: iconst_1
    //   1044: aaload
    //   1045: sipush #29375
    //   1048: ldc2_w 669096576789181828
    //   1051: lload_2
    //   1052: lxor
    //   1053: <illegal opcode> z : (IJ)Ljava/lang/String;
    //   1058: invokevirtual equals : (Ljava/lang/Object;)Z
    //   1061: iload #12
    //   1063: lload_2
    //   1064: lconst_0
    //   1065: lcmp
    //   1066: ifle -> 1234
    //   1069: ifeq -> 1232
    //   1072: ifeq -> 1212
    //   1075: goto -> 1082
    //   1078: invokestatic a : (Ljava/lang/RuntimeException;)Ljava/lang/RuntimeException;
    //   1081: athrow
    //   1082: aload_1
    //   1083: checkcast org/bukkit/entity/Player
    //   1086: invokeinterface getWorld : ()Lorg/bukkit/World;
    //   1091: invokeinterface getLivingEntities : ()Ljava/util/List;
    //   1096: invokeinterface iterator : ()Ljava/util/Iterator;
    //   1101: astore #13
    //   1103: aload #13
    //   1105: invokeinterface hasNext : ()Z
    //   1110: ifeq -> 1193
    //   1113: aload #13
    //   1115: invokeinterface next : ()Ljava/lang/Object;
    //   1120: checkcast org/bukkit/entity/LivingEntity
    //   1123: astore #14
    //   1125: lload_2
    //   1126: lconst_0
    //   1127: lcmp
    //   1128: ifle -> 1182
    //   1131: aload #14
    //   1133: iload #12
    //   1135: lload_2
    //   1136: lconst_0
    //   1137: lcmp
    //   1138: ifle -> 1197
    //   1141: ifeq -> 1177
    //   1144: instanceof org/bukkit/entity/Player
    //   1147: iload #12
    //   1149: ifeq -> 1232
    //   1152: goto -> 1159
    //   1155: invokestatic a : (Ljava/lang/RuntimeException;)Ljava/lang/RuntimeException;
    //   1158: athrow
    //   1159: ifeq -> 1175
    //   1162: goto -> 1169
    //   1165: invokestatic a : (Ljava/lang/RuntimeException;)Ljava/lang/RuntimeException;
    //   1168: athrow
    //   1169: lload_2
    //   1170: lconst_0
    //   1171: lcmp
    //   1172: ifge -> 1103
    //   1175: aload #14
    //   1177: invokeinterface remove : ()V
    //   1182: iload #12
    //   1184: lload_2
    //   1185: lconst_0
    //   1186: lcmp
    //   1187: ifle -> 1110
    //   1190: ifne -> 1103
    //   1193: aload_1
    //   1194: sipush #19787
    //   1197: ldc2_w 6361242413643647614
    //   1200: lload_2
    //   1201: lxor
    //   1202: <illegal opcode> z : (IJ)Ljava/lang/String;
    //   1207: invokeinterface sendMessage : (Ljava/lang/String;)V
    //   1212: aload #4
    //   1214: iconst_1
    //   1215: aaload
    //   1216: sipush #22543
    //   1219: ldc2_w 2428141344348200713
    //   1222: lload_2
    //   1223: lxor
    //   1224: <illegal opcode> z : (IJ)Ljava/lang/String;
    //   1229: invokevirtual equals : (Ljava/lang/Object;)Z
    //   1232: iload #12
    //   1234: lload_2
    //   1235: lconst_0
    //   1236: lcmp
    //   1237: ifle -> 1352
    //   1240: ifeq -> 1350
    //   1243: ifeq -> 1330
    //   1246: goto -> 1253
    //   1249: invokestatic a : (Ljava/lang/RuntimeException;)Ljava/lang/RuntimeException;
    //   1252: athrow
    //   1253: getstatic me/rerere/matrix/internal/pd.k : Z
    //   1256: iload #12
    //   1258: ifeq -> 1279
    //   1261: goto -> 1268
    //   1264: invokestatic a : (Ljava/lang/RuntimeException;)Ljava/lang/RuntimeException;
    //   1267: athrow
    //   1268: ifne -> 1282
    //   1271: goto -> 1278
    //   1274: invokestatic a : (Ljava/lang/RuntimeException;)Ljava/lang/RuntimeException;
    //   1277: athrow
    //   1278: iconst_1
    //   1279: goto -> 1283
    //   1282: iconst_0
    //   1283: putstatic me/rerere/matrix/internal/pd.k : Z
    //   1286: aload_1
    //   1287: new java/lang/StringBuilder
    //   1290: dup
    //   1291: invokespecial <init> : ()V
    //   1294: getstatic org/bukkit/ChatColor.GREEN : Lorg/bukkit/ChatColor;
    //   1297: invokevirtual append : (Ljava/lang/Object;)Ljava/lang/StringBuilder;
    //   1300: sipush #25334
    //   1303: ldc2_w 1369497621680448965
    //   1306: lload_2
    //   1307: lxor
    //   1308: <illegal opcode> z : (IJ)Ljava/lang/String;
    //   1313: invokevirtual append : (Ljava/lang/String;)Ljava/lang/StringBuilder;
    //   1316: getstatic me/rerere/matrix/internal/pd.k : Z
    //   1319: invokevirtual append : (Z)Ljava/lang/StringBuilder;
    //   1322: invokevirtual toString : ()Ljava/lang/String;
    //   1325: invokeinterface sendMessage : (Ljava/lang/String;)V
    //   1330: aload #4
    //   1332: iconst_1
    //   1333: aaload
    //   1334: sipush #4163
    //   1337: ldc2_w 6168880616329811816
    //   1340: lload_2
    //   1341: lxor
    //   1342: <illegal opcode> z : (IJ)Ljava/lang/String;
    //   1347: invokevirtual equals : (Ljava/lang/Object;)Z
    //   1350: iload #12
    //   1352: lload_2
    //   1353: lconst_0
    //   1354: lcmp
    //   1355: iflt -> 1469
    //   1358: ifeq -> 1467
    //   1361: ifeq -> 1448
    //   1364: goto -> 1371
    //   1367: invokestatic a : (Ljava/lang/RuntimeException;)Ljava/lang/RuntimeException;
    //   1370: athrow
    //   1371: getstatic me/rerere/matrix/internal/pd.b : Z
    //   1374: iload #12
    //   1376: ifeq -> 1397
    //   1379: goto -> 1386
    //   1382: invokestatic a : (Ljava/lang/RuntimeException;)Ljava/lang/RuntimeException;
    //   1385: athrow
    //   1386: ifne -> 1400
    //   1389: goto -> 1396
    //   1392: invokestatic a : (Ljava/lang/RuntimeException;)Ljava/lang/RuntimeException;
    //   1395: athrow
    //   1396: iconst_1
    //   1397: goto -> 1401
    //   1400: iconst_0
    //   1401: putstatic me/rerere/matrix/internal/pd.b : Z
    //   1404: aload_1
    //   1405: new java/lang/StringBuilder
    //   1408: dup
    //   1409: invokespecial <init> : ()V
    //   1412: getstatic org/bukkit/ChatColor.GREEN : Lorg/bukkit/ChatColor;
    //   1415: invokevirtual append : (Ljava/lang/Object;)Ljava/lang/StringBuilder;
    //   1418: sipush #26691
    //   1421: ldc2_w 5287113687412010873
    //   1424: lload_2
    //   1425: lxor
    //   1426: <illegal opcode> z : (IJ)Ljava/lang/String;
    //   1431: invokevirtual append : (Ljava/lang/String;)Ljava/lang/StringBuilder;
    //   1434: getstatic me/rerere/matrix/internal/pd.b : Z
    //   1437: invokevirtual append : (Z)Ljava/lang/StringBuilder;
    //   1440: invokevirtual toString : ()Ljava/lang/String;
    //   1443: invokeinterface sendMessage : (Ljava/lang/String;)V
    //   1448: aload #4
    //   1450: iconst_1
    //   1451: aaload
    //   1452: bipush #124
    //   1454: ldc2_w 4128818350293714778
    //   1457: lload_2
    //   1458: lxor
    //   1459: <illegal opcode> z : (IJ)Ljava/lang/String;
    //   1464: invokevirtual equalsIgnoreCase : (Ljava/lang/String;)Z
    //   1467: iload #12
    //   1469: lload_2
    //   1470: lconst_0
    //   1471: lcmp
    //   1472: iflt -> 1580
    //   1475: ifeq -> 1578
    //   1478: ifeq -> 1558
    //   1481: goto -> 1488
    //   1484: invokestatic a : (Ljava/lang/RuntimeException;)Ljava/lang/RuntimeException;
    //   1487: athrow
    //   1488: invokestatic b : ()Lme/rerere/matrix/Matrix;
    //   1491: invokevirtual b : ()Lme/rerere/matrix/internal/mn;
    //   1494: aload_1
    //   1495: checkcast org/bukkit/entity/Player
    //   1498: invokeinterface getUniqueId : ()Ljava/util/UUID;
    //   1503: invokevirtual b : (Ljava/util/UUID;)Lme/rerere/matrix/internal/yl;
    //   1506: aload_1
    //   1507: <illegal opcode> accept : (Lorg/bukkit/command/CommandSender;)Ljava/util/function/Consumer;
    //   1512: lload #5
    //   1514: dup2_x1
    //   1515: pop2
    //   1516: invokevirtual b : (JLjava/util/function/Consumer;)I
    //   1519: istore #13
    //   1521: aload_1
    //   1522: new java/lang/StringBuilder
    //   1525: dup
    //   1526: invokespecial <init> : ()V
    //   1529: sipush #4821
    //   1532: ldc2_w 3186207179181266378
    //   1535: lload_2
    //   1536: lxor
    //   1537: <illegal opcode> z : (IJ)Ljava/lang/String;
    //   1542: invokevirtual append : (Ljava/lang/String;)Ljava/lang/StringBuilder;
    //   1545: iload #13
    //   1547: invokevirtual append : (I)Ljava/lang/StringBuilder;
    //   1550: invokevirtual toString : ()Ljava/lang/String;
    //   1553: invokeinterface sendMessage : (Ljava/lang/String;)V
    //   1558: aload #4
    //   1560: iconst_1
    //   1561: aaload
    //   1562: sipush #12028
    //   1565: ldc2_w 2410221058882251203
    //   1568: lload_2
    //   1569: lxor
    //   1570: <illegal opcode> z : (IJ)Ljava/lang/String;
    //   1575: invokevirtual equals : (Ljava/lang/Object;)Z
    //   1578: iload #12
    //   1580: lload_2
    //   1581: lconst_0
    //   1582: lcmp
    //   1583: ifle -> 1771
    //   1586: ifeq -> 1769
    //   1589: ifeq -> 1749
    //   1592: goto -> 1599
    //   1595: invokestatic a : (Ljava/lang/RuntimeException;)Ljava/lang/RuntimeException;
    //   1598: athrow
    //   1599: aload #4
    //   1601: iload #12
    //   1603: lload_2
    //   1604: lconst_0
    //   1605: lcmp
    //   1606: ifle -> 1701
    //   1609: ifeq -> 1700
    //   1612: goto -> 1619
    //   1615: invokestatic a : (Ljava/lang/RuntimeException;)Ljava/lang/RuntimeException;
    //   1618: athrow
    //   1619: lload_2
    //   1620: lconst_0
    //   1621: lcmp
    //   1622: ifle -> 1693
    //   1625: arraylength
    //   1626: iconst_2
    //   1627: if_icmpne -> 1691
    //   1630: goto -> 1637
    //   1633: invokestatic a : (Ljava/lang/RuntimeException;)Ljava/lang/RuntimeException;
    //   1636: athrow
    //   1637: aconst_null
    //   1638: putstatic me/rerere/matrix/internal/pd.i : Ljava/lang/String;
    //   1641: aload_1
    //   1642: new java/lang/StringBuilder
    //   1645: dup
    //   1646: invokespecial <init> : ()V
    //   1649: getstatic org/bukkit/ChatColor.GREEN : Lorg/bukkit/ChatColor;
    //   1652: invokevirtual append : (Ljava/lang/Object;)Ljava/lang/StringBuilder;
    //   1655: sipush #24003
    //   1658: ldc2_w 4240283417352624841
    //   1661: lload_2
    //   1662: lxor
    //   1663: <illegal opcode> z : (IJ)Ljava/lang/String;
    //   1668: invokevirtual append : (Ljava/lang/String;)Ljava/lang/StringBuilder;
    //   1671: invokevirtual toString : ()Ljava/lang/String;
    //   1674: invokeinterface sendMessage : (Ljava/lang/String;)V
    //   1679: iload #12
    //   1681: ifne -> 1749
    //   1684: goto -> 1691
    //   1687: invokestatic a : (Ljava/lang/RuntimeException;)Ljava/lang/RuntimeException;
    //   1690: athrow
    //   1691: aload #4
    //   1693: goto -> 1700
    //   1696: invokestatic a : (Ljava/lang/RuntimeException;)Ljava/lang/RuntimeException;
    //   1699: athrow
    //   1700: iconst_2
    //   1701: aaload
    //   1702: putstatic me/rerere/matrix/internal/pd.i : Ljava/lang/String;
    //   1705: aload_1
    //   1706: new java/lang/StringBuilder
    //   1709: dup
    //   1710: invokespecial <init> : ()V
    //   1713: getstatic org/bukkit/ChatColor.GREEN : Lorg/bukkit/ChatColor;
    //   1716: invokevirtual append : (Ljava/lang/Object;)Ljava/lang/StringBuilder;
    //   1719: sipush #16921
    //   1722: ldc2_w 2299307363235808553
    //   1725: lload_2
    //   1726: lxor
    //   1727: <illegal opcode> z : (IJ)Ljava/lang/String;
    //   1732: invokevirtual append : (Ljava/lang/String;)Ljava/lang/StringBuilder;
    //   1735: getstatic me/rerere/matrix/internal/pd.i : Ljava/lang/String;
    //   1738: invokevirtual append : (Ljava/lang/String;)Ljava/lang/StringBuilder;
    //   1741: invokevirtual toString : ()Ljava/lang/String;
    //   1744: invokeinterface sendMessage : (Ljava/lang/String;)V
    //   1749: aload #4
    //   1751: iconst_1
    //   1752: aaload
    //   1753: sipush #3129
    //   1756: ldc2_w 3615435290407144253
    //   1759: lload_2
    //   1760: lxor
    //   1761: <illegal opcode> z : (IJ)Ljava/lang/String;
    //   1766: invokevirtual equals : (Ljava/lang/Object;)Z
    //   1769: iload #12
    //   1771: lload_2
    //   1772: lconst_0
    //   1773: lcmp
    //   1774: iflt -> 1902
    //   1777: ifeq -> 1900
    //   1780: ifeq -> 1880
    //   1783: goto -> 1790
    //   1786: invokestatic a : (Ljava/lang/RuntimeException;)Ljava/lang/RuntimeException;
    //   1789: athrow
    //   1790: invokestatic b : ()Lme/rerere/matrix/Matrix;
    //   1793: invokevirtual b : ()Lme/rerere/matrix/internal/mn;
    //   1796: aload_1
    //   1797: checkcast org/bukkit/entity/Player
    //   1800: invokeinterface getUniqueId : ()Ljava/util/UUID;
    //   1805: invokevirtual b : (Ljava/util/UUID;)Lme/rerere/matrix/internal/yl;
    //   1808: astore #13
    //   1810: aload #13
    //   1812: aload #13
    //   1814: invokevirtual j : ()Z
    //   1817: iload #12
    //   1819: ifeq -> 1833
    //   1822: ifne -> 1836
    //   1825: goto -> 1832
    //   1828: invokestatic a : (Ljava/lang/RuntimeException;)Ljava/lang/RuntimeException;
    //   1831: athrow
    //   1832: iconst_1
    //   1833: goto -> 1837
    //   1836: iconst_0
    //   1837: invokevirtual p : (Z)V
    //   1840: aload_1
    //   1841: new java/lang/StringBuilder
    //   1844: dup
    //   1845: invokespecial <init> : ()V
    //   1848: sipush #588
    //   1851: ldc2_w 2486102950801016144
    //   1854: lload_2
    //   1855: lxor
    //   1856: <illegal opcode> z : (IJ)Ljava/lang/String;
    //   1861: invokevirtual append : (Ljava/lang/String;)Ljava/lang/StringBuilder;
    //   1864: aload #13
    //   1866: invokevirtual j : ()Z
    //   1869: invokevirtual append : (Z)Ljava/lang/StringBuilder;
    //   1872: invokevirtual toString : ()Ljava/lang/String;
    //   1875: invokeinterface sendMessage : (Ljava/lang/String;)V
    //   1880: aload #4
    //   1882: iconst_1
    //   1883: aaload
    //   1884: sipush #2431
    //   1887: ldc2_w 2385960286007168577
    //   1890: lload_2
    //   1891: lxor
    //   1892: <illegal opcode> z : (IJ)Ljava/lang/String;
    //   1897: invokevirtual equals : (Ljava/lang/Object;)Z
    //   1900: iload #12
    //   1902: lload_2
    //   1903: lconst_0
    //   1904: lcmp
    //   1905: iflt -> 2020
    //   1908: ifeq -> 2018
    //   1911: ifeq -> 1998
    //   1914: goto -> 1921
    //   1917: invokestatic a : (Ljava/lang/RuntimeException;)Ljava/lang/RuntimeException;
    //   1920: athrow
    //   1921: getstatic me/rerere/matrix/internal/pd.u : Z
    //   1924: iload #12
    //   1926: ifeq -> 1947
    //   1929: goto -> 1936
    //   1932: invokestatic a : (Ljava/lang/RuntimeException;)Ljava/lang/RuntimeException;
    //   1935: athrow
    //   1936: ifne -> 1950
    //   1939: goto -> 1946
    //   1942: invokestatic a : (Ljava/lang/RuntimeException;)Ljava/lang/RuntimeException;
    //   1945: athrow
    //   1946: iconst_1
    //   1947: goto -> 1951
    //   1950: iconst_0
    //   1951: putstatic me/rerere/matrix/internal/pd.u : Z
    //   1954: aload_1
    //   1955: new java/lang/StringBuilder
    //   1958: dup
    //   1959: invokespecial <init> : ()V
    //   1962: getstatic org/bukkit/ChatColor.GREEN : Lorg/bukkit/ChatColor;
    //   1965: invokevirtual append : (Ljava/lang/Object;)Ljava/lang/StringBuilder;
    //   1968: sipush #8469
    //   1971: ldc2_w 210531028042524176
    //   1974: lload_2
    //   1975: lxor
    //   1976: <illegal opcode> z : (IJ)Ljava/lang/String;
    //   1981: invokevirtual append : (Ljava/lang/String;)Ljava/lang/StringBuilder;
    //   1984: getstatic me/rerere/matrix/internal/pd.u : Z
    //   1987: invokevirtual append : (Z)Ljava/lang/StringBuilder;
    //   1990: invokevirtual toString : ()Ljava/lang/String;
    //   1993: invokeinterface sendMessage : (Ljava/lang/String;)V
    //   1998: aload #4
    //   2000: iconst_1
    //   2001: aaload
    //   2002: sipush #23523
    //   2005: ldc2_w 6164218371001048269
    //   2008: lload_2
    //   2009: lxor
    //   2010: <illegal opcode> z : (IJ)Ljava/lang/String;
    //   2015: invokevirtual equals : (Ljava/lang/Object;)Z
    //   2018: iload #12
    //   2020: lload_2
    //   2021: lconst_0
    //   2022: lcmp
    //   2023: ifle -> 2138
    //   2026: ifeq -> 2136
    //   2029: ifeq -> 2116
    //   2032: goto -> 2039
    //   2035: invokestatic a : (Ljava/lang/RuntimeException;)Ljava/lang/RuntimeException;
    //   2038: athrow
    //   2039: getstatic me/rerere/matrix/internal/pd.z : Z
    //   2042: iload #12
    //   2044: ifeq -> 2065
    //   2047: goto -> 2054
    //   2050: invokestatic a : (Ljava/lang/RuntimeException;)Ljava/lang/RuntimeException;
    //   2053: athrow
    //   2054: ifne -> 2068
    //   2057: goto -> 2064
    //   2060: invokestatic a : (Ljava/lang/RuntimeException;)Ljava/lang/RuntimeException;
    //   2063: athrow
    //   2064: iconst_1
    //   2065: goto -> 2069
    //   2068: iconst_0
    //   2069: putstatic me/rerere/matrix/internal/pd.z : Z
    //   2072: aload_1
    //   2073: new java/lang/StringBuilder
    //   2076: dup
    //   2077: invokespecial <init> : ()V
    //   2080: getstatic org/bukkit/ChatColor.GREEN : Lorg/bukkit/ChatColor;
    //   2083: invokevirtual append : (Ljava/lang/Object;)Ljava/lang/StringBuilder;
    //   2086: sipush #31886
    //   2089: ldc2_w 7086591951355444103
    //   2092: lload_2
    //   2093: lxor
    //   2094: <illegal opcode> z : (IJ)Ljava/lang/String;
    //   2099: invokevirtual append : (Ljava/lang/String;)Ljava/lang/StringBuilder;
    //   2102: getstatic me/rerere/matrix/internal/pd.z : Z
    //   2105: invokevirtual append : (Z)Ljava/lang/StringBuilder;
    //   2108: invokevirtual toString : ()Ljava/lang/String;
    //   2111: invokeinterface sendMessage : (Ljava/lang/String;)V
    //   2116: aload #4
    //   2118: iconst_1
    //   2119: aaload
    //   2120: sipush #29819
    //   2123: ldc2_w 1275087268119376735
    //   2126: lload_2
    //   2127: lxor
    //   2128: <illegal opcode> z : (IJ)Ljava/lang/String;
    //   2133: invokevirtual equals : (Ljava/lang/Object;)Z
    //   2136: iload #12
    //   2138: lload_2
    //   2139: lconst_0
    //   2140: lcmp
    //   2141: iflt -> 2256
    //   2144: ifeq -> 2254
    //   2147: ifeq -> 2234
    //   2150: goto -> 2157
    //   2153: invokestatic a : (Ljava/lang/RuntimeException;)Ljava/lang/RuntimeException;
    //   2156: athrow
    //   2157: getstatic me/rerere/matrix/internal/pd.r : Z
    //   2160: iload #12
    //   2162: ifeq -> 2183
    //   2165: goto -> 2172
    //   2168: invokestatic a : (Ljava/lang/RuntimeException;)Ljava/lang/RuntimeException;
    //   2171: athrow
    //   2172: ifne -> 2186
    //   2175: goto -> 2182
    //   2178: invokestatic a : (Ljava/lang/RuntimeException;)Ljava/lang/RuntimeException;
    //   2181: athrow
    //   2182: iconst_1
    //   2183: goto -> 2187
    //   2186: iconst_0
    //   2187: putstatic me/rerere/matrix/internal/pd.r : Z
    //   2190: aload_1
    //   2191: new java/lang/StringBuilder
    //   2194: dup
    //   2195: invokespecial <init> : ()V
    //   2198: getstatic org/bukkit/ChatColor.GREEN : Lorg/bukkit/ChatColor;
    //   2201: invokevirtual append : (Ljava/lang/Object;)Ljava/lang/StringBuilder;
    //   2204: sipush #25446
    //   2207: ldc2_w 6148134674323563617
    //   2210: lload_2
    //   2211: lxor
    //   2212: <illegal opcode> z : (IJ)Ljava/lang/String;
    //   2217: invokevirtual append : (Ljava/lang/String;)Ljava/lang/StringBuilder;
    //   2220: getstatic me/rerere/matrix/internal/pd.r : Z
    //   2223: invokevirtual append : (Z)Ljava/lang/StringBuilder;
    //   2226: invokevirtual toString : ()Ljava/lang/String;
    //   2229: invokeinterface sendMessage : (Ljava/lang/String;)V
    //   2234: aload #4
    //   2236: iconst_1
    //   2237: aaload
    //   2238: sipush #20181
    //   2241: ldc2_w 3735504804206889441
    //   2244: lload_2
    //   2245: lxor
    //   2246: <illegal opcode> z : (IJ)Ljava/lang/String;
    //   2251: invokevirtual equals : (Ljava/lang/Object;)Z
    //   2254: iload #12
    //   2256: lload_2
    //   2257: lconst_0
    //   2258: lcmp
    //   2259: ifle -> 2374
    //   2262: ifeq -> 2372
    //   2265: ifeq -> 2352
    //   2268: goto -> 2275
    //   2271: invokestatic a : (Ljava/lang/RuntimeException;)Ljava/lang/RuntimeException;
    //   2274: athrow
    //   2275: getstatic me/rerere/matrix/internal/pd.l : Z
    //   2278: iload #12
    //   2280: ifeq -> 2301
    //   2283: goto -> 2290
    //   2286: invokestatic a : (Ljava/lang/RuntimeException;)Ljava/lang/RuntimeException;
    //   2289: athrow
    //   2290: ifne -> 2304
    //   2293: goto -> 2300
    //   2296: invokestatic a : (Ljava/lang/RuntimeException;)Ljava/lang/RuntimeException;
    //   2299: athrow
    //   2300: iconst_1
    //   2301: goto -> 2305
    //   2304: iconst_0
    //   2305: putstatic me/rerere/matrix/internal/pd.l : Z
    //   2308: aload_1
    //   2309: new java/lang/StringBuilder
    //   2312: dup
    //   2313: invokespecial <init> : ()V
    //   2316: getstatic org/bukkit/ChatColor.GREEN : Lorg/bukkit/ChatColor;
    //   2319: invokevirtual append : (Ljava/lang/Object;)Ljava/lang/StringBuilder;
    //   2322: sipush #11707
    //   2325: ldc2_w 5818094638499637901
    //   2328: lload_2
    //   2329: lxor
    //   2330: <illegal opcode> z : (IJ)Ljava/lang/String;
    //   2335: invokevirtual append : (Ljava/lang/String;)Ljava/lang/StringBuilder;
    //   2338: getstatic me/rerere/matrix/internal/pd.l : Z
    //   2341: invokevirtual append : (Z)Ljava/lang/StringBuilder;
    //   2344: invokevirtual toString : ()Ljava/lang/String;
    //   2347: invokeinterface sendMessage : (Ljava/lang/String;)V
    //   2352: aload #4
    //   2354: iconst_1
    //   2355: aaload
    //   2356: sipush #2917
    //   2359: ldc2_w 3138705956961455217
    //   2362: lload_2
    //   2363: lxor
    //   2364: <illegal opcode> z : (IJ)Ljava/lang/String;
    //   2369: invokevirtual equals : (Ljava/lang/Object;)Z
    //   2372: iload #12
    //   2374: lload_2
    //   2375: lconst_0
    //   2376: lcmp
    //   2377: iflt -> 2498
    //   2380: ifeq -> 2490
    //   2383: ifeq -> 2470
    //   2386: goto -> 2393
    //   2389: invokestatic a : (Ljava/lang/RuntimeException;)Ljava/lang/RuntimeException;
    //   2392: athrow
    //   2393: getstatic me/rerere/matrix/internal/pd.x : Z
    //   2396: iload #12
    //   2398: ifeq -> 2419
    //   2401: goto -> 2408
    //   2404: invokestatic a : (Ljava/lang/RuntimeException;)Ljava/lang/RuntimeException;
    //   2407: athrow
    //   2408: ifne -> 2422
    //   2411: goto -> 2418
    //   2414: invokestatic a : (Ljava/lang/RuntimeException;)Ljava/lang/RuntimeException;
    //   2417: athrow
    //   2418: iconst_1
    //   2419: goto -> 2423
    //   2422: iconst_0
    //   2423: putstatic me/rerere/matrix/internal/pd.x : Z
    //   2426: aload_1
    //   2427: new java/lang/StringBuilder
    //   2430: dup
    //   2431: invokespecial <init> : ()V
    //   2434: getstatic org/bukkit/ChatColor.GREEN : Lorg/bukkit/ChatColor;
    //   2437: invokevirtual append : (Ljava/lang/Object;)Ljava/lang/StringBuilder;
    //   2440: sipush #21449
    //   2443: ldc2_w 5910231425790039234
    //   2446: lload_2
    //   2447: lxor
    //   2448: <illegal opcode> z : (IJ)Ljava/lang/String;
    //   2453: invokevirtual append : (Ljava/lang/String;)Ljava/lang/StringBuilder;
    //   2456: getstatic me/rerere/matrix/internal/pd.x : Z
    //   2459: invokevirtual append : (Z)Ljava/lang/StringBuilder;
    //   2462: invokevirtual toString : ()Ljava/lang/String;
    //   2465: invokeinterface sendMessage : (Ljava/lang/String;)V
    //   2470: aload #4
    //   2472: iconst_1
    //   2473: aaload
    //   2474: sipush #30227
    //   2477: ldc2_w 6195653023669612808
    //   2480: lload_2
    //   2481: lxor
    //   2482: <illegal opcode> z : (IJ)Ljava/lang/String;
    //   2487: invokevirtual equals : (Ljava/lang/Object;)Z
    //   2490: lload_2
    //   2491: lconst_0
    //   2492: lcmp
    //   2493: ifle -> 2647
    //   2496: iload #12
    //   2498: ifeq -> 2647
    //   2501: ifeq -> 2627
    //   2504: goto -> 2511
    //   2507: invokestatic a : (Ljava/lang/RuntimeException;)Ljava/lang/RuntimeException;
    //   2510: athrow
    //   2511: iconst_0
    //   2512: istore #13
    //   2514: iload #13
    //   2516: sipush #10000
    //   2519: if_icmpge -> 2608
    //   2522: sipush #31963
    //   2525: ldc2_w 4037693228977880049
    //   2528: lload_2
    //   2529: lxor
    //   2530: <illegal opcode> z : (IJ)Ljava/lang/String;
    //   2535: lload_2
    //   2536: lconst_0
    //   2537: lcmp
    //   2538: iflt -> 2631
    //   2541: invokestatic getWorld : (Ljava/lang/String;)Lorg/bukkit/World;
    //   2544: aload_1
    //   2545: checkcast org/bukkit/entity/Player
    //   2548: invokeinterface getLocation : ()Lorg/bukkit/Location;
    //   2553: getstatic org/bukkit/entity/EntityType.ZOMBIE : Lorg/bukkit/entity/EntityType;
    //   2556: invokeinterface spawnEntity : (Lorg/bukkit/Location;Lorg/bukkit/entity/EntityType;)Lorg/bukkit/entity/Entity;
    //   2561: checkcast org/bukkit/entity/LivingEntity
    //   2564: astore #14
    //   2566: aload #14
    //   2568: iconst_0
    //   2569: invokeinterface setCollidable : (Z)V
    //   2574: aload #14
    //   2576: iconst_0
    //   2577: invokeinterface setAI : (Z)V
    //   2582: iinc #13, 1
    //   2585: iload #12
    //   2587: ifeq -> 2627
    //   2590: iload #12
    //   2592: ifne -> 2514
    //   2595: lload_2
    //   2596: lconst_0
    //   2597: lcmp
    //   2598: ifle -> 2585
    //   2601: goto -> 2608
    //   2604: invokestatic a : (Ljava/lang/RuntimeException;)Ljava/lang/RuntimeException;
    //   2607: athrow
    //   2608: aload_1
    //   2609: sipush #18158
    //   2612: ldc2_w 5550198380871008710
    //   2615: lload_2
    //   2616: lxor
    //   2617: <illegal opcode> z : (IJ)Ljava/lang/String;
    //   2622: invokeinterface sendMessage : (Ljava/lang/String;)V
    //   2627: aload #4
    //   2629: iconst_1
    //   2630: aaload
    //   2631: sipush #25054
    //   2634: ldc2_w 66044608308176589
    //   2637: lload_2
    //   2638: lxor
    //   2639: <illegal opcode> z : (IJ)Ljava/lang/String;
    //   2644: invokevirtual equals : (Ljava/lang/Object;)Z
    //   2647: ifeq -> 2773
    //   2650: getstatic me/rerere/matrix/internal/pd.v : Lorg/bukkit/scheduler/BukkitTask;
    //   2653: iload #12
    //   2655: ifeq -> 2745
    //   2658: goto -> 2665
    //   2661: invokestatic a : (Ljava/lang/RuntimeException;)Ljava/lang/RuntimeException;
    //   2664: athrow
    //   2665: lload_2
    //   2666: lconst_0
    //   2667: lcmp
    //   2668: ifle -> 2738
    //   2671: ifnonnull -> 2735
    //   2674: goto -> 2681
    //   2677: invokestatic a : (Ljava/lang/RuntimeException;)Ljava/lang/RuntimeException;
    //   2680: athrow
    //   2681: aload_1
    //   2682: sipush #10293
    //   2685: ldc2_w 6707606308011978557
    //   2688: lload_2
    //   2689: lxor
    //   2690: <illegal opcode> z : (IJ)Ljava/lang/String;
    //   2695: invokeinterface sendMessage : (Ljava/lang/String;)V
    //   2700: invokestatic getScheduler : ()Lorg/bukkit/scheduler/BukkitScheduler;
    //   2703: invokestatic b : ()Lme/rerere/matrix/Matrix;
    //   2706: <illegal opcode> run : ()Ljava/lang/Runnable;
    //   2711: lconst_0
    //   2712: ldc2_w 5
    //   2715: invokeinterface runTaskTimer : (Lorg/bukkit/plugin/Plugin;Ljava/lang/Runnable;JJ)Lorg/bukkit/scheduler/BukkitTask;
    //   2720: putstatic me/rerere/matrix/internal/pd.v : Lorg/bukkit/scheduler/BukkitTask;
    //   2723: iload #12
    //   2725: ifne -> 2773
    //   2728: goto -> 2735
    //   2731: invokestatic a : (Ljava/lang/RuntimeException;)Ljava/lang/RuntimeException;
    //   2734: athrow
    //   2735: getstatic me/rerere/matrix/internal/pd.v : Lorg/bukkit/scheduler/BukkitTask;
    //   2738: goto -> 2745
    //   2741: invokestatic a : (Ljava/lang/RuntimeException;)Ljava/lang/RuntimeException;
    //   2744: athrow
    //   2745: invokeinterface cancel : ()V
    //   2750: aconst_null
    //   2751: putstatic me/rerere/matrix/internal/pd.v : Lorg/bukkit/scheduler/BukkitTask;
    //   2754: aload_1
    //   2755: sipush #29650
    //   2758: ldc2_w 3723585915714041052
    //   2761: lload_2
    //   2762: lxor
    //   2763: <illegal opcode> z : (IJ)Ljava/lang/String;
    //   2768: invokeinterface sendMessage : (Ljava/lang/String;)V
    //   2773: return
    // Exception table:
    //   from	to	target	type
    //   43	73	76	java/lang/RuntimeException
    //   84	99	102	java/lang/RuntimeException
    //   96	114	117	java/lang/RuntimeException
    //   106	124	127	java/lang/RuntimeException
    //   136	188	188	java/lang/RuntimeException
    //   224	268	271	java/lang/RuntimeException
    //   262	296	299	java/lang/RuntimeException
    //   303	328	331	java/lang/RuntimeException
    //   314	336	339	java/lang/RuntimeException
    //   343	366	369	java/lang/RuntimeException
    //   373	387	390	java/lang/RuntimeException
    //   384	402	405	java/lang/RuntimeException
    //   394	412	415	java/lang/RuntimeException
    //   485	499	502	java/lang/RuntimeException
    //   496	514	517	java/lang/RuntimeException
    //   506	524	527	java/lang/RuntimeException
    //   597	611	614	java/lang/RuntimeException
    //   608	662	665	java/lang/RuntimeException
    //   689	703	706	java/lang/RuntimeException
    //   700	717	720	java/lang/RuntimeException
    //   744	758	761	java/lang/RuntimeException
    //   849	863	866	java/lang/RuntimeException
    //   949	963	966	java/lang/RuntimeException
    //   960	978	981	java/lang/RuntimeException
    //   970	988	991	java/lang/RuntimeException
    //   1061	1075	1078	java/lang/RuntimeException
    //   1125	1152	1155	java/lang/RuntimeException
    //   1144	1162	1165	java/lang/RuntimeException
    //   1232	1246	1249	java/lang/RuntimeException
    //   1243	1261	1264	java/lang/RuntimeException
    //   1253	1271	1274	java/lang/RuntimeException
    //   1350	1364	1367	java/lang/RuntimeException
    //   1361	1379	1382	java/lang/RuntimeException
    //   1371	1389	1392	java/lang/RuntimeException
    //   1467	1481	1484	java/lang/RuntimeException
    //   1578	1592	1595	java/lang/RuntimeException
    //   1589	1612	1615	java/lang/RuntimeException
    //   1599	1630	1633	java/lang/RuntimeException
    //   1619	1684	1687	java/lang/RuntimeException
    //   1637	1693	1696	java/lang/RuntimeException
    //   1769	1783	1786	java/lang/RuntimeException
    //   1810	1825	1828	java/lang/RuntimeException
    //   1900	1914	1917	java/lang/RuntimeException
    //   1911	1929	1932	java/lang/RuntimeException
    //   1921	1939	1942	java/lang/RuntimeException
    //   2018	2032	2035	java/lang/RuntimeException
    //   2029	2047	2050	java/lang/RuntimeException
    //   2039	2057	2060	java/lang/RuntimeException
    //   2136	2150	2153	java/lang/RuntimeException
    //   2147	2165	2168	java/lang/RuntimeException
    //   2157	2175	2178	java/lang/RuntimeException
    //   2254	2268	2271	java/lang/RuntimeException
    //   2265	2283	2286	java/lang/RuntimeException
    //   2275	2293	2296	java/lang/RuntimeException
    //   2372	2386	2389	java/lang/RuntimeException
    //   2383	2401	2404	java/lang/RuntimeException
    //   2393	2411	2414	java/lang/RuntimeException
    //   2490	2504	2507	java/lang/RuntimeException
    //   2566	2595	2604	java/lang/RuntimeException
    //   2647	2658	2661	java/lang/RuntimeException
    //   2650	2674	2677	java/lang/RuntimeException
    //   2665	2728	2731	java/lang/RuntimeException
    //   2681	2738	2741	java/lang/RuntimeException
  }
  
  public List b(long paramLong) {
    // Byte code:
    //   0: bipush #8
    //   2: anewarray java/lang/String
    //   5: dup
    //   6: iconst_0
    //   7: sipush #3727
    //   10: ldc2_w 6952068011518242970
    //   13: lload_1
    //   14: lxor
    //   15: <illegal opcode> z : (IJ)Ljava/lang/String;
    //   20: aastore
    //   21: dup
    //   22: iconst_1
    //   23: sipush #32120
    //   26: ldc2_w 6313831235490366333
    //   29: lload_1
    //   30: lxor
    //   31: <illegal opcode> z : (IJ)Ljava/lang/String;
    //   36: aastore
    //   37: dup
    //   38: iconst_2
    //   39: sipush #512
    //   42: ldc2_w 696265907722304536
    //   45: lload_1
    //   46: lxor
    //   47: <illegal opcode> z : (IJ)Ljava/lang/String;
    //   52: aastore
    //   53: dup
    //   54: iconst_3
    //   55: sipush #20603
    //   58: ldc2_w 5380904423182102086
    //   61: lload_1
    //   62: lxor
    //   63: <illegal opcode> z : (IJ)Ljava/lang/String;
    //   68: aastore
    //   69: dup
    //   70: iconst_4
    //   71: sipush #31866
    //   74: ldc2_w 8503615711577260617
    //   77: lload_1
    //   78: lxor
    //   79: <illegal opcode> z : (IJ)Ljava/lang/String;
    //   84: aastore
    //   85: dup
    //   86: iconst_5
    //   87: sipush #9108
    //   90: ldc2_w 5695468978505948560
    //   93: lload_1
    //   94: lxor
    //   95: <illegal opcode> z : (IJ)Ljava/lang/String;
    //   100: aastore
    //   101: dup
    //   102: bipush #6
    //   104: sipush #26751
    //   107: ldc2_w 2962650913806374478
    //   110: lload_1
    //   111: lxor
    //   112: <illegal opcode> z : (IJ)Ljava/lang/String;
    //   117: aastore
    //   118: dup
    //   119: bipush #7
    //   121: sipush #11260
    //   124: ldc2_w 2784193075875714550
    //   127: lload_1
    //   128: lxor
    //   129: <illegal opcode> z : (IJ)Ljava/lang/String;
    //   134: aastore
    //   135: invokestatic asList : ([Ljava/lang/Object;)Ljava/util/List;
    //   138: areturn
  }
  
  static {
    long l = e ^ 0x3DFEBF718743L;
    h(null);
    (new byte[8])[0] = (byte)(int)(l >>> 56L);
    for (byte b1 = 1; b1 < 8; b1++)
      (new byte[8])[b1] = (byte)(int)(l << b1 * 8 >>> 56L); 
    Cipher cipher;
    (cipher = Cipher.getInstance("DES/CBC/PKCS5Padding")).init(2, SecretKeyFactory.getInstance("DES").generateSecret(new DESKeySpec(new byte[8])), new IvParameterSpec(new byte[8]));
    String[] arrayOfString = new String[60];
    boolean bool = false;
    String str;
    int i = (str = "9\003\037\007^%d\fj\032((?'4):U\030oA\0278\031XG40A2  SFJf?e:\004b2\035m%fR3O\035\020p.s/\023mCe.uO\030.e'<\0358\002\003w;\032\000)\004\fA 4LA\004buc#MvO\\<^5\r\020u\035'\001n+\020\035/$\026i3\0329p S^yCRv\032'\0165d2kb\030M(\007.\021'Gt[\013_, \006{\000\b\000l<\020=BsXB9}-\\a(\004P\b%;z8\0019\003q\031z\rJ?/D~  '\035\fi+t[y\017 \036X\n\022U|*\020z~\"\022X$\\\b?\0203x|\023M\030{N\020gHz\031\005(J8^<\0351A3%Lb)1(pL?|\0039pe:\036\030T%[9\013Rt[1[!:?ri\032 @\\6H\026U.:h\023OPO\035=Rk| 'v|G\037Dd?9\f\023\000?q6\n(#/U 5Xk\020`\026p$:UX}(\f\"\034S\0049h\0060B))\0164E^^s%\tn+\002S\035U7\027\024mN@0=\031\006eX\023fUy[P\nP\037xOt+\033c+ \032\007.\tftKL;!5PgE\016y\033\020:bRa#AB U\001:\nO4\n\021K('@Mkp\021\020\021 \016\nuex(p\017=hkk\024Fi\013]C7gj\005\0200\020\0259\021\0066Tm\030;!-KC`?]\0079d\016~\020} <g+u\016\026OjP.PU/51\020V}#%\023Hhn;\020\037s6JDc^'\020k2%\005yLPf0b\002;b5-\006-\001ly\0319&ydn\006\\\013\016Y~*s\020@|0U !&\030\034R:A{Ayu^4mfGz\020Coc0\035\023NO`(-Z.\013\036V\022\nNB|\000vvs\0138.\031\001] \0208vi. :t`QCM\t7\026k7yMp* \\\020WY\"\0209\024Y Sy|\rF$v\007Ly&*\002=2\035(S\021vL0%Ov2>j\tq%R?PUQ-\030u7'!I4\r0rBX(\007S}h(m\002P9\017\027pDm\004sO7\035V0\000NvP\026S(\007F;.w#4-'\033f+\t\025=]p72(<\035fP\r\032Mw?`n\017do\020Bk_\024%=\005r\020/DX7R\031\020L@\032e\034\020@x4\tID3\004T\0204\032\034!+l\t\r}0\020\0200M'\025mS31\007<8(rt\025r\026V\026wYA\027\006Kg\016Q\025dHm\020\031vx\001\r\020J\020Q\037fQH\020Ju\020<KPB^\034Jf").length();
    byte b2 = 16;
    byte b = -1;
    while (true);
  }
  
  public static void h(String paramString) {
    d = paramString;
  }
  
  public static String e() {
    return d;
  }
  
  private static RuntimeException a(RuntimeException paramRuntimeException) {
    return paramRuntimeException;
  }
  
  private static String a(byte[] paramArrayOfbyte) {
    byte b1 = 0;
    int i;
    char[] arrayOfChar = new char[i = paramArrayOfbyte.length];
    for (byte b2 = 0; b2 < i; b2++) {
      int j;
      if ((j = 0xFF & paramArrayOfbyte[b2]) < 192) {
        arrayOfChar[b1++] = (char)j;
      } else if (j < 224) {
        char c = (char)((char)(j & 0x1F) << 6);
        j = paramArrayOfbyte[++b2];
        c = (char)(c | (char)(j & 0x3F));
        arrayOfChar[b1++] = c;
      } else if (b2 < i - 2) {
        char c = (char)((char)(j & 0xF) << 12);
        j = paramArrayOfbyte[++b2];
        c = (char)(c | (char)(j & 0x3F) << 6);
        j = paramArrayOfbyte[++b2];
        c = (char)(c | (char)(j & 0x3F));
        arrayOfChar[b1++] = c;
      } 
    } 
    return new String(arrayOfChar, 0, b1);
  }
  
  private static String a(int paramInt, long paramLong) {
    int i = paramInt ^ (int)(paramLong & 0x7FFFL) ^ 0x1442;
    if (h[i] == null) {
      Object[] arrayOfObject;
      try {
        Long long_ = Long.valueOf(Thread.currentThread().getId());
        arrayOfObject = (Object[])j.get(long_);
        if (arrayOfObject == null) {
          arrayOfObject = new Object[3];
          arrayOfObject[0] = Cipher.getInstance("DES/CBC/PKCS5Padding");
          arrayOfObject[1] = SecretKeyFactory.getInstance("DES");
          arrayOfObject[2] = new IvParameterSpec(new byte[8]);
          j.put(long_, arrayOfObject);
        } 
      } catch (Exception exception) {
        throw new RuntimeException("me/rerere/matrix/internal/pd", exception);
      } 
      byte[] arrayOfByte1 = new byte[8];
      arrayOfByte1[0] = (byte)(int)(paramLong >>> 56L);
      for (byte b = 1; b < 8; b++)
        arrayOfByte1[b] = (byte)(int)(paramLong << b * 8 >>> 56L); 
      DESKeySpec dESKeySpec = new DESKeySpec(arrayOfByte1);
      SecretKey secretKey = ((SecretKeyFactory)arrayOfObject[1]).generateSecret(dESKeySpec);
      ((Cipher)arrayOfObject[0]).init(2, secretKey, (IvParameterSpec)arrayOfObject[2]);
      byte[] arrayOfByte2 = g[i].getBytes("ISO-8859-1");
      h[i] = a(((Cipher)arrayOfObject[0]).doFinal(arrayOfByte2));
    } 
    return h[i];
  }
  
  private static Object a(MethodHandles.Lookup paramLookup, MutableCallSite paramMutableCallSite, String paramString, Object[] paramArrayOfObject) {
    int i = ((Integer)paramArrayOfObject[0]).intValue();
    long l = ((Long)paramArrayOfObject[1]).longValue();
    String str = a(i, l);
    MethodHandle methodHandle = MethodHandles.constant(String.class, str);
    paramMutableCallSite.setTarget(MethodHandles.dropArguments(methodHandle, 0, new Class[] { int.class, long.class }));
    return str;
  }
  
  private static CallSite a(MethodHandles.Lookup paramLookup, String paramString, MethodType paramMethodType) {
    // Byte code:
    //   0: new java/lang/invoke/MutableCallSite
    //   3: dup
    //   4: aload_2
    //   5: invokespecial <init> : (Ljava/lang/invoke/MethodType;)V
    //   8: astore_3
    //   9: aload_3
    //   10: ldc_w
    //   13: ldc_w [Ljava/lang/Object;
    //   16: aload_2
    //   17: invokevirtual parameterCount : ()I
    //   20: invokevirtual asCollector : (Ljava/lang/Class;I)Ljava/lang/invoke/MethodHandle;
    //   23: iconst_0
    //   24: iconst_3
    //   25: anewarray java/lang/Object
    //   28: dup
    //   29: iconst_0
    //   30: aload_0
    //   31: aastore
    //   32: dup
    //   33: iconst_1
    //   34: aload_3
    //   35: aastore
    //   36: dup
    //   37: iconst_2
    //   38: aload_1
    //   39: aastore
    //   40: invokestatic insertArguments : (Ljava/lang/invoke/MethodHandle;I[Ljava/lang/Object;)Ljava/lang/invoke/MethodHandle;
    //   43: aload_2
    //   44: invokestatic explicitCastArguments : (Ljava/lang/invoke/MethodHandle;Ljava/lang/invoke/MethodType;)Ljava/lang/invoke/MethodHandle;
    //   47: invokevirtual setTarget : (Ljava/lang/invoke/MethodHandle;)V
    //   50: goto -> 104
    //   53: astore #4
    //   55: new java/lang/RuntimeException
    //   58: dup
    //   59: new java/lang/StringBuilder
    //   62: dup
    //   63: invokespecial <init> : ()V
    //   66: ldc_w 'me/rerere/matrix/internal/pd'
    //   69: invokevirtual append : (Ljava/lang/String;)Ljava/lang/StringBuilder;
    //   72: ldc_w ' : '
    //   75: invokevirtual append : (Ljava/lang/String;)Ljava/lang/StringBuilder;
    //   78: aload_1
    //   79: invokevirtual append : (Ljava/lang/String;)Ljava/lang/StringBuilder;
    //   82: ldc_w ' : '
    //   85: invokevirtual append : (Ljava/lang/String;)Ljava/lang/StringBuilder;
    //   88: aload_2
    //   89: invokevirtual toString : ()Ljava/lang/String;
    //   92: invokevirtual append : (Ljava/lang/String;)Ljava/lang/StringBuilder;
    //   95: invokevirtual toString : ()Ljava/lang/String;
    //   98: aload #4
    //   100: invokespecial <init> : (Ljava/lang/String;Ljava/lang/Throwable;)V
    //   103: athrow
    //   104: aload_3
    //   105: areturn
    // Exception table:
    //   from	to	target	type
    //   9	50	53	java/lang/Exception
  }
}


/* Location:              C:\Users\Administrator\Desktop\Matrix_7.0.0_alpha28(3)(1).jar!\me\rerere\matrix\internal\pd.class
 * Java compiler version: 8 (52.0)
 * JD-Core Version:       1.1.3
 */