package me.rerere.matrix.internal;

import java.lang.invoke.CallSite;
import java.lang.invoke.MethodHandle;
import java.lang.invoke.MethodHandles;
import java.lang.invoke.MethodType;
import java.lang.invoke.MutableCallSite;
import java.util.HashMap;
import java.util.Map;
import javax.crypto.Cipher;
import javax.crypto.SecretKey;
import javax.crypto.SecretKeyFactory;
import javax.crypto.spec.DESKeySpec;
import javax.crypto.spec.IvParameterSpec;
import me.rerere.matrix.thirdparty.kotlin.jvm.functions.Function1;
import me.rerere.matrix.thirdparty.kotlin.jvm.internal.Lambda;
import me.rerere.matrix.thirdparty.org.jetbrains.annotations.NotNull;

public final class um extends Lambda implements Function1 {
  public static final um i;
  
  private static final long a = o3.a(-6337091054423338755L, 5441015623445558402L, MethodHandles.lookup().lookupClass()).a(21378495993269L);
  
  private static final String[] b;
  
  private static final String[] d;
  
  private static final Map e = new HashMap<>(13);
  
  @NotNull
  public final CharSequence b(byte paramByte, long paramLong) {
    // Byte code:
    //   0: getstatic me/rerere/matrix/internal/um.a : J
    //   3: lload_2
    //   4: lxor
    //   5: lstore_2
    //   6: sipush #21565
    //   9: ldc2_w 6549335559313216583
    //   12: lload_2
    //   13: lxor
    //   14: <illegal opcode> g : (IJ)Ljava/lang/String;
    //   19: astore #4
    //   21: iconst_1
    //   22: anewarray java/lang/Object
    //   25: astore #5
    //   27: aload #5
    //   29: iconst_0
    //   30: iload_1
    //   31: invokestatic valueOf : (B)Ljava/lang/Byte;
    //   34: aastore
    //   35: aload #5
    //   37: astore #5
    //   39: aload #4
    //   41: aload #5
    //   43: aload #5
    //   45: arraylength
    //   46: invokestatic copyOf : ([Ljava/lang/Object;I)[Ljava/lang/Object;
    //   49: invokestatic format : (Ljava/lang/String;[Ljava/lang/Object;)Ljava/lang/String;
    //   52: dup
    //   53: sipush #29159
    //   56: ldc2_w 2487846294966530460
    //   59: lload_2
    //   60: lxor
    //   61: <illegal opcode> g : (IJ)Ljava/lang/String;
    //   66: invokestatic checkNotNullExpressionValue : (Ljava/lang/Object;Ljava/lang/String;)V
    //   69: checkcast java/lang/CharSequence
    //   72: areturn
  }
  
  static {
    long l = a ^ 0x5BE675F30CABL;
    (new byte[8])[0] = (byte)(int)(l >>> 56L);
    for (byte b1 = 1; b1 < 8; b1++)
      (new byte[8])[b1] = (byte)(int)(l << b1 * 8 >>> 56L); 
    Cipher cipher;
    (cipher = Cipher.getInstance("DES/CBC/PKCS5Padding")).init(2, SecretKeyFactory.getInstance("DES").generateSecret(new DESKeySpec(new byte[8])), new IvParameterSpec(new byte[8]));
    String[] arrayOfString = new String[2];
    boolean bool = false;
    String str;
    int i = (str = "\030=Ii>Rî&¯?Cz¯B(N]:çkxY6ìX@2Jà\003Äá­]l:\002 Ì1;å¾ýçp\035<").length();
    byte b2 = 16;
    byte b = -1;
    while (true);
  }
  
  public um() {
    super(1);
  }
  
  private static String a(byte[] paramArrayOfbyte) {
    byte b1 = 0;
    int i;
    char[] arrayOfChar = new char[i = paramArrayOfbyte.length];
    for (byte b2 = 0; b2 < i; b2++) {
      int j;
      if ((j = 0xFF & paramArrayOfbyte[b2]) < 192) {
        arrayOfChar[b1++] = (char)j;
      } else if (j < 224) {
        char c = (char)((char)(j & 0x1F) << 6);
        j = paramArrayOfbyte[++b2];
        c = (char)(c | (char)(j & 0x3F));
        arrayOfChar[b1++] = c;
      } else if (b2 < i - 2) {
        char c = (char)((char)(j & 0xF) << 12);
        j = paramArrayOfbyte[++b2];
        c = (char)(c | (char)(j & 0x3F) << 6);
        j = paramArrayOfbyte[++b2];
        c = (char)(c | (char)(j & 0x3F));
        arrayOfChar[b1++] = c;
      } 
    } 
    return new String(arrayOfChar, 0, b1);
  }
  
  private static String a(int paramInt, long paramLong) {
    int i = paramInt ^ (int)(paramLong & 0x7FFFL) ^ 0x65EE;
    if (d[i] == null) {
      Object[] arrayOfObject;
      try {
        Long long_ = Long.valueOf(Thread.currentThread().getId());
        arrayOfObject = (Object[])e.get(long_);
        if (arrayOfObject == null) {
          arrayOfObject = new Object[3];
          arrayOfObject[0] = Cipher.getInstance("DES/CBC/PKCS5Padding");
          arrayOfObject[1] = SecretKeyFactory.getInstance("DES");
          arrayOfObject[2] = new IvParameterSpec(new byte[8]);
          e.put(long_, arrayOfObject);
        } 
      } catch (Exception exception) {
        throw new RuntimeException("me/rerere/matrix/internal/um", exception);
      } 
      byte[] arrayOfByte1 = new byte[8];
      arrayOfByte1[0] = (byte)(int)(paramLong >>> 56L);
      for (byte b = 1; b < 8; b++)
        arrayOfByte1[b] = (byte)(int)(paramLong << b * 8 >>> 56L); 
      DESKeySpec dESKeySpec = new DESKeySpec(arrayOfByte1);
      SecretKey secretKey = ((SecretKeyFactory)arrayOfObject[1]).generateSecret(dESKeySpec);
      ((Cipher)arrayOfObject[0]).init(2, secretKey, (IvParameterSpec)arrayOfObject[2]);
      byte[] arrayOfByte2 = b[i].getBytes("ISO-8859-1");
      d[i] = a(((Cipher)arrayOfObject[0]).doFinal(arrayOfByte2));
    } 
    return d[i];
  }
  
  private static Object a(MethodHandles.Lookup paramLookup, MutableCallSite paramMutableCallSite, String paramString, Object[] paramArrayOfObject) {
    int i = ((Integer)paramArrayOfObject[0]).intValue();
    long l = ((Long)paramArrayOfObject[1]).longValue();
    String str = a(i, l);
    MethodHandle methodHandle = MethodHandles.constant(String.class, str);
    paramMutableCallSite.setTarget(MethodHandles.dropArguments(methodHandle, 0, new Class[] { int.class, long.class }));
    return str;
  }
  
  private static CallSite a(MethodHandles.Lookup paramLookup, String paramString, MethodType paramMethodType) {
    // Byte code:
    //   0: new java/lang/invoke/MutableCallSite
    //   3: dup
    //   4: aload_2
    //   5: invokespecial <init> : (Ljava/lang/invoke/MethodType;)V
    //   8: astore_3
    //   9: aload_3
    //   10: ldc_w
    //   13: ldc [Ljava/lang/Object;
    //   15: aload_2
    //   16: invokevirtual parameterCount : ()I
    //   19: invokevirtual asCollector : (Ljava/lang/Class;I)Ljava/lang/invoke/MethodHandle;
    //   22: iconst_0
    //   23: iconst_3
    //   24: anewarray java/lang/Object
    //   27: dup
    //   28: iconst_0
    //   29: aload_0
    //   30: aastore
    //   31: dup
    //   32: iconst_1
    //   33: aload_3
    //   34: aastore
    //   35: dup
    //   36: iconst_2
    //   37: aload_1
    //   38: aastore
    //   39: invokestatic insertArguments : (Ljava/lang/invoke/MethodHandle;I[Ljava/lang/Object;)Ljava/lang/invoke/MethodHandle;
    //   42: aload_2
    //   43: invokestatic explicitCastArguments : (Ljava/lang/invoke/MethodHandle;Ljava/lang/invoke/MethodType;)Ljava/lang/invoke/MethodHandle;
    //   46: invokevirtual setTarget : (Ljava/lang/invoke/MethodHandle;)V
    //   49: goto -> 102
    //   52: astore #4
    //   54: new java/lang/RuntimeException
    //   57: dup
    //   58: new java/lang/StringBuilder
    //   61: dup
    //   62: invokespecial <init> : ()V
    //   65: ldc 'me/rerere/matrix/internal/um'
    //   67: invokevirtual append : (Ljava/lang/String;)Ljava/lang/StringBuilder;
    //   70: ldc_w ' : '
    //   73: invokevirtual append : (Ljava/lang/String;)Ljava/lang/StringBuilder;
    //   76: aload_1
    //   77: invokevirtual append : (Ljava/lang/String;)Ljava/lang/StringBuilder;
    //   80: ldc_w ' : '
    //   83: invokevirtual append : (Ljava/lang/String;)Ljava/lang/StringBuilder;
    //   86: aload_2
    //   87: invokevirtual toString : ()Ljava/lang/String;
    //   90: invokevirtual append : (Ljava/lang/String;)Ljava/lang/StringBuilder;
    //   93: invokevirtual toString : ()Ljava/lang/String;
    //   96: aload #4
    //   98: invokespecial <init> : (Ljava/lang/String;Ljava/lang/Throwable;)V
    //   101: athrow
    //   102: aload_3
    //   103: areturn
    // Exception table:
    //   from	to	target	type
    //   9	49	52	java/lang/Exception
  }
}


/* Location:              C:\Users\Administrator\Desktop\Matrix_7.0.0_alpha28(3)(1).jar!\me\rerere\matrix\interna\\um.class
 * Java compiler version: 8 (52.0)
 * JD-Core Version:       1.1.3
 */